Workbook

Sheet Erklärungen
B1: Erläuterungen zur Korrelationstabelle
B2: Stand 01.02.2025
B4: Tabelle Transformation | D4: Beschreibt den Übergang von DM.01-AV-CH nach DMAV Version 1.0 und umgekehrt.
A5: Nr. | B5: Spalte | C5: Titel | D5: Inhalt
A6: 10 | B6: =IF(A6="","",IF(ISERROR(SUBSTITUTE(ADDRESS(1,A6,4,1),"1","")),"",SUBSTITUTE(ADDRESS(1,A6,4,1),"1",""))) -> J | C6: {=IF(A6="","",IF(ISERROR(INDEX(Transformation!$A$5:$AT$5,A6)),"",INDEX(Transformation!$A$5:$AT$5,A6)))} -> Link | D6: Hyperlink zum entsprechenden Modell oder Dienst im DMAV Version 1.0
A7: 11 | B7: =IF(A7="","",IF(ISERROR(SUBSTITUTE(ADDRESS(1,A7,4,1),"1","")),"",SUBSTITUTE(ADDRESS(1,A7,4,1),"1",""))) -> K | C7: {=IF(A7="","",IF(ISERROR(INDEX(Transformation!$A$5:$AT$5,A7)),"",INDEX(Transformation!$A$5:$AT$5,A7)))} -> Typ | D7: Art des Elements (Domain, Klasse, Wertebereich etc.)
A8: 12 | B8: =IF(A8="","",IF(ISERROR(SUBSTITUTE(ADDRESS(1,A8,4,1),"1","")),"",SUBSTITUTE(ADDRESS(1,A8,4,1),"1",""))) -> L | C8: {=IF(A8="","",IF(ISERROR(INDEX(Transformation!$A$5:$AT$5,A8)),"",INDEX(Transformation!$A$5:$AT$5,A8)))} -> Topic | D8: Thema / Topic
A9: 13 | B9: =IF(A9="","",IF(ISERROR(SUBSTITUTE(ADDRESS(1,A9,4,1),"1","")),"",SUBSTITUTE(ADDRESS(1,A9,4,1),"1",""))) -> M | C9: {=IF(A9="","",IF(ISERROR(INDEX(Transformation!$A$5:$AT$5,A9)),"",INDEX(Transformation!$A$5:$AT$5,A9)))} -> Class | D9: Benennung des Elements (Domain, Klasse, Wertebereichs etc.)
A10: 14 | B10: =IF(A10="","",IF(ISERROR(SUBSTITUTE(ADDRESS(1,A10,4,1),"1","")),"",SUBSTITUTE(ADDRESS(1,A10,4,1),"1",""))) -> N | C10: {=IF(A10="","",IF(ISERROR(INDEX(Transformation!$A$5:$AT$5,A10)),"",INDEX(Transformation!$A$5:$AT$5,A10)))} -> Attribut | D10: Attributname / Attributsbezeichnung
A11: 15 | B11: =IF(A11="","",IF(ISERROR(SUBSTITUTE(ADDRESS(1,A11,4,1),"1","")),"",SUBSTITUTE(ADDRESS(1,A11,4,1),"1",""))) -> O | C11: {=IF(A11="","",IF(ISERROR(INDEX(Transformation!$A$5:$AT$5,A11)),"",INDEX(Transformation!$A$5:$AT$5,A11)))} -> Structure | D11: Hyperlink zur Definition der Struktur des entsprechenden Attributs
A12: 16 | B12: =IF(A12="","",IF(ISERROR(SUBSTITUTE(ADDRESS(1,A12,4,1),"1","")),"",SUBSTITUTE(ADDRESS(1,A12,4,1),"1",""))) -> P | C12: {=IF(A12="","",IF(ISERROR(INDEX(Transformation!$A$5:$AT$5,A12)),"",INDEX(Transformation!$A$5:$AT$5,A12)))} -> Substruct | D12: Hyperlink zur Definition der Unterstruktur der entsprechenden Struktur
A13: 18 | B13: =IF(A13="","",IF(ISERROR(SUBSTITUTE(ADDRESS(1,A13,4,1),"1","")),"",SUBSTITUTE(ADDRESS(1,A13,4,1),"1",""))) -> R | C13: {=IF(A13="","",IF(ISERROR(INDEX(Transformation!$A$5:$AT$5,A13)),"",INDEX(Transformation!$A$5:$AT$5,A13)))} -> Bemerkung | D13: Defaultwert oder Mapping der Werte beim Übergang von DM.01-AV-CH nach DMAV Version 1.0
A14: 20 | B14: =IF(A14="","",IF(ISERROR(SUBSTITUTE(ADDRESS(1,A14,4,1),"1","")),"",SUBSTITUTE(ADDRESS(1,A14,4,1),"1",""))) -> T | C14: {=IF(A14="","",IF(ISERROR(INDEX(Transformation!$A$5:$AT$5,A14)),"",INDEX(Transformation!$A$5:$AT$5,A14)))} -> Bedingung / Voraussetzung in DM.01-AV-CH | D14: Bedingung im DM.01-AV-CH damit das Attribut / der Datensatz ins DMAV Version 1.0 übertragen wird
A15: 21 | B15: =IF(A15="","",IF(ISERROR(SUBSTITUTE(ADDRESS(1,A15,4,1),"1","")),"",SUBSTITUTE(ADDRESS(1,A15,4,1),"1",""))) -> U | C15: {=IF(A15="","",IF(ISERROR(INDEX(Transformation!$A$5:$AT$5,A15)),"",INDEX(Transformation!$A$5:$AT$5,A15)))} -> T | D15: Art der Transformation: K = kopieren V = verschieben
A16: 22 | B16: =IF(A16="","",IF(ISERROR(SUBSTITUTE(ADDRESS(1,A16,4,1),"1","")),"",SUBSTITUTE(ADDRESS(1,A16,4,1),"1",""))) -> V | C16: {=IF(A16="","",IF(ISERROR(INDEX(Transformation!$A$5:$AT$5,A16)),"",INDEX(Transformation!$A$5:$AT$5,A16)))} -> Klasse | D16: In welche Klasse, welches Attribut sind die Daten vom DM.01-AV-CH nach DMAV Version 1.0 zu überführen?
A17: 23 | B17: =IF(A17="","",IF(ISERROR(SUBSTITUTE(ADDRESS(1,A17,4,1),"1","")),"",SUBSTITUTE(ADDRESS(1,A17,4,1),"1",""))) -> W | C17: {=IF(A17="","",IF(ISERROR(INDEX(Transformation!$A$5:$AT$5,A17)),"",INDEX(Transformation!$A$5:$AT$5,A17)))} -> Ergänzung | D17: Wie sind die als MANDATORY bezeichneten Attribute im DMAV Version 1.0 zu ergänzen, sodass das Objekt konsistent im DMAV Version 1.0 abgebildet wird
... A26: 35 | B26: =IF(A26="","",IF(ISERROR(SUBSTITUTE(ADDRESS(1,A26,4,1),"1","")),"",SUBSTITUTE(ADDRESS(1,A26,4,1),"1",""))) -> AI | C26: {=IF(A26="","",IF(ISERROR(INDEX(Transformation!$A$5:$AT$5,A26)),"",INDEX(Transformation!$A$5:$AT$5,A26)))} -> Attribut | D26: Attributname / Attributsbezeichnung
B28: Tabelle DMAV_Doku | D28: Enthält den Objektkatalog aus den Modelldokumentationen.
B29: Spalte | C29: Titel | D29: Inhalt
A30: 1 | B30: =IF(A30="","",IF(ISERROR(SUBSTITUTE(ADDRESS(1,A30,4,1),"1","")),"",SUBSTITUTE(ADDRESS(1,A30,4,1),"1",""))) -> A | C30: {=IF(A30="","",IF(ISERROR(INDEX(DMAV_Doku!$A$5:$AH$5,A30)),"",INDEX(DMAV_Doku!$A$5:$AH$5,A30)))} -> Dok | D30: Kürzel für das Geodatenmodell
A31: 2 | B31: =IF(A31="","",IF(ISERROR(SUBSTITUTE(ADDRESS(1,A31,4,1),"1","")),"",SUBSTITUTE(ADDRESS(1,A31,4,1),"1",""))) -> B | C31: {=IF(A31="","",IF(ISERROR(INDEX(DMAV_Doku!$A$5:$AH$5,A31)),"",INDEX(DMAV_Doku!$A$5:$AH$5,A31)))} -> Nr. | D31: Zeilennummer
A32: 3 | B32: =IF(A32="","",IF(ISERROR(SUBSTITUTE(ADDRESS(1,A32,4,1),"1","")),"",SUBSTITUTE(ADDRESS(1,A32,4,1),"1",""))) -> C | C32: {=IF(A32="","",IF(ISERROR(INDEX(DMAV_Doku!$A$5:$AH$5,A32)),"",INDEX(DMAV_Doku!$A$5:$AH$5,A32)))} -> Typ | D32: Art des Elements (Domain, Klasse, Wertebereich etc.)
A33: 4 | B33: =IF(A33="","",IF(ISERROR(SUBSTITUTE(ADDRESS(1,A33,4,1),"1","")),"",SUBSTITUTE(ADDRESS(1,A33,4,1),"1",""))) -> D | C33: {=IF(A33="","",IF(ISERROR(INDEX(DMAV_Doku!$A$5:$AH$5,A33)),"",INDEX(DMAV_Doku!$A$5:$AH$5,A33)))} -> MAN. | D33: MANDATORY, sind Daten zu diesem Attribut zu erfassen: 0..1 = optional (nicht MANDATORY) 1 = obligatorisch (MANDATORY)
A34: 6 | B34: =IF(A34="","",IF(ISERROR(SUBSTITUTE(ADDRESS(1,A34,4,1),"1","")),"",SUBSTITUTE(ADDRESS(1,A34,4,1),"1",""))) -> F | C34: {=IF(A34="","",IF(ISERROR(INDEX(DMAV_Doku!$A$5:$AH$5,A34)),"",INDEX(DMAV_Doku!$A$5:$AH$5,A34)))} -> Domain | D34: Hyperlink zur Definition des Wertebereichs des entsprechenden Attributs
A35: 7 | B35: =IF(A35="","",IF(ISERROR(SUBSTITUTE(ADDRESS(1,A35,4,1),"1","")),"",SUBSTITUTE(ADDRESS(1,A35,4,1),"1",""))) -> G | C35: {=IF(A35="","",IF(ISERROR(INDEX(DMAV_Doku!$A$5:$AH$5,A35)),"",INDEX(DMAV_Doku!$A$5:$AH$5,A35)))} -> Modell | D35: Hyperlink zum entsprechenden Attribut, Struktur, Wertebereich im DMAV Version 1.0
A36: 12 | B36: =IF(A36="","",IF(ISERROR(SUBSTITUTE(ADDRESS(1,A36,4,1),"1","")),"",SUBSTITUTE(ADDRESS(1,A36,4,1),"1",""))) -> L | C36: {=IF(A36="","",IF(ISERROR(INDEX(DMAV_Doku!$A$5:$AH$5,A36)),"",INDEX(DMAV_Doku!$A$5:$AH$5,A36)))} -> Dokument | D36: Name der deutschen Modelldokumentation, in welcher das Attribut, der Wertebereich beschrieben ist
A37: 13 | B37: =IF(A37="","",IF(ISERROR(SUBSTITUTE(ADDRESS(1,A37,4,1),"1","")),"",SUBSTITUTE(ADDRESS(1,A37,4,1),"1",""))) -> M | C37: {=IF(A37="","",IF(ISERROR(INDEX(DMAV_Doku!$A$5:$AH$5,A37)),"",INDEX(DMAV_Doku!$A$5:$AH$5,A37)))} -> Name | D37: Name der Klasse (deutsch)
A38: 14 | B38: =IF(A38="","",IF(ISERROR(SUBSTITUTE(ADDRESS(1,A38,4,1),"1","")),"",SUBSTITUTE(ADDRESS(1,A38,4,1),"1",""))) -> N | C38: {=IF(A38="","",IF(ISERROR(INDEX(DMAV_Doku!$A$5:$AH$5,A38)),"",INDEX(DMAV_Doku!$A$5:$AH$5,A38)))} -> Attribut | D38: Name des Attributs (deutsch)
A39: 15 | B39: =IF(A39="","",IF(ISERROR(SUBSTITUTE(ADDRESS(1,A39,4,1),"1","")),"",SUBSTITUTE(ADDRESS(1,A39,4,1),"1",""))) -> O | C39: {=IF(A39="","",IF(ISERROR(INDEX(DMAV_Doku!$A$5:$AH$5,A39)),"",INDEX(DMAV_Doku!$A$5:$AH$5,A39)))} -> Wert | D39: Wertebereich des Attributs
A40: 16 | B40: =IF(A40="","",IF(ISERROR(SUBSTITUTE(ADDRESS(1,A40,4,1),"1","")),"",SUBSTITUTE(ADDRESS(1,A40,4,1),"1",""))) -> P | C40: {=IF(A40="","",IF(ISERROR(INDEX(DMAV_Doku!$A$5:$AH$5,A40)),"",INDEX(DMAV_Doku!$A$5:$AH$5,A40)))} -> Default | D40: Defaultwert für das Attribut
A41: 17 | B41: =IF(A41="","",IF(ISERROR(SUBSTITUTE(ADDRESS(1,A41,4,1),"1","")),"",SUBSTITUTE(ADDRESS(1,A41,4,1),"1",""))) -> Q | C41: {=IF(A41="","",IF(ISERROR(INDEX(DMAV_Doku!$A$5:$AH$5,A41)),"",INDEX(DMAV_Doku!$A$5:$AH$5,A41)))} -> Beschreibung | D41: Beschreibung des Attributs gemäss Modelldokumentation (deutsch)
... A56: 34 | B56: =IF(A56="","",IF(ISERROR(SUBSTITUTE(ADDRESS(1,A56,4,1),"1","")),"",SUBSTITUTE(ADDRESS(1,A56,4,1),"1",""))) -> AH | C56: {=IF(A56="","",IF(ISERROR(INDEX(DMAV_Doku!$A$5:$AH$5,A56)),"",INDEX(DMAV_Doku!$A$5:$AH$5,A56)))} -> Commento | D56: Commento all'attributo / requisiti per la modellazione dei dati secondo la documentazione del modello (in italiano)
B58: Tabelle DMAV_Modell | D58: Enthält den Objektkatalog aus der Modellbeschreibung in INTERLIS 2.4.
B59: Spalte | C59: Titel | D59: Inhalt
A60: 1 | B60: =IF(A60="","",IF(ISERROR(SUBSTITUTE(ADDRESS(1,A60,4,1),"1","")),"",SUBSTITUTE(ADDRESS(1,A60,4,1),"1",""))) -> A | C60: {=IF(A60="","",IF(ISERROR(INDEX(DMAV_Modell!$A$5:$BB$5,A60)),"",INDEX(DMAV_Modell!$A$5:$BB$5,A60)))} -> Modell | D60: Kürzel für das Geodatenmodell
A61: 2 | B61: =IF(A61="","",IF(ISERROR(SUBSTITUTE(ADDRESS(1,A61,4,1),"1","")),"",SUBSTITUTE(ADDRESS(1,A61,4,1),"1",""))) -> B | C61: {=IF(A61="","",IF(ISERROR(INDEX(DMAV_Modell!$A$5:$BB$5,A61)),"",INDEX(DMAV_Modell!$A$5:$BB$5,A61)))} -> Nr | D61: Zeilennummer
A62: 4 | B62: =IF(A62="","",IF(ISERROR(SUBSTITUTE(ADDRESS(1,A62,4,1),"1","")),"",SUBSTITUTE(ADDRESS(1,A62,4,1),"1",""))) -> D | C62: {=IF(A62="","",IF(ISERROR(INDEX(DMAV_Modell!$A$5:$BB$5,A62)),"",INDEX(DMAV_Modell!$A$5:$BB$5,A62)))} -> CheckID | D62: Identifikator der Bedingung (Constraint)
A63: 5 | B63: =IF(A63="","",IF(ISERROR(SUBSTITUTE(ADDRESS(1,A63,4,1),"1","")),"",SUBSTITUTE(ADDRESS(1,A63,4,1),"1",""))) -> E | C63: {=IF(A63="","",IF(ISERROR(INDEX(DMAV_Modell!$A$5:$BB$5,A63)),"",INDEX(DMAV_Modell!$A$5:$BB$5,A63)))} -> Domain | D63: Hyperlink zur Definition des Wertebereichs des entsprechenden Attributs
A64: 6 | B64: =IF(A64="","",IF(ISERROR(SUBSTITUTE(ADDRESS(1,A64,4,1),"1","")),"",SUBSTITUTE(ADDRESS(1,A64,4,1),"1",""))) -> F | C64: {=IF(A64="","",IF(ISERROR(INDEX(DMAV_Modell!$A$5:$BB$5,A64)),"",INDEX(DMAV_Modell!$A$5:$BB$5,A64)))} -> Doku | D64: Hyperlink zur entsprechenden Beschreibung in der Modelldokumentation
A65: 11 | B65: =IF(A65="","",IF(ISERROR(SUBSTITUTE(ADDRESS(1,A65,4,1),"1","")),"",SUBSTITUTE(ADDRESS(1,A65,4,1),"1",""))) -> K | C65: {=IF(A65="","",IF(ISERROR(INDEX(DMAV_Modell!$A$5:$BB$5,A65)),"",INDEX(DMAV_Modell!$A$5:$BB$5,A65)))} -> Neu | D65: Datum der Einführung oder der Ergänzung des Elements
A66: 12 | B66: =IF(A66="","",IF(ISERROR(SUBSTITUTE(ADDRESS(1,A66,4,1),"1","")),"",SUBSTITUTE(ADDRESS(1,A66,4,1),"1",""))) -> L | C66: {=IF(A66="","",IF(ISERROR(INDEX(DMAV_Modell!$A$5:$BB$5,A66)),"",INDEX(DMAV_Modell!$A$5:$BB$5,A66)))} -> Gelöscht | D66: Datum der Löschung des Elements
A67: 14 | B67: =IF(A67="","",IF(ISERROR(SUBSTITUTE(ADDRESS(1,A67,4,1),"1","")),"",SUBSTITUTE(ADDRESS(1,A67,4,1),"1",""))) -> N | C67: {=IF(A67="","",IF(ISERROR(INDEX(DMAV_Modell!$A$5:$BB$5,A67)),"",INDEX(DMAV_Modell!$A$5:$BB$5,A67)))} -> Datei | D67: Dateiname der Modellbeschreibung in INTERLIS 2.4
A68: 15 | B68: =IF(A68="","",IF(ISERROR(SUBSTITUTE(ADDRESS(1,A68,4,1),"1","")),"",SUBSTITUTE(ADDRESS(1,A68,4,1),"1",""))) -> O | C68: {=IF(A68="","",IF(ISERROR(INDEX(DMAV_Modell!$A$5:$BB$5,A68)),"",INDEX(DMAV_Modell!$A$5:$BB$5,A68)))} -> Modell | D68: Name des Modells gemäss Modellbeschreibung in INTERLIS 2.4
A69: 16 | B69: =IF(A69="","",IF(ISERROR(SUBSTITUTE(ADDRESS(1,A69,4,1),"1","")),"",SUBSTITUTE(ADDRESS(1,A69,4,1),"1",""))) -> P | C69: {=IF(A69="","",IF(ISERROR(INDEX(DMAV_Modell!$A$5:$BB$5,A69)),"",INDEX(DMAV_Modell!$A$5:$BB$5,A69)))} -> Topic | D69: Thema / Topic
A70: 17 | B70: =IF(A70="","",IF(ISERROR(SUBSTITUTE(ADDRESS(1,A70,4,1),"1","")),"",SUBSTITUTE(ADDRESS(1,A70,4,1),"1",""))) -> Q | C70: {=IF(A70="","",IF(ISERROR(INDEX(DMAV_Modell!$A$5:$BB$5,A70)),"",INDEX(DMAV_Modell!$A$5:$BB$5,A70)))} -> Typ | D70: Art des Elements (Domain, Klasse, Wertebereich etc.)
A71: 18 | B71: =IF(A71="","",IF(ISERROR(SUBSTITUTE(ADDRESS(1,A71,4,1),"1","")),"",SUBSTITUTE(ADDRESS(1,A71,4,1),"1",""))) -> R | C71: {=IF(A71="","",IF(ISERROR(INDEX(DMAV_Modell!$A$5:$BB$5,A71)),"",INDEX(DMAV_Modell!$A$5:$BB$5,A71)))} -> Name | D71: Name des Elements (Attribut, Struktur)
... A105: 54 | B105: =IF(A105="","",IF(ISERROR(SUBSTITUTE(ADDRESS(1,A105,4,1),"1","")),"",SUBSTITUTE(ADDRESS(1,A105,4,1),"1",""))) -> BB | C105: {=IF(A105="","",IF(ISERROR(INDEX(DMAV_Modell!$A$5:$BB$5,A105)),"",INDEX(DMAV_Modell!$A$5:$BB$5,A105)))} -> Dichiarazioni | D105: Esplicazione della condizione (Constraint)
B107: Tabelle DMAV_Dienste | D107: Enthält den Objektkatalog aus der Modellbeschreibung in INTERLIS 2.4.
B108: Spalte | C108: Titel | D108: Inhalt
A109: 1 | B109: =IF(A109="","",IF(ISERROR(SUBSTITUTE(ADDRESS(1,A109,4,1),"1","")),"",SUBSTITUTE(ADDRESS(1,A109,4,1),"1",""))) -> A | C109: {=IF(A109="","",IF(ISERROR(INDEX(DMAV_Dienste!$A$5:$BA$5,A109)),"",INDEX(DMAV_Dienste!$A$5:$BA$5,A109)))} -> Modell | D109: Kürzel für das Geodatenmodell
A110: 2 | B110: =IF(A110="","",IF(ISERROR(SUBSTITUTE(ADDRESS(1,A110,4,1),"1","")),"",SUBSTITUTE(ADDRESS(1,A110,4,1),"1",""))) -> B | C110: {=IF(A110="","",IF(ISERROR(INDEX(DMAV_Dienste!$A$5:$BA$5,A110)),"",INDEX(DMAV_Dienste!$A$5:$BA$5,A110)))} -> Nr | D110: Zeilennummer
A111: 4 | B111: =IF(A111="","",IF(ISERROR(SUBSTITUTE(ADDRESS(1,A111,4,1),"1","")),"",SUBSTITUTE(ADDRESS(1,A111,4,1),"1",""))) -> D | C111: {=IF(A111="","",IF(ISERROR(INDEX(DMAV_Dienste!$A$5:$BA$5,A111)),"",INDEX(DMAV_Dienste!$A$5:$BA$5,A111)))} -> CheckID | D111: Identifikator der Bedingung (Constraint)
A112: 5 | B112: =IF(A112="","",IF(ISERROR(SUBSTITUTE(ADDRESS(1,A112,4,1),"1","")),"",SUBSTITUTE(ADDRESS(1,A112,4,1),"1",""))) -> E | C112: {=IF(A112="","",IF(ISERROR(INDEX(DMAV_Dienste!$A$5:$BA$5,A112)),"",INDEX(DMAV_Dienste!$A$5:$BA$5,A112)))} -> Domain | D112: Hyperlink zur Definition des Wertebereichs des entsprechenden Attributs
A113: 10 | B113: =IF(A113="","",IF(ISERROR(SUBSTITUTE(ADDRESS(1,A113,4,1),"1","")),"",SUBSTITUTE(ADDRESS(1,A113,4,1),"1",""))) -> J | C113: {=IF(A113="","",IF(ISERROR(INDEX(DMAV_Dienste!$A$5:$BA$5,A113)),"",INDEX(DMAV_Dienste!$A$5:$BA$5,A113)))} -> neu | D113: Datum der Einführung oder der Ergänzung des Elements
A114: 11 | B114: =IF(A114="","",IF(ISERROR(SUBSTITUTE(ADDRESS(1,A114,4,1),"1","")),"",SUBSTITUTE(ADDRESS(1,A114,4,1),"1",""))) -> K | C114: {=IF(A114="","",IF(ISERROR(INDEX(DMAV_Dienste!$A$5:$BA$5,A114)),"",INDEX(DMAV_Dienste!$A$5:$BA$5,A114)))} -> gelöscht | D114: Datum der Löschung des Elements
A115: 13 | B115: =IF(A115="","",IF(ISERROR(SUBSTITUTE(ADDRESS(1,A115,4,1),"1","")),"",SUBSTITUTE(ADDRESS(1,A115,4,1),"1",""))) -> M | C115: {=IF(A115="","",IF(ISERROR(INDEX(DMAV_Dienste!$A$5:$BA$5,A115)),"",INDEX(DMAV_Dienste!$A$5:$BA$5,A115)))} -> Datei | D115: Dateiname der Modellbeschreibung in INTERLIS 2.4
A116: 14 | B116: =IF(A116="","",IF(ISERROR(SUBSTITUTE(ADDRESS(1,A116,4,1),"1","")),"",SUBSTITUTE(ADDRESS(1,A116,4,1),"1",""))) -> N | C116: {=IF(A116="","",IF(ISERROR(INDEX(DMAV_Dienste!$A$5:$BA$5,A116)),"",INDEX(DMAV_Dienste!$A$5:$BA$5,A116)))} -> Modell | D116: Name des Modells gemäss Modellbeschreibung in INTERLIS 2.4
A117: 15 | B117: =IF(A117="","",IF(ISERROR(SUBSTITUTE(ADDRESS(1,A117,4,1),"1","")),"",SUBSTITUTE(ADDRESS(1,A117,4,1),"1",""))) -> O | C117: {=IF(A117="","",IF(ISERROR(INDEX(DMAV_Dienste!$A$5:$BA$5,A117)),"",INDEX(DMAV_Dienste!$A$5:$BA$5,A117)))} -> Topic | D117: Thema / Topic
A118: 16 | B118: =IF(A118="","",IF(ISERROR(SUBSTITUTE(ADDRESS(1,A118,4,1),"1","")),"",SUBSTITUTE(ADDRESS(1,A118,4,1),"1",""))) -> P | C118: {=IF(A118="","",IF(ISERROR(INDEX(DMAV_Dienste!$A$5:$BA$5,A118)),"",INDEX(DMAV_Dienste!$A$5:$BA$5,A118)))} -> Typ | D118: Art des Elements (Domain, Klasse, Wertebereich etc.)
A119: 17 | B119: =IF(A119="","",IF(ISERROR(SUBSTITUTE(ADDRESS(1,A119,4,1),"1","")),"",SUBSTITUTE(ADDRESS(1,A119,4,1),"1",""))) -> Q | C119: {=IF(A119="","",IF(ISERROR(INDEX(DMAV_Dienste!$A$5:$BA$5,A119)),"",INDEX(DMAV_Dienste!$A$5:$BA$5,A119)))} -> Name | D119: Name des Elements (Attribut, Struktur)
A120: 18 | B120: =IF(A120="","",IF(ISERROR(SUBSTITUTE(ADDRESS(1,A120,4,1),"1","")),"",SUBSTITUTE(ADDRESS(1,A120,4,1),"1",""))) -> R | C120: {=IF(A120="","",IF(ISERROR(INDEX(DMAV_Dienste!$A$5:$BA$5,A120)),"",INDEX(DMAV_Dienste!$A$5:$BA$5,A120)))} -> MAN. | D120: MANDATORY, sind Daten zu diesem Objekt zu erfassen: Empty = optional (nicht MANDATORY) x = obligatorisch (MANDATORY)
... A153: 53 | B153: =IF(A153="","",IF(ISERROR(SUBSTITUTE(ADDRESS(1,A153,4,1),"1","")),"",SUBSTITUTE(ADDRESS(1,A153,4,1),"1",""))) -> BA | C153: {=IF(A153="","",IF(ISERROR(INDEX(DMAV_Dienste!$A$5:$BA$5,A153)),"",INDEX(DMAV_Dienste!$A$5:$BA$5,A153)))} -> Dichiarazioni | D153: Esplicazione della condizione (Constraint)
B155: Tabelle DM01-AV-CH | D155: Enthält die Definition des Modells DM.01-AV-CH in INTERLIS 1.
B156: Spalte | C156: Titel | D156: Inhalt
A157: 1 | B157: =IF(A157="","",IF(ISERROR(SUBSTITUTE(ADDRESS(1,A157,4,1),"1","")),"",SUBSTITUTE(ADDRESS(1,A157,4,1),"1",""))) -> A | C157: {=IF(A157="","",IF(ISERROR(INDEX('DM01-AV-CH'!$A$5:$AZ$5,A157)),"",INDEX('DM01-AV-CH'!$A$5:$AZ$5,A157)))} -> Nr. | D157: Zeilennummer
A158: 2 | B158: =IF(A158="","",IF(ISERROR(SUBSTITUTE(ADDRESS(1,A158,4,1),"1","")),"",SUBSTITUTE(ADDRESS(1,A158,4,1),"1",""))) -> B | C158: {=IF(A158="","",IF(ISERROR(INDEX('DM01-AV-CH'!$A$5:$AZ$5,A158)),"",INDEX('DM01-AV-CH'!$A$5:$AZ$5,A158)))} -> ID | D158: Attribut ist (Teil des) Identifikators: ID = Attribut ist Identifikator ID+ = Attribut ist in Kombination mit anderen Attributen Identifikator
A159: 3 | B159: =IF(A159="","",IF(ISERROR(SUBSTITUTE(ADDRESS(1,A159,4,1),"1","")),"",SUBSTITUTE(ADDRESS(1,A159,4,1),"1",""))) -> C | C159: {=IF(A159="","",IF(ISERROR(INDEX('DM01-AV-CH'!$A$5:$AZ$5,A159)),"",INDEX('DM01-AV-CH'!$A$5:$AZ$5,A159)))} -> FK | D159: Attribut ist Fremdschlüssel: Empty = kein Fremdschlüssel x = Fremdschlüssel
A160: 4 | B160: =IF(A160="","",IF(ISERROR(SUBSTITUTE(ADDRESS(1,A160,4,1),"1","")),"",SUBSTITUTE(ADDRESS(1,A160,4,1),"1",""))) -> D | C160: {=IF(A160="","",IF(ISERROR(INDEX('DM01-AV-CH'!$A$5:$AZ$5,A160)),"",INDEX('DM01-AV-CH'!$A$5:$AZ$5,A160)))} -> Opt. | D160: MANDATORY, sind Daten zu diesem Objekt zu erfassen: Empty = optional (nicht MANDATORY) x = obligatorisch (MANDATORY)
A161: 5 | B161: =IF(A161="","",IF(ISERROR(SUBSTITUTE(ADDRESS(1,A161,4,1),"1","")),"",SUBSTITUTE(ADDRESS(1,A161,4,1),"1",""))) -> E | C161: {=IF(A161="","",IF(ISERROR(INDEX('DM01-AV-CH'!$A$5:$AZ$5,A161)),"",INDEX('DM01-AV-CH'!$A$5:$AZ$5,A161)))} -> ADK | D161: Attribut, Definition, Kommentar: Handelt es sich beim vorliegenden Eintrag um ein Attribut, eine Definiton oder um einen Kommentar
A162: 7 | B162: =IF(A162="","",IF(ISERROR(SUBSTITUTE(ADDRESS(1,A162,4,1),"1","")),"",SUBSTITUTE(ADDRESS(1,A162,4,1),"1",""))) -> G | C162: {=IF(A162="","",IF(ISERROR(INDEX('DM01-AV-CH'!$A$5:$AZ$5,A162)),"",INDEX('DM01-AV-CH'!$A$5:$AZ$5,A162)))} -> Topic | D162: Thema / Topic (deutsch)
A163: 8 | B163: =IF(A163="","",IF(ISERROR(SUBSTITUTE(ADDRESS(1,A163,4,1),"1","")),"",SUBSTITUTE(ADDRESS(1,A163,4,1),"1",""))) -> H | C163: {=IF(A163="","",IF(ISERROR(INDEX('DM01-AV-CH'!$A$5:$AZ$5,A163)),"",INDEX('DM01-AV-CH'!$A$5:$AZ$5,A163)))} -> Tabelle | D163: Tabellenname (deutsch)
A164: 9 | B164: =IF(A164="","",IF(ISERROR(SUBSTITUTE(ADDRESS(1,A164,4,1),"1","")),"",SUBSTITUTE(ADDRESS(1,A164,4,1),"1",""))) -> I | C164: {=IF(A164="","",IF(ISERROR(INDEX('DM01-AV-CH'!$A$5:$AZ$5,A164)),"",INDEX('DM01-AV-CH'!$A$5:$AZ$5,A164)))} -> Attribut | D164: Attributname (deutsch)
A165: 10 | B165: =IF(A165="","",IF(ISERROR(SUBSTITUTE(ADDRESS(1,A165,4,1),"1","")),"",SUBSTITUTE(ADDRESS(1,A165,4,1),"1",""))) -> J | C165: {=IF(A165="","",IF(ISERROR(INDEX('DM01-AV-CH'!$A$5:$AZ$5,A165)),"",INDEX('DM01-AV-CH'!$A$5:$AZ$5,A165)))} -> Wertebereich | D165: Wertebereich
A166: 11 | B166: =IF(A166="","",IF(ISERROR(SUBSTITUTE(ADDRESS(1,A166,4,1),"1","")),"",SUBSTITUTE(ADDRESS(1,A166,4,1),"1",""))) -> K | C166: {=IF(A166="","",IF(ISERROR(INDEX('DM01-AV-CH'!$A$5:$AZ$5,A166)),"",INDEX('DM01-AV-CH'!$A$5:$AZ$5,A166)))} -> Default | D166: Defaultwert
A167: 12 | B167: =IF(A167="","",IF(ISERROR(SUBSTITUTE(ADDRESS(1,A167,4,1),"1","")),"",SUBSTITUTE(ADDRESS(1,A167,4,1),"1",""))) -> L | C167: {=IF(A167="","",IF(ISERROR(INDEX('DM01-AV-CH'!$A$5:$AZ$5,A167)),"",INDEX('DM01-AV-CH'!$A$5:$AZ$5,A167)))} -> Bemerkung | D167: Kommentar zum Element (deutsch)
A168: 14 | B168: =IF(A168="","",IF(ISERROR(SUBSTITUTE(ADDRESS(1,A168,4,1),"1","")),"",SUBSTITUTE(ADDRESS(1,A168,4,1),"1",""))) -> N | C168: {=IF(A168="","",IF(ISERROR(INDEX('DM01-AV-CH'!$A$5:$AZ$5,A168)),"",INDEX('DM01-AV-CH'!$A$5:$AZ$5,A168)))} -> Topic | D168: Thème / Topic (en français)
... A179: 26 | B179: =IF(A179="","",IF(ISERROR(SUBSTITUTE(ADDRESS(1,A179,4,1),"1","")),"",SUBSTITUTE(ADDRESS(1,A179,4,1),"1",""))) -> Z | C179: {=IF(A179="","",IF(ISERROR(INDEX('DM01-AV-CH'!$A$5:$AZ$5,A179)),"",INDEX('DM01-AV-CH'!$A$5:$AZ$5,A179)))} -> Commenti | D179: Commento alla registrazione (in italiano)

Sheet Transformation
J1: Modelltransfer (DMAV <> DM.01-AV-CH)
J2: Stand: 01.02.2026
A4: Zeile | B4: {=MID(CELL("adresse",DMAV_Modell!$A$1),FIND("]",CELL("adresse",DMAV_Modell!$A$1))+1,FIND("!",CELL("adresse",DMAV_Modell!$A$1))-FIND("]",CELL("adresse",DMAV_Modell!$A$1))-1)} -> DMAV_Modell | E4: {=MID(CELL("adresse",DMAV_Dienste!$A$1),FIND("]",CELL("adresse",DMAV_Dienste!$A$1))+1,FIND("!",CELL("adresse",DMAV_Dienste!$A$1))-FIND("]",CELL("adresse",DMAV_Dienste!$A$1))-1)} -> DMAV_Dienste | H4: {="'"&MID(CELL("adresse",'DM01-AV-CH'!$A$1),FIND("]",CELL("adresse",'DM01-AV-CH'!$A$1))+1,FIND("!",CELL("adresse",'DM01-AV-CH'!$A$1))-FIND("]",CELL("adresse",'DM01-AV-CH'!$A$1))-1)} -> 'DM01-AV-CH' | K4: DMAV Version 1.0 | T4: Übergang von DM.01-AV-CH nach DMAV Version 1.0 | Y4: Übergang von DMAV Version 1.0 nach DM.01-AV-CH | AG4: DM.01-AV-CH
A5: Nr. | B5: DR1 | C5: DR2 | D5: DR3 | E5: GR1 | F5: GR2 | G5: GR3 | H5: R1 | J5: Link | K5: Typ | L5: Topic | M5: Class | N5: Attribut | O5: Structure | P5: Substruct | R5: Bemerkung | T5: Bedingung / Voraussetzung in DM.01-AV-CH | U5: T | V5: Klasse | W5: Ergänzung | Y5: Bedingung / Voraussetzung in DMAV | Z5: T | AA5: Tabelle | AB5: Ergänzung | AD5: Bemerkungen | AF5: Link | AG5: Topic | AH5: Tabelle | AI5: Attribut
A6: 1 | B6: =IF($A6="","",IF(_xlfn.XLOOKUP($A6,Korrelation!$D$4:$D$1197,Korrelation!E$4:E$1197,"-",0)="-",0,MATCH(_xlfn.XLOOKUP($A6,Korrelation!$D$4:$D$1197,Korrelation!E$4:E$1197,"",0),DMAV_Modell!$G$6:$G$677,0))) -> 1 | C6: =IF($A6="","",IF(_xlfn.XLOOKUP($A6,Korrelation!$D$4:$D$1197,Korrelation!F$4:F$1197,"-",0)="-",0,MATCH(_xlfn.XLOOKUP($A6,Korrelation!$D$4:$D$1197,Korrelation!F$4:F$1197,"",0),DMAV_Modell!$G$6:$G$677,0))) -> 0 | D6: =IF($A6="","",IF(_xlfn.XLOOKUP($A6,Korrelation!$D$4:$D$1197,Korrelation!G$4:G$1197,"-",0)="-",0,MATCH(_xlfn.XLOOKUP($A6,Korrelation!$D$4:$D$1197,Korrelation!G$4:G$1197,"",0),DMAV_Modell!$G$6:$G$677,0))) -> 0 | E6: =IF($A6="","",IF(_xlfn.XLOOKUP($A6,Korrelation!$D$4:$D$1197,Korrelation!H$4:H$1197,"-",0)="-",0,MATCH(_xlfn.XLOOKUP($A6,Korrelation!$D$4:$D$1197,Korrelation!H$4:H$1197,"",0),DMAV_Dienste!$F$6:$F$140,0))) -> 0 | F6: =IF($A6="","",IF(_xlfn.XLOOKUP($A6,Korrelation!$D$4:$D$1197,Korrelation!I$4:I$1197,"-",0)="-",0,MATCH(_xlfn.XLOOKUP($A6,Korrelation!$D$4:$D$1197,Korrelation!I$4:I$1197,"",0),DMAV_Dienste!$F$6:$F$140,0))) -> 0 | G6: =IF($A6="","",IF(_xlfn.XLOOKUP($A6,Korrelation!$D$4:$D$1197,Korrelation!J$4:J$1197,"-",0)="-",0,MATCH(_xlfn.XLOOKUP($A6,Korrelation!$D$4:$D$1197,Korrelation!J$4:J$1197,"",0),DMAV_Dienste!$F$6:$F$140,0))) -> 0 | H6: =IF($A6="","",IF(_xlfn.XLOOKUP($A6,Korrelation!$D$4:$D$1197,Korrelation!K$4:K$1197,"-",0)="-",0,MATCH(_xlfn.XLOOKUP($A6,Korrelation!$D$4:$D$1197,Korrelation!K$4:K$1197,"",0),'DM01-AV-CH'!$A$6:$A$834,0))) -> 0 | J6: {=IF(B6=0,IF(E6=0,"",HYPERLINK("#"&RIGHT(CELL("adresse",OFFSET(DMAV_Dienste!$M$6,E6-1,0)),LEN(CELL("adresse",OFFSET(DMAV_Dienste!$M$6,E6-1,0)))-FIND("]",CELL("adresse",OFFSET(DMAV_Dienste!$M$6,E6-1,0)))),"Dienst")),HYPERLINK("#"&RIGHT(CELL("adresse",OFFSET(DMAV_Modell!$N$6,B6-1,0)),LEN(CELL("adresse",OFFSET(DMAV_Modell!$N$6,B6-1,0)))-FIND("]",CELL("adresse",OFFSET(DMAV_Modell!$N$6,B6-1,0)))),"Modell"))} -> Modell | K6: {=IF($B6=0,IF($E6=0,"",IF(INDEX(DMAV_Dienste!P$6:P$140,$E6)="","",INDEX(DMAV_Dienste!P$6:P$140,$E6))),IF(INDEX(DMAV_Modell!Q$6:Q$838,$B6)="","",INDEX(DMAV_Modell!Q$6:Q$838,$B6)))} -> IMPORTS | L6: {=IF($B6=0,IF($E6=0,"",IF(INDEX(DMAV_Dienste!O$6:O$140,$E6)="","",INDEX(DMAV_Dienste!O$6:O$140,$E6))),IF(INDEX(DMAV_Modell!P$6:P$838,$B6)="","",INDEX(DMAV_Modell!P$6:P$838,$B6)))} | M6: {=IF($B6=0,IF($E6=0,"",IF(INDEX(DMAV_Dienste!Q$6:Q$140,$E6)="","",INDEX(DMAV_Dienste!Q$6:Q$140,$E6))),IF(INDEX(DMAV_Modell!R$6:R$838,$B6)="","",INDEX(DMAV_Modell!R$6:R$838,$B6)))} -> DMAV_Bodenbedeckung_V1_1 | N6: {=IF($B6=0,IF($E6=0,"",IF(INDEX(DMAV_Dienste!T$6:T$140,$E6)="","",INDEX(DMAV_Dienste!T$6:T$140,$E6))),IF(INDEX(DMAV_Modell!U$6:U$838,$B6)="","",INDEX(DMAV_Modell!U$6:U$838,$B6)))} | O6: {=IF(C6=0,IF(F6=0,"",HYPERLINK("#"&RIGHT(CELL("adresse",OFFSET(DMAV_Dienste!$M$6,F6-1,0)),LEN(CELL("adresse",OFFSET(DMAV_Dienste!$M$6,F6-1,0)))-FIND("]",CELL("adresse",OFFSET(DMAV_Dienste!$M$6,F6-1,0)))),"Structure")),HYPERLINK("#"&RIGHT(CELL("adresse",OFFSET(DMAV_Modell!$N$6,C6-1,0)),LEN(CELL("adresse",OFFSET(DMAV_Modell!$N$6,C6-1,0)))-FIND("]",CELL("adresse",OFFSET(DMAV_Modell!$N$6,C6-1,0)))),"Structure"))} | P6: {=IF(D6=0,IF(G6=0,"",HYPERLINK("#"&RIGHT(CELL("adresse",OFFSET(DMAV_Dienste!$M$6,G6-1,0)),LEN(CELL("adresse",OFFSET(DMAV_Dienste!$M$6,G6-1,0)))-FIND("]",CELL("adresse",OFFSET(DMAV_Dienste!$M$6,G6-1,0)))),"Substructure")),HYPERLINK("#"&RIGHT(CELL("adresse",OFFSET(DMAV_Modell!$N$6,D6-1,0)),LEN(CELL("adresse",OFFSET(DMAV_Modell!$N$6,D6-1,0)))-FIND("]",CELL("adresse",OFFSET(DMAV_Modell!$N$6,D6-1,0)))),"Substructure"))} | AF6: {=IF(H6=0,"",HYPERLINK("#"&RIGHT(CELL("adresse",OFFSET('DM01-AV-CH'!$G$6,H6-1,0)),LEN(CELL("adresse",OFFSET('DM01-AV-CH'!$G$6,H6-1,0)))-FIND("]",CELL("adresse",OFFSET('DM01-AV-CH'!$G$6,H6-1,0)))),"Modell"))} | AG6: {=IF($H6=0,"",IF(INDEX('DM01-AV-CH'!G$6:G$834,$H6)="","",INDEX('DM01-AV-CH'!G$6:G$834,$H6)))} | AH6: {=IF($H6=0,"",IF(INDEX('DM01-AV-CH'!H$6:H$834,$H6)="","",INDEX('DM01-AV-CH'!H$6:H$834,$H6)))} | AI6: {=IF($H6=0,"",IF(INDEX('DM01-AV-CH'!I$6:I$834,$H6)="","",INDEX('DM01-AV-CH'!I$6:I$834,$H6)))}
A7: 2 | B7: =IF($A7="","",IF(_xlfn.XLOOKUP($A7,Korrelation!$D$4:$D$1197,Korrelation!E$4:E$1197,"-",0)="-",0,MATCH(_xlfn.XLOOKUP($A7,Korrelation!$D$4:$D$1197,Korrelation!E$4:E$1197,"",0),DMAV_Modell!$G$6:$G$677,0))) -> 2 | C7: =IF($A7="","",IF(_xlfn.XLOOKUP($A7,Korrelation!$D$4:$D$1197,Korrelation!F$4:F$1197,"-",0)="-",0,MATCH(_xlfn.XLOOKUP($A7,Korrelation!$D$4:$D$1197,Korrelation!F$4:F$1197,"",0),DMAV_Modell!$G$6:$G$677,0))) -> 0 | D7: =IF($A7="","",IF(_xlfn.XLOOKUP($A7,Korrelation!$D$4:$D$1197,Korrelation!G$4:G$1197,"-",0)="-",0,MATCH(_xlfn.XLOOKUP($A7,Korrelation!$D$4:$D$1197,Korrelation!G$4:G$1197,"",0),DMAV_Modell!$G$6:$G$677,0))) -> 0 | E7: =IF($A7="","",IF(_xlfn.XLOOKUP($A7,Korrelation!$D$4:$D$1197,Korrelation!H$4:H$1197,"-",0)="-",0,MATCH(_xlfn.XLOOKUP($A7,Korrelation!$D$4:$D$1197,Korrelation!H$4:H$1197,"",0),DMAV_Dienste!$F$6:$F$140,0))) -> 0 | F7: =IF($A7="","",IF(_xlfn.XLOOKUP($A7,Korrelation!$D$4:$D$1197,Korrelation!I$4:I$1197,"-",0)="-",0,MATCH(_xlfn.XLOOKUP($A7,Korrelation!$D$4:$D$1197,Korrelation!I$4:I$1197,"",0),DMAV_Dienste!$F$6:$F$140,0))) -> 0 | G7: =IF($A7="","",IF(_xlfn.XLOOKUP($A7,Korrelation!$D$4:$D$1197,Korrelation!J$4:J$1197,"-",0)="-",0,MATCH(_xlfn.XLOOKUP($A7,Korrelation!$D$4:$D$1197,Korrelation!J$4:J$1197,"",0),DMAV_Dienste!$F$6:$F$140,0))) -> 0 | H7: =IF($A7="","",IF(_xlfn.XLOOKUP($A7,Korrelation!$D$4:$D$1197,Korrelation!K$4:K$1197,"-",0)="-",0,MATCH(_xlfn.XLOOKUP($A7,Korrelation!$D$4:$D$1197,Korrelation!K$4:K$1197,"",0),'DM01-AV-CH'!$A$6:$A$834,0))) -> 0 | J7: {=IF(B7=0,IF(E7=0,"",HYPERLINK("#"&RIGHT(CELL("adresse",OFFSET(DMAV_Dienste!$M$6,E7-1,0)),LEN(CELL("adresse",OFFSET(DMAV_Dienste!$M$6,E7-1,0)))-FIND("]",CELL("adresse",OFFSET(DMAV_Dienste!$M$6,E7-1,0)))),"Dienst")),HYPERLINK("#"&RIGHT(CELL("adresse",OFFSET(DMAV_Modell!$N$6,B7-1,0)),LEN(CELL("adresse",OFFSET(DMAV_Modell!$N$6,B7-1,0)))-FIND("]",CELL("adresse",OFFSET(DMAV_Modell!$N$6,B7-1,0)))),"Modell"))} -> Modell | K7: {=IF($B7=0,IF($E7=0,"",IF(INDEX(DMAV_Dienste!P$6:P$140,$E7)="","",INDEX(DMAV_Dienste!P$6:P$140,$E7))),IF(INDEX(DMAV_Modell!Q$6:Q$838,$B7)="","",INDEX(DMAV_Modell!Q$6:Q$838,$B7)))} -> IMPORTS | L7: {=IF($B7=0,IF($E7=0,"",IF(INDEX(DMAV_Dienste!O$6:O$140,$E7)="","",INDEX(DMAV_Dienste!O$6:O$140,$E7))),IF(INDEX(DMAV_Modell!P$6:P$838,$B7)="","",INDEX(DMAV_Modell!P$6:P$838,$B7)))} | M7: {=IF($B7=0,IF($E7=0,"",IF(INDEX(DMAV_Dienste!Q$6:Q$140,$E7)="","",INDEX(DMAV_Dienste!Q$6:Q$140,$E7))),IF(INDEX(DMAV_Modell!R$6:R$838,$B7)="","",INDEX(DMAV_Modell!R$6:R$838,$B7)))} -> DMAV_DauerndeBodenverschiebungen_V1_1 | N7: {=IF($B7=0,IF($E7=0,"",IF(INDEX(DMAV_Dienste!T$6:T$140,$E7)="","",INDEX(DMAV_Dienste!T$6:T$140,$E7))),IF(INDEX(DMAV_Modell!U$6:U$838,$B7)="","",INDEX(DMAV_Modell!U$6:U$838,$B7)))} | O7: {=IF(C7=0,IF(F7=0,"",HYPERLINK("#"&RIGHT(CELL("adresse",OFFSET(DMAV_Dienste!$M$6,F7-1,0)),LEN(CELL("adresse",OFFSET(DMAV_Dienste!$M$6,F7-1,0)))-FIND("]",CELL("adresse",OFFSET(DMAV_Dienste!$M$6,F7-1,0)))),"Structure")),HYPERLINK("#"&RIGHT(CELL("adresse",OFFSET(DMAV_Modell!$N$6,C7-1,0)),LEN(CELL("adresse",OFFSET(DMAV_Modell!$N$6,C7-1,0)))-FIND("]",CELL("adresse",OFFSET(DMAV_Modell!$N$6,C7-1,0)))),"Structure"))} | P7: {=IF(D7=0,IF(G7=0,"",HYPERLINK("#"&RIGHT(CELL("adresse",OFFSET(DMAV_Dienste!$M$6,G7-1,0)),LEN(CELL("adresse",OFFSET(DMAV_Dienste!$M$6,G7-1,0)))-FIND("]",CELL("adresse",OFFSET(DMAV_Dienste!$M$6,G7-1,0)))),"Substructure")),HYPERLINK("#"&RIGHT(CELL("adresse",OFFSET(DMAV_Modell!$N$6,D7-1,0)),LEN(CELL("adresse",OFFSET(DMAV_Modell!$N$6,D7-1,0)))-FIND("]",CELL("adresse",OFFSET(DMAV_Modell!$N$6,D7-1,0)))),"Substructure"))} | AF7: {=IF(H7=0,"",HYPERLINK("#"&RIGHT(CELL("adresse",OFFSET('DM01-AV-CH'!$G$6,H7-1,0)),LEN(CELL("adresse",OFFSET('DM01-AV-CH'!$G$6,H7-1,0)))-FIND("]",CELL("adresse",OFFSET('DM01-AV-CH'!$G$6,H7-1,0)))),"Modell"))} | AG7: {=IF($H7=0,"",IF(INDEX('DM01-AV-CH'!G$6:G$834,$H7)="","",INDEX('DM01-AV-CH'!G$6:G$834,$H7)))} | AH7: {=IF($H7=0,"",IF(INDEX('DM01-AV-CH'!H$6:H$834,$H7)="","",INDEX('DM01-AV-CH'!H$6:H$834,$H7)))} | AI7: {=IF($H7=0,"",IF(INDEX('DM01-AV-CH'!I$6:I$834,$H7)="","",INDEX('DM01-AV-CH'!I$6:I$834,$H7)))}
A8: 3 | B8: =IF($A8="","",IF(_xlfn.XLOOKUP($A8,Korrelation!$D$4:$D$1197,Korrelation!E$4:E$1197,"-",0)="-",0,MATCH(_xlfn.XLOOKUP($A8,Korrelation!$D$4:$D$1197,Korrelation!E$4:E$1197,"",0),DMAV_Modell!$G$6:$G$677,0))) -> 3 | C8: =IF($A8="","",IF(_xlfn.XLOOKUP($A8,Korrelation!$D$4:$D$1197,Korrelation!F$4:F$1197,"-",0)="-",0,MATCH(_xlfn.XLOOKUP($A8,Korrelation!$D$4:$D$1197,Korrelation!F$4:F$1197,"",0),DMAV_Modell!$G$6:$G$677,0))) -> 0 | D8: =IF($A8="","",IF(_xlfn.XLOOKUP($A8,Korrelation!$D$4:$D$1197,Korrelation!G$4:G$1197,"-",0)="-",0,MATCH(_xlfn.XLOOKUP($A8,Korrelation!$D$4:$D$1197,Korrelation!G$4:G$1197,"",0),DMAV_Modell!$G$6:$G$677,0))) -> 0 | E8: =IF($A8="","",IF(_xlfn.XLOOKUP($A8,Korrelation!$D$4:$D$1197,Korrelation!H$4:H$1197,"-",0)="-",0,MATCH(_xlfn.XLOOKUP($A8,Korrelation!$D$4:$D$1197,Korrelation!H$4:H$1197,"",0),DMAV_Dienste!$F$6:$F$140,0))) -> 0 | F8: =IF($A8="","",IF(_xlfn.XLOOKUP($A8,Korrelation!$D$4:$D$1197,Korrelation!I$4:I$1197,"-",0)="-",0,MATCH(_xlfn.XLOOKUP($A8,Korrelation!$D$4:$D$1197,Korrelation!I$4:I$1197,"",0),DMAV_Dienste!$F$6:$F$140,0))) -> 0 | G8: =IF($A8="","",IF(_xlfn.XLOOKUP($A8,Korrelation!$D$4:$D$1197,Korrelation!J$4:J$1197,"-",0)="-",0,MATCH(_xlfn.XLOOKUP($A8,Korrelation!$D$4:$D$1197,Korrelation!J$4:J$1197,"",0),DMAV_Dienste!$F$6:$F$140,0))) -> 0 | H8: =IF($A8="","",IF(_xlfn.XLOOKUP($A8,Korrelation!$D$4:$D$1197,Korrelation!K$4:K$1197,"-",0)="-",0,MATCH(_xlfn.XLOOKUP($A8,Korrelation!$D$4:$D$1197,Korrelation!K$4:K$1197,"",0),'DM01-AV-CH'!$A$6:$A$834,0))) -> 0 | J8: {=IF(B8=0,IF(E8=0,"",HYPERLINK("#"&RIGHT(CELL("adresse",OFFSET(DMAV_Dienste!$M$6,E8-1,0)),LEN(CELL("adresse",OFFSET(DMAV_Dienste!$M$6,E8-1,0)))-FIND("]",CELL("adresse",OFFSET(DMAV_Dienste!$M$6,E8-1,0)))),"Dienst")),HYPERLINK("#"&RIGHT(CELL("adresse",OFFSET(DMAV_Modell!$N$6,B8-1,0)),LEN(CELL("adresse",OFFSET(DMAV_Modell!$N$6,B8-1,0)))-FIND("]",CELL("adresse",OFFSET(DMAV_Modell!$N$6,B8-1,0)))),"Modell"))} -> Modell | K8: {=IF($B8=0,IF($E8=0,"",IF(INDEX(DMAV_Dienste!P$6:P$140,$E8)="","",INDEX(DMAV_Dienste!P$6:P$140,$E8))),IF(INDEX(DMAV_Modell!Q$6:Q$838,$B8)="","",INDEX(DMAV_Modell!Q$6:Q$838,$B8)))} -> IMPORTS | L8: {=IF($B8=0,IF($E8=0,"",IF(INDEX(DMAV_Dienste!O$6:O$140,$E8)="","",INDEX(DMAV_Dienste!O$6:O$140,$E8))),IF(INDEX(DMAV_Modell!P$6:P$838,$B8)="","",INDEX(DMAV_Modell!P$6:P$838,$B8)))} | M8: {=IF($B8=0,IF($E8=0,"",IF(INDEX(DMAV_Dienste!Q$6:Q$140,$E8)="","",INDEX(DMAV_Dienste!Q$6:Q$140,$E8))),IF(INDEX(DMAV_Modell!R$6:R$838,$B8)="","",INDEX(DMAV_Modell!R$6:R$838,$B8)))} -> DMAV_Dienstbarkeitsgrenzen_V1_1 | N8: {=IF($B8=0,IF($E8=0,"",IF(INDEX(DMAV_Dienste!T$6:T$140,$E8)="","",INDEX(DMAV_Dienste!T$6:T$140,$E8))),IF(INDEX(DMAV_Modell!U$6:U$838,$B8)="","",INDEX(DMAV_Modell!U$6:U$838,$B8)))} | O8: {=IF(C8=0,IF(F8=0,"",HYPERLINK("#"&RIGHT(CELL("adresse",OFFSET(DMAV_Dienste!$M$6,F8-1,0)),LEN(CELL("adresse",OFFSET(DMAV_Dienste!$M$6,F8-1,0)))-FIND("]",CELL("adresse",OFFSET(DMAV_Dienste!$M$6,F8-1,0)))),"Structure")),HYPERLINK("#"&RIGHT(CELL("adresse",OFFSET(DMAV_Modell!$N$6,C8-1,0)),LEN(CELL("adresse",OFFSET(DMAV_Modell!$N$6,C8-1,0)))-FIND("]",CELL("adresse",OFFSET(DMAV_Modell!$N$6,C8-1,0)))),"Structure"))} | P8: {=IF(D8=0,IF(G8=0,"",HYPERLINK("#"&RIGHT(CELL("adresse",OFFSET(DMAV_Dienste!$M$6,G8-1,0)),LEN(CELL("adresse",OFFSET(DMAV_Dienste!$M$6,G8-1,0)))-FIND("]",CELL("adresse",OFFSET(DMAV_Dienste!$M$6,G8-1,0)))),"Substructure")),HYPERLINK("#"&RIGHT(CELL("adresse",OFFSET(DMAV_Modell!$N$6,D8-1,0)),LEN(CELL("adresse",OFFSET(DMAV_Modell!$N$6,D8-1,0)))-FIND("]",CELL("adresse",OFFSET(DMAV_Modell!$N$6,D8-1,0)))),"Substructure"))} | AF8: {=IF(H8=0,"",HYPERLINK("#"&RIGHT(CELL("adresse",OFFSET('DM01-AV-CH'!$G$6,H8-1,0)),LEN(CELL("adresse",OFFSET('DM01-AV-CH'!$G$6,H8-1,0)))-FIND("]",CELL("adresse",OFFSET('DM01-AV-CH'!$G$6,H8-1,0)))),"Modell"))} | AG8: {=IF($H8=0,"",IF(INDEX('DM01-AV-CH'!G$6:G$834,$H8)="","",INDEX('DM01-AV-CH'!G$6:G$834,$H8)))} | AH8: {=IF($H8=0,"",IF(INDEX('DM01-AV-CH'!H$6:H$834,$H8)="","",INDEX('DM01-AV-CH'!H$6:H$834,$H8)))} | AI8: {=IF($H8=0,"",IF(INDEX('DM01-AV-CH'!I$6:I$834,$H8)="","",INDEX('DM01-AV-CH'!I$6:I$834,$H8)))}
A9: 4 | B9: =IF($A9="","",IF(_xlfn.XLOOKUP($A9,Korrelation!$D$4:$D$1197,Korrelation!E$4:E$1197,"-",0)="-",0,MATCH(_xlfn.XLOOKUP($A9,Korrelation!$D$4:$D$1197,Korrelation!E$4:E$1197,"",0),DMAV_Modell!$G$6:$G$677,0))) -> 4 | C9: =IF($A9="","",IF(_xlfn.XLOOKUP($A9,Korrelation!$D$4:$D$1197,Korrelation!F$4:F$1197,"-",0)="-",0,MATCH(_xlfn.XLOOKUP($A9,Korrelation!$D$4:$D$1197,Korrelation!F$4:F$1197,"",0),DMAV_Modell!$G$6:$G$677,0))) -> 0 | D9: =IF($A9="","",IF(_xlfn.XLOOKUP($A9,Korrelation!$D$4:$D$1197,Korrelation!G$4:G$1197,"-",0)="-",0,MATCH(_xlfn.XLOOKUP($A9,Korrelation!$D$4:$D$1197,Korrelation!G$4:G$1197,"",0),DMAV_Modell!$G$6:$G$677,0))) -> 0 | E9: =IF($A9="","",IF(_xlfn.XLOOKUP($A9,Korrelation!$D$4:$D$1197,Korrelation!H$4:H$1197,"-",0)="-",0,MATCH(_xlfn.XLOOKUP($A9,Korrelation!$D$4:$D$1197,Korrelation!H$4:H$1197,"",0),DMAV_Dienste!$F$6:$F$140,0))) -> 0 | F9: =IF($A9="","",IF(_xlfn.XLOOKUP($A9,Korrelation!$D$4:$D$1197,Korrelation!I$4:I$1197,"-",0)="-",0,MATCH(_xlfn.XLOOKUP($A9,Korrelation!$D$4:$D$1197,Korrelation!I$4:I$1197,"",0),DMAV_Dienste!$F$6:$F$140,0))) -> 0 | G9: =IF($A9="","",IF(_xlfn.XLOOKUP($A9,Korrelation!$D$4:$D$1197,Korrelation!J$4:J$1197,"-",0)="-",0,MATCH(_xlfn.XLOOKUP($A9,Korrelation!$D$4:$D$1197,Korrelation!J$4:J$1197,"",0),DMAV_Dienste!$F$6:$F$140,0))) -> 0 | H9: =IF($A9="","",IF(_xlfn.XLOOKUP($A9,Korrelation!$D$4:$D$1197,Korrelation!K$4:K$1197,"-",0)="-",0,MATCH(_xlfn.XLOOKUP($A9,Korrelation!$D$4:$D$1197,Korrelation!K$4:K$1197,"",0),'DM01-AV-CH'!$A$6:$A$834,0))) -> 0 | J9: {=IF(B9=0,IF(E9=0,"",HYPERLINK("#"&RIGHT(CELL("adresse",OFFSET(DMAV_Dienste!$M$6,E9-1,0)),LEN(CELL("adresse",OFFSET(DMAV_Dienste!$M$6,E9-1,0)))-FIND("]",CELL("adresse",OFFSET(DMAV_Dienste!$M$6,E9-1,0)))),"Dienst")),HYPERLINK("#"&RIGHT(CELL("adresse",OFFSET(DMAV_Modell!$N$6,B9-1,0)),LEN(CELL("adresse",OFFSET(DMAV_Modell!$N$6,B9-1,0)))-FIND("]",CELL("adresse",OFFSET(DMAV_Modell!$N$6,B9-1,0)))),"Modell"))} -> Modell | K9: {=IF($B9=0,IF($E9=0,"",IF(INDEX(DMAV_Dienste!P$6:P$140,$E9)="","",INDEX(DMAV_Dienste!P$6:P$140,$E9))),IF(INDEX(DMAV_Modell!Q$6:Q$838,$B9)="","",INDEX(DMAV_Modell!Q$6:Q$838,$B9)))} -> IMPORTS | L9: {=IF($B9=0,IF($E9=0,"",IF(INDEX(DMAV_Dienste!O$6:O$140,$E9)="","",INDEX(DMAV_Dienste!O$6:O$140,$E9))),IF(INDEX(DMAV_Modell!P$6:P$838,$B9)="","",INDEX(DMAV_Modell!P$6:P$838,$B9)))} | M9: {=IF($B9=0,IF($E9=0,"",IF(INDEX(DMAV_Dienste!Q$6:Q$140,$E9)="","",INDEX(DMAV_Dienste!Q$6:Q$140,$E9))),IF(INDEX(DMAV_Modell!R$6:R$838,$B9)="","",INDEX(DMAV_Modell!R$6:R$838,$B9)))} -> DMAV_Einzelobjekte_V1_1 | N9: {=IF($B9=0,IF($E9=0,"",IF(INDEX(DMAV_Dienste!T$6:T$140,$E9)="","",INDEX(DMAV_Dienste!T$6:T$140,$E9))),IF(INDEX(DMAV_Modell!U$6:U$838,$B9)="","",INDEX(DMAV_Modell!U$6:U$838,$B9)))} | O9: {=IF(C9=0,IF(F9=0,"",HYPERLINK("#"&RIGHT(CELL("adresse",OFFSET(DMAV_Dienste!$M$6,F9-1,0)),LEN(CELL("adresse",OFFSET(DMAV_Dienste!$M$6,F9-1,0)))-FIND("]",CELL("adresse",OFFSET(DMAV_Dienste!$M$6,F9-1,0)))),"Structure")),HYPERLINK("#"&RIGHT(CELL("adresse",OFFSET(DMAV_Modell!$N$6,C9-1,0)),LEN(CELL("adresse",OFFSET(DMAV_Modell!$N$6,C9-1,0)))-FIND("]",CELL("adresse",OFFSET(DMAV_Modell!$N$6,C9-1,0)))),"Structure"))} | P9: {=IF(D9=0,IF(G9=0,"",HYPERLINK("#"&RIGHT(CELL("adresse",OFFSET(DMAV_Dienste!$M$6,G9-1,0)),LEN(CELL("adresse",OFFSET(DMAV_Dienste!$M$6,G9-1,0)))-FIND("]",CELL("adresse",OFFSET(DMAV_Dienste!$M$6,G9-1,0)))),"Substructure")),HYPERLINK("#"&RIGHT(CELL("adresse",OFFSET(DMAV_Modell!$N$6,D9-1,0)),LEN(CELL("adresse",OFFSET(DMAV_Modell!$N$6,D9-1,0)))-FIND("]",CELL("adresse",OFFSET(DMAV_Modell!$N$6,D9-1,0)))),"Substructure"))} | AF9: {=IF(H9=0,"",HYPERLINK("#"&RIGHT(CELL("adresse",OFFSET('DM01-AV-CH'!$G$6,H9-1,0)),LEN(CELL("adresse",OFFSET('DM01-AV-CH'!$G$6,H9-1,0)))-FIND("]",CELL("adresse",OFFSET('DM01-AV-CH'!$G$6,H9-1,0)))),"Modell"))} | AG9: {=IF($H9=0,"",IF(INDEX('DM01-AV-CH'!G$6:G$834,$H9)="","",INDEX('DM01-AV-CH'!G$6:G$834,$H9)))} | AH9: {=IF($H9=0,"",IF(INDEX('DM01-AV-CH'!H$6:H$834,$H9)="","",INDEX('DM01-AV-CH'!H$6:H$834,$H9)))} | AI9: {=IF($H9=0,"",IF(INDEX('DM01-AV-CH'!I$6:I$834,$H9)="","",INDEX('DM01-AV-CH'!I$6:I$834,$H9)))}
A10: 5 | B10: =IF($A10="","",IF(_xlfn.XLOOKUP($A10,Korrelation!$D$4:$D$1197,Korrelation!E$4:E$1197,"-",0)="-",0,MATCH(_xlfn.XLOOKUP($A10,Korrelation!$D$4:$D$1197,Korrelation!E$4:E$1197,"",0),DMAV_Modell!$G$6:$G$677,0))) -> 5 | C10: =IF($A10="","",IF(_xlfn.XLOOKUP($A10,Korrelation!$D$4:$D$1197,Korrelation!F$4:F$1197,"-",0)="-",0,MATCH(_xlfn.XLOOKUP($A10,Korrelation!$D$4:$D$1197,Korrelation!F$4:F$1197,"",0),DMAV_Modell!$G$6:$G$677,0))) -> 0 | D10: =IF($A10="","",IF(_xlfn.XLOOKUP($A10,Korrelation!$D$4:$D$1197,Korrelation!G$4:G$1197,"-",0)="-",0,MATCH(_xlfn.XLOOKUP($A10,Korrelation!$D$4:$D$1197,Korrelation!G$4:G$1197,"",0),DMAV_Modell!$G$6:$G$677,0))) -> 0 | E10: =IF($A10="","",IF(_xlfn.XLOOKUP($A10,Korrelation!$D$4:$D$1197,Korrelation!H$4:H$1197,"-",0)="-",0,MATCH(_xlfn.XLOOKUP($A10,Korrelation!$D$4:$D$1197,Korrelation!H$4:H$1197,"",0),DMAV_Dienste!$F$6:$F$140,0))) -> 0 | F10: =IF($A10="","",IF(_xlfn.XLOOKUP($A10,Korrelation!$D$4:$D$1197,Korrelation!I$4:I$1197,"-",0)="-",0,MATCH(_xlfn.XLOOKUP($A10,Korrelation!$D$4:$D$1197,Korrelation!I$4:I$1197,"",0),DMAV_Dienste!$F$6:$F$140,0))) -> 0 | G10: =IF($A10="","",IF(_xlfn.XLOOKUP($A10,Korrelation!$D$4:$D$1197,Korrelation!J$4:J$1197,"-",0)="-",0,MATCH(_xlfn.XLOOKUP($A10,Korrelation!$D$4:$D$1197,Korrelation!J$4:J$1197,"",0),DMAV_Dienste!$F$6:$F$140,0))) -> 0 | H10: =IF($A10="","",IF(_xlfn.XLOOKUP($A10,Korrelation!$D$4:$D$1197,Korrelation!K$4:K$1197,"-",0)="-",0,MATCH(_xlfn.XLOOKUP($A10,Korrelation!$D$4:$D$1197,Korrelation!K$4:K$1197,"",0),'DM01-AV-CH'!$A$6:$A$834,0))) -> 0 | J10: {=IF(B10=0,IF(E10=0,"",HYPERLINK("#"&RIGHT(CELL("adresse",OFFSET(DMAV_Dienste!$M$6,E10-1,0)),LEN(CELL("adresse",OFFSET(DMAV_Dienste!$M$6,E10-1,0)))-FIND("]",CELL("adresse",OFFSET(DMAV_Dienste!$M$6,E10-1,0)))),"Dienst")),HYPERLINK("#"&RIGHT(CELL("adresse",OFFSET(DMAV_Modell!$N$6,B10-1,0)),LEN(CELL("adresse",OFFSET(DMAV_Modell!$N$6,B10-1,0)))-FIND("]",CELL("adresse",OFFSET(DMAV_Modell!$N$6,B10-1,0)))),"Modell"))} -> Modell | K10: {=IF($B10=0,IF($E10=0,"",IF(INDEX(DMAV_Dienste!P$6:P$140,$E10)="","",INDEX(DMAV_Dienste!P$6:P$140,$E10))),IF(INDEX(DMAV_Modell!Q$6:Q$838,$B10)="","",INDEX(DMAV_Modell!Q$6:Q$838,$B10)))} -> IMPORTS | L10: {=IF($B10=0,IF($E10=0,"",IF(INDEX(DMAV_Dienste!O$6:O$140,$E10)="","",INDEX(DMAV_Dienste!O$6:O$140,$E10))),IF(INDEX(DMAV_Modell!P$6:P$838,$B10)="","",INDEX(DMAV_Modell!P$6:P$838,$B10)))} | M10: {=IF($B10=0,IF($E10=0,"",IF(INDEX(DMAV_Dienste!Q$6:Q$140,$E10)="","",INDEX(DMAV_Dienste!Q$6:Q$140,$E10))),IF(INDEX(DMAV_Modell!R$6:R$838,$B10)="","",INDEX(DMAV_Modell!R$6:R$838,$B10)))} -> DMAV_FixpunkteAVKategorie3_V1_1 | N10: {=IF($B10=0,IF($E10=0,"",IF(INDEX(DMAV_Dienste!T$6:T$140,$E10)="","",INDEX(DMAV_Dienste!T$6:T$140,$E10))),IF(INDEX(DMAV_Modell!U$6:U$838,$B10)="","",INDEX(DMAV_Modell!U$6:U$838,$B10)))} | O10: {=IF(C10=0,IF(F10=0,"",HYPERLINK("#"&RIGHT(CELL("adresse",OFFSET(DMAV_Dienste!$M$6,F10-1,0)),LEN(CELL("adresse",OFFSET(DMAV_Dienste!$M$6,F10-1,0)))-FIND("]",CELL("adresse",OFFSET(DMAV_Dienste!$M$6,F10-1,0)))),"Structure")),HYPERLINK("#"&RIGHT(CELL("adresse",OFFSET(DMAV_Modell!$N$6,C10-1,0)),LEN(CELL("adresse",OFFSET(DMAV_Modell!$N$6,C10-1,0)))-FIND("]",CELL("adresse",OFFSET(DMAV_Modell!$N$6,C10-1,0)))),"Structure"))} | P10: {=IF(D10=0,IF(G10=0,"",HYPERLINK("#"&RIGHT(CELL("adresse",OFFSET(DMAV_Dienste!$M$6,G10-1,0)),LEN(CELL("adresse",OFFSET(DMAV_Dienste!$M$6,G10-1,0)))-FIND("]",CELL("adresse",OFFSET(DMAV_Dienste!$M$6,G10-1,0)))),"Substructure")),HYPERLINK("#"&RIGHT(CELL("adresse",OFFSET(DMAV_Modell!$N$6,D10-1,0)),LEN(CELL("adresse",OFFSET(DMAV_Modell!$N$6,D10-1,0)))-FIND("]",CELL("adresse",OFFSET(DMAV_Modell!$N$6,D10-1,0)))),"Substructure"))} | AF10: {=IF(H10=0,"",HYPERLINK("#"&RIGHT(CELL("adresse",OFFSET('DM01-AV-CH'!$G$6,H10-1,0)),LEN(CELL("adresse",OFFSET('DM01-AV-CH'!$G$6,H10-1,0)))-FIND("]",CELL("adresse",OFFSET('DM01-AV-CH'!$G$6,H10-1,0)))),"Modell"))} | AG10: {=IF($H10=0,"",IF(INDEX('DM01-AV-CH'!G$6:G$834,$H10)="","",INDEX('DM01-AV-CH'!G$6:G$834,$H10)))} | AH10: {=IF($H10=0,"",IF(INDEX('DM01-AV-CH'!H$6:H$834,$H10)="","",INDEX('DM01-AV-CH'!H$6:H$834,$H10)))} | AI10: {=IF($H10=0,"",IF(INDEX('DM01-AV-CH'!I$6:I$834,$H10)="","",INDEX('DM01-AV-CH'!I$6:I$834,$H10)))}
A11: 6 | B11: =IF($A11="","",IF(_xlfn.XLOOKUP($A11,Korrelation!$D$4:$D$1197,Korrelation!E$4:E$1197,"-",0)="-",0,MATCH(_xlfn.XLOOKUP($A11,Korrelation!$D$4:$D$1197,Korrelation!E$4:E$1197,"",0),DMAV_Modell!$G$6:$G$677,0))) -> 6 | C11: =IF($A11="","",IF(_xlfn.XLOOKUP($A11,Korrelation!$D$4:$D$1197,Korrelation!F$4:F$1197,"-",0)="-",0,MATCH(_xlfn.XLOOKUP($A11,Korrelation!$D$4:$D$1197,Korrelation!F$4:F$1197,"",0),DMAV_Modell!$G$6:$G$677,0))) -> 0 | D11: =IF($A11="","",IF(_xlfn.XLOOKUP($A11,Korrelation!$D$4:$D$1197,Korrelation!G$4:G$1197,"-",0)="-",0,MATCH(_xlfn.XLOOKUP($A11,Korrelation!$D$4:$D$1197,Korrelation!G$4:G$1197,"",0),DMAV_Modell!$G$6:$G$677,0))) -> 0 | E11: =IF($A11="","",IF(_xlfn.XLOOKUP($A11,Korrelation!$D$4:$D$1197,Korrelation!H$4:H$1197,"-",0)="-",0,MATCH(_xlfn.XLOOKUP($A11,Korrelation!$D$4:$D$1197,Korrelation!H$4:H$1197,"",0),DMAV_Dienste!$F$6:$F$140,0))) -> 0 | F11: =IF($A11="","",IF(_xlfn.XLOOKUP($A11,Korrelation!$D$4:$D$1197,Korrelation!I$4:I$1197,"-",0)="-",0,MATCH(_xlfn.XLOOKUP($A11,Korrelation!$D$4:$D$1197,Korrelation!I$4:I$1197,"",0),DMAV_Dienste!$F$6:$F$140,0))) -> 0 | G11: =IF($A11="","",IF(_xlfn.XLOOKUP($A11,Korrelation!$D$4:$D$1197,Korrelation!J$4:J$1197,"-",0)="-",0,MATCH(_xlfn.XLOOKUP($A11,Korrelation!$D$4:$D$1197,Korrelation!J$4:J$1197,"",0),DMAV_Dienste!$F$6:$F$140,0))) -> 0 | H11: =IF($A11="","",IF(_xlfn.XLOOKUP($A11,Korrelation!$D$4:$D$1197,Korrelation!K$4:K$1197,"-",0)="-",0,MATCH(_xlfn.XLOOKUP($A11,Korrelation!$D$4:$D$1197,Korrelation!K$4:K$1197,"",0),'DM01-AV-CH'!$A$6:$A$834,0))) -> 0 | J11: {=IF(B11=0,IF(E11=0,"",HYPERLINK("#"&RIGHT(CELL("adresse",OFFSET(DMAV_Dienste!$M$6,E11-1,0)),LEN(CELL("adresse",OFFSET(DMAV_Dienste!$M$6,E11-1,0)))-FIND("]",CELL("adresse",OFFSET(DMAV_Dienste!$M$6,E11-1,0)))),"Dienst")),HYPERLINK("#"&RIGHT(CELL("adresse",OFFSET(DMAV_Modell!$N$6,B11-1,0)),LEN(CELL("adresse",OFFSET(DMAV_Modell!$N$6,B11-1,0)))-FIND("]",CELL("adresse",OFFSET(DMAV_Modell!$N$6,B11-1,0)))),"Modell"))} -> Modell | K11: {=IF($B11=0,IF($E11=0,"",IF(INDEX(DMAV_Dienste!P$6:P$140,$E11)="","",INDEX(DMAV_Dienste!P$6:P$140,$E11))),IF(INDEX(DMAV_Modell!Q$6:Q$838,$B11)="","",INDEX(DMAV_Modell!Q$6:Q$838,$B11)))} -> IMPORTS | L11: {=IF($B11=0,IF($E11=0,"",IF(INDEX(DMAV_Dienste!O$6:O$140,$E11)="","",INDEX(DMAV_Dienste!O$6:O$140,$E11))),IF(INDEX(DMAV_Modell!P$6:P$838,$B11)="","",INDEX(DMAV_Modell!P$6:P$838,$B11)))} | M11: {=IF($B11=0,IF($E11=0,"",IF(INDEX(DMAV_Dienste!Q$6:Q$140,$E11)="","",INDEX(DMAV_Dienste!Q$6:Q$140,$E11))),IF(INDEX(DMAV_Modell!R$6:R$838,$B11)="","",INDEX(DMAV_Modell!R$6:R$838,$B11)))} -> DMAV_Gebaeudeadressen_V1_1 | N11: {=IF($B11=0,IF($E11=0,"",IF(INDEX(DMAV_Dienste!T$6:T$140,$E11)="","",INDEX(DMAV_Dienste!T$6:T$140,$E11))),IF(INDEX(DMAV_Modell!U$6:U$838,$B11)="","",INDEX(DMAV_Modell!U$6:U$838,$B11)))} | O11: {=IF(C11=0,IF(F11=0,"",HYPERLINK("#"&RIGHT(CELL("adresse",OFFSET(DMAV_Dienste!$M$6,F11-1,0)),LEN(CELL("adresse",OFFSET(DMAV_Dienste!$M$6,F11-1,0)))-FIND("]",CELL("adresse",OFFSET(DMAV_Dienste!$M$6,F11-1,0)))),"Structure")),HYPERLINK("#"&RIGHT(CELL("adresse",OFFSET(DMAV_Modell!$N$6,C11-1,0)),LEN(CELL("adresse",OFFSET(DMAV_Modell!$N$6,C11-1,0)))-FIND("]",CELL("adresse",OFFSET(DMAV_Modell!$N$6,C11-1,0)))),"Structure"))} | P11: {=IF(D11=0,IF(G11=0,"",HYPERLINK("#"&RIGHT(CELL("adresse",OFFSET(DMAV_Dienste!$M$6,G11-1,0)),LEN(CELL("adresse",OFFSET(DMAV_Dienste!$M$6,G11-1,0)))-FIND("]",CELL("adresse",OFFSET(DMAV_Dienste!$M$6,G11-1,0)))),"Substructure")),HYPERLINK("#"&RIGHT(CELL("adresse",OFFSET(DMAV_Modell!$N$6,D11-1,0)),LEN(CELL("adresse",OFFSET(DMAV_Modell!$N$6,D11-1,0)))-FIND("]",CELL("adresse",OFFSET(DMAV_Modell!$N$6,D11-1,0)))),"Substructure"))} | AF11: {=IF(H11=0,"",HYPERLINK("#"&RIGHT(CELL("adresse",OFFSET('DM01-AV-CH'!$G$6,H11-1,0)),LEN(CELL("adresse",OFFSET('DM01-AV-CH'!$G$6,H11-1,0)))-FIND("]",CELL("adresse",OFFSET('DM01-AV-CH'!$G$6,H11-1,0)))),"Modell"))} | AG11: {=IF($H11=0,"",IF(INDEX('DM01-AV-CH'!G$6:G$834,$H11)="","",INDEX('DM01-AV-CH'!G$6:G$834,$H11)))} | AH11: {=IF($H11=0,"",IF(INDEX('DM01-AV-CH'!H$6:H$834,$H11)="","",INDEX('DM01-AV-CH'!H$6:H$834,$H11)))} | AI11: {=IF($H11=0,"",IF(INDEX('DM01-AV-CH'!I$6:I$834,$H11)="","",INDEX('DM01-AV-CH'!I$6:I$834,$H11)))}
A12: 7 | B12: =IF($A12="","",IF(_xlfn.XLOOKUP($A12,Korrelation!$D$4:$D$1197,Korrelation!E$4:E$1197,"-",0)="-",0,MATCH(_xlfn.XLOOKUP($A12,Korrelation!$D$4:$D$1197,Korrelation!E$4:E$1197,"",0),DMAV_Modell!$G$6:$G$677,0))) -> 7 | C12: =IF($A12="","",IF(_xlfn.XLOOKUP($A12,Korrelation!$D$4:$D$1197,Korrelation!F$4:F$1197,"-",0)="-",0,MATCH(_xlfn.XLOOKUP($A12,Korrelation!$D$4:$D$1197,Korrelation!F$4:F$1197,"",0),DMAV_Modell!$G$6:$G$677,0))) -> 0 | D12: =IF($A12="","",IF(_xlfn.XLOOKUP($A12,Korrelation!$D$4:$D$1197,Korrelation!G$4:G$1197,"-",0)="-",0,MATCH(_xlfn.XLOOKUP($A12,Korrelation!$D$4:$D$1197,Korrelation!G$4:G$1197,"",0),DMAV_Modell!$G$6:$G$677,0))) -> 0 | E12: =IF($A12="","",IF(_xlfn.XLOOKUP($A12,Korrelation!$D$4:$D$1197,Korrelation!H$4:H$1197,"-",0)="-",0,MATCH(_xlfn.XLOOKUP($A12,Korrelation!$D$4:$D$1197,Korrelation!H$4:H$1197,"",0),DMAV_Dienste!$F$6:$F$140,0))) -> 0 | F12: =IF($A12="","",IF(_xlfn.XLOOKUP($A12,Korrelation!$D$4:$D$1197,Korrelation!I$4:I$1197,"-",0)="-",0,MATCH(_xlfn.XLOOKUP($A12,Korrelation!$D$4:$D$1197,Korrelation!I$4:I$1197,"",0),DMAV_Dienste!$F$6:$F$140,0))) -> 0 | G12: =IF($A12="","",IF(_xlfn.XLOOKUP($A12,Korrelation!$D$4:$D$1197,Korrelation!J$4:J$1197,"-",0)="-",0,MATCH(_xlfn.XLOOKUP($A12,Korrelation!$D$4:$D$1197,Korrelation!J$4:J$1197,"",0),DMAV_Dienste!$F$6:$F$140,0))) -> 0 | H12: =IF($A12="","",IF(_xlfn.XLOOKUP($A12,Korrelation!$D$4:$D$1197,Korrelation!K$4:K$1197,"-",0)="-",0,MATCH(_xlfn.XLOOKUP($A12,Korrelation!$D$4:$D$1197,Korrelation!K$4:K$1197,"",0),'DM01-AV-CH'!$A$6:$A$834,0))) -> 0 | J12: {=IF(B12=0,IF(E12=0,"",HYPERLINK("#"&RIGHT(CELL("adresse",OFFSET(DMAV_Dienste!$M$6,E12-1,0)),LEN(CELL("adresse",OFFSET(DMAV_Dienste!$M$6,E12-1,0)))-FIND("]",CELL("adresse",OFFSET(DMAV_Dienste!$M$6,E12-1,0)))),"Dienst")),HYPERLINK("#"&RIGHT(CELL("adresse",OFFSET(DMAV_Modell!$N$6,B12-1,0)),LEN(CELL("adresse",OFFSET(DMAV_Modell!$N$6,B12-1,0)))-FIND("]",CELL("adresse",OFFSET(DMAV_Modell!$N$6,B12-1,0)))),"Modell"))} -> Modell | K12: {=IF($B12=0,IF($E12=0,"",IF(INDEX(DMAV_Dienste!P$6:P$140,$E12)="","",INDEX(DMAV_Dienste!P$6:P$140,$E12))),IF(INDEX(DMAV_Modell!Q$6:Q$838,$B12)="","",INDEX(DMAV_Modell!Q$6:Q$838,$B12)))} -> IMPORTS | L12: {=IF($B12=0,IF($E12=0,"",IF(INDEX(DMAV_Dienste!O$6:O$140,$E12)="","",INDEX(DMAV_Dienste!O$6:O$140,$E12))),IF(INDEX(DMAV_Modell!P$6:P$838,$B12)="","",INDEX(DMAV_Modell!P$6:P$838,$B12)))} | M12: {=IF($B12=0,IF($E12=0,"",IF(INDEX(DMAV_Dienste!Q$6:Q$140,$E12)="","",INDEX(DMAV_Dienste!Q$6:Q$140,$E12))),IF(INDEX(DMAV_Modell!R$6:R$838,$B12)="","",INDEX(DMAV_Modell!R$6:R$838,$B12)))} -> DMAV_Grundstuecke_V1_1 | N12: {=IF($B12=0,IF($E12=0,"",IF(INDEX(DMAV_Dienste!T$6:T$140,$E12)="","",INDEX(DMAV_Dienste!T$6:T$140,$E12))),IF(INDEX(DMAV_Modell!U$6:U$838,$B12)="","",INDEX(DMAV_Modell!U$6:U$838,$B12)))} | O12: {=IF(C12=0,IF(F12=0,"",HYPERLINK("#"&RIGHT(CELL("adresse",OFFSET(DMAV_Dienste!$M$6,F12-1,0)),LEN(CELL("adresse",OFFSET(DMAV_Dienste!$M$6,F12-1,0)))-FIND("]",CELL("adresse",OFFSET(DMAV_Dienste!$M$6,F12-1,0)))),"Structure")),HYPERLINK("#"&RIGHT(CELL("adresse",OFFSET(DMAV_Modell!$N$6,C12-1,0)),LEN(CELL("adresse",OFFSET(DMAV_Modell!$N$6,C12-1,0)))-FIND("]",CELL("adresse",OFFSET(DMAV_Modell!$N$6,C12-1,0)))),"Structure"))} | P12: {=IF(D12=0,IF(G12=0,"",HYPERLINK("#"&RIGHT(CELL("adresse",OFFSET(DMAV_Dienste!$M$6,G12-1,0)),LEN(CELL("adresse",OFFSET(DMAV_Dienste!$M$6,G12-1,0)))-FIND("]",CELL("adresse",OFFSET(DMAV_Dienste!$M$6,G12-1,0)))),"Substructure")),HYPERLINK("#"&RIGHT(CELL("adresse",OFFSET(DMAV_Modell!$N$6,D12-1,0)),LEN(CELL("adresse",OFFSET(DMAV_Modell!$N$6,D12-1,0)))-FIND("]",CELL("adresse",OFFSET(DMAV_Modell!$N$6,D12-1,0)))),"Substructure"))} | AF12: {=IF(H12=0,"",HYPERLINK("#"&RIGHT(CELL("adresse",OFFSET('DM01-AV-CH'!$G$6,H12-1,0)),LEN(CELL("adresse",OFFSET('DM01-AV-CH'!$G$6,H12-1,0)))-FIND("]",CELL("adresse",OFFSET('DM01-AV-CH'!$G$6,H12-1,0)))),"Modell"))} | AG12: {=IF($H12=0,"",IF(INDEX('DM01-AV-CH'!G$6:G$834,$H12)="","",INDEX('DM01-AV-CH'!G$6:G$834,$H12)))} | AH12: {=IF($H12=0,"",IF(INDEX('DM01-AV-CH'!H$6:H$834,$H12)="","",INDEX('DM01-AV-CH'!H$6:H$834,$H12)))} | AI12: {=IF($H12=0,"",IF(INDEX('DM01-AV-CH'!I$6:I$834,$H12)="","",INDEX('DM01-AV-CH'!I$6:I$834,$H12)))}
A13: 8 | B13: =IF($A13="","",IF(_xlfn.XLOOKUP($A13,Korrelation!$D$4:$D$1197,Korrelation!E$4:E$1197,"-",0)="-",0,MATCH(_xlfn.XLOOKUP($A13,Korrelation!$D$4:$D$1197,Korrelation!E$4:E$1197,"",0),DMAV_Modell!$G$6:$G$677,0))) -> 8 | C13: =IF($A13="","",IF(_xlfn.XLOOKUP($A13,Korrelation!$D$4:$D$1197,Korrelation!F$4:F$1197,"-",0)="-",0,MATCH(_xlfn.XLOOKUP($A13,Korrelation!$D$4:$D$1197,Korrelation!F$4:F$1197,"",0),DMAV_Modell!$G$6:$G$677,0))) -> 0 | D13: =IF($A13="","",IF(_xlfn.XLOOKUP($A13,Korrelation!$D$4:$D$1197,Korrelation!G$4:G$1197,"-",0)="-",0,MATCH(_xlfn.XLOOKUP($A13,Korrelation!$D$4:$D$1197,Korrelation!G$4:G$1197,"",0),DMAV_Modell!$G$6:$G$677,0))) -> 0 | E13: =IF($A13="","",IF(_xlfn.XLOOKUP($A13,Korrelation!$D$4:$D$1197,Korrelation!H$4:H$1197,"-",0)="-",0,MATCH(_xlfn.XLOOKUP($A13,Korrelation!$D$4:$D$1197,Korrelation!H$4:H$1197,"",0),DMAV_Dienste!$F$6:$F$140,0))) -> 0 | F13: =IF($A13="","",IF(_xlfn.XLOOKUP($A13,Korrelation!$D$4:$D$1197,Korrelation!I$4:I$1197,"-",0)="-",0,MATCH(_xlfn.XLOOKUP($A13,Korrelation!$D$4:$D$1197,Korrelation!I$4:I$1197,"",0),DMAV_Dienste!$F$6:$F$140,0))) -> 0 | G13: =IF($A13="","",IF(_xlfn.XLOOKUP($A13,Korrelation!$D$4:$D$1197,Korrelation!J$4:J$1197,"-",0)="-",0,MATCH(_xlfn.XLOOKUP($A13,Korrelation!$D$4:$D$1197,Korrelation!J$4:J$1197,"",0),DMAV_Dienste!$F$6:$F$140,0))) -> 0 | H13: =IF($A13="","",IF(_xlfn.XLOOKUP($A13,Korrelation!$D$4:$D$1197,Korrelation!K$4:K$1197,"-",0)="-",0,MATCH(_xlfn.XLOOKUP($A13,Korrelation!$D$4:$D$1197,Korrelation!K$4:K$1197,"",0),'DM01-AV-CH'!$A$6:$A$834,0))) -> 0 | J13: {=IF(B13=0,IF(E13=0,"",HYPERLINK("#"&RIGHT(CELL("adresse",OFFSET(DMAV_Dienste!$M$6,E13-1,0)),LEN(CELL("adresse",OFFSET(DMAV_Dienste!$M$6,E13-1,0)))-FIND("]",CELL("adresse",OFFSET(DMAV_Dienste!$M$6,E13-1,0)))),"Dienst")),HYPERLINK("#"&RIGHT(CELL("adresse",OFFSET(DMAV_Modell!$N$6,B13-1,0)),LEN(CELL("adresse",OFFSET(DMAV_Modell!$N$6,B13-1,0)))-FIND("]",CELL("adresse",OFFSET(DMAV_Modell!$N$6,B13-1,0)))),"Modell"))} -> Modell | K13: {=IF($B13=0,IF($E13=0,"",IF(INDEX(DMAV_Dienste!P$6:P$140,$E13)="","",INDEX(DMAV_Dienste!P$6:P$140,$E13))),IF(INDEX(DMAV_Modell!Q$6:Q$838,$B13)="","",INDEX(DMAV_Modell!Q$6:Q$838,$B13)))} -> IMPORTS | L13: {=IF($B13=0,IF($E13=0,"",IF(INDEX(DMAV_Dienste!O$6:O$140,$E13)="","",INDEX(DMAV_Dienste!O$6:O$140,$E13))),IF(INDEX(DMAV_Modell!P$6:P$838,$B13)="","",INDEX(DMAV_Modell!P$6:P$838,$B13)))} | M13: {=IF($B13=0,IF($E13=0,"",IF(INDEX(DMAV_Dienste!Q$6:Q$140,$E13)="","",INDEX(DMAV_Dienste!Q$6:Q$140,$E13))),IF(INDEX(DMAV_Modell!R$6:R$838,$B13)="","",INDEX(DMAV_Modell!R$6:R$838,$B13)))} -> DMAV_HoheitsgrenzenAV_V1_0 | N13: {=IF($B13=0,IF($E13=0,"",IF(INDEX(DMAV_Dienste!T$6:T$140,$E13)="","",INDEX(DMAV_Dienste!T$6:T$140,$E13))),IF(INDEX(DMAV_Modell!U$6:U$838,$B13)="","",INDEX(DMAV_Modell!U$6:U$838,$B13)))} | O13: {=IF(C13=0,IF(F13=0,"",HYPERLINK("#"&RIGHT(CELL("adresse",OFFSET(DMAV_Dienste!$M$6,F13-1,0)),LEN(CELL("adresse",OFFSET(DMAV_Dienste!$M$6,F13-1,0)))-FIND("]",CELL("adresse",OFFSET(DMAV_Dienste!$M$6,F13-1,0)))),"Structure")),HYPERLINK("#"&RIGHT(CELL("adresse",OFFSET(DMAV_Modell!$N$6,C13-1,0)),LEN(CELL("adresse",OFFSET(DMAV_Modell!$N$6,C13-1,0)))-FIND("]",CELL("adresse",OFFSET(DMAV_Modell!$N$6,C13-1,0)))),"Structure"))} | P13: {=IF(D13=0,IF(G13=0,"",HYPERLINK("#"&RIGHT(CELL("adresse",OFFSET(DMAV_Dienste!$M$6,G13-1,0)),LEN(CELL("adresse",OFFSET(DMAV_Dienste!$M$6,G13-1,0)))-FIND("]",CELL("adresse",OFFSET(DMAV_Dienste!$M$6,G13-1,0)))),"Substructure")),HYPERLINK("#"&RIGHT(CELL("adresse",OFFSET(DMAV_Modell!$N$6,D13-1,0)),LEN(CELL("adresse",OFFSET(DMAV_Modell!$N$6,D13-1,0)))-FIND("]",CELL("adresse",OFFSET(DMAV_Modell!$N$6,D13-1,0)))),"Substructure"))} | AF13: {=IF(H13=0,"",HYPERLINK("#"&RIGHT(CELL("adresse",OFFSET('DM01-AV-CH'!$G$6,H13-1,0)),LEN(CELL("adresse",OFFSET('DM01-AV-CH'!$G$6,H13-1,0)))-FIND("]",CELL("adresse",OFFSET('DM01-AV-CH'!$G$6,H13-1,0)))),"Modell"))} | AG13: {=IF($H13=0,"",IF(INDEX('DM01-AV-CH'!G$6:G$834,$H13)="","",INDEX('DM01-AV-CH'!G$6:G$834,$H13)))} | AH13: {=IF($H13=0,"",IF(INDEX('DM01-AV-CH'!H$6:H$834,$H13)="","",INDEX('DM01-AV-CH'!H$6:H$834,$H13)))} | AI13: {=IF($H13=0,"",IF(INDEX('DM01-AV-CH'!I$6:I$834,$H13)="","",INDEX('DM01-AV-CH'!I$6:I$834,$H13)))}
A14: 9 | B14: =IF($A14="","",IF(_xlfn.XLOOKUP($A14,Korrelation!$D$4:$D$1197,Korrelation!E$4:E$1197,"-",0)="-",0,MATCH(_xlfn.XLOOKUP($A14,Korrelation!$D$4:$D$1197,Korrelation!E$4:E$1197,"",0),DMAV_Modell!$G$6:$G$677,0))) -> 9 | C14: =IF($A14="","",IF(_xlfn.XLOOKUP($A14,Korrelation!$D$4:$D$1197,Korrelation!F$4:F$1197,"-",0)="-",0,MATCH(_xlfn.XLOOKUP($A14,Korrelation!$D$4:$D$1197,Korrelation!F$4:F$1197,"",0),DMAV_Modell!$G$6:$G$677,0))) -> 0 | D14: =IF($A14="","",IF(_xlfn.XLOOKUP($A14,Korrelation!$D$4:$D$1197,Korrelation!G$4:G$1197,"-",0)="-",0,MATCH(_xlfn.XLOOKUP($A14,Korrelation!$D$4:$D$1197,Korrelation!G$4:G$1197,"",0),DMAV_Modell!$G$6:$G$677,0))) -> 0 | E14: =IF($A14="","",IF(_xlfn.XLOOKUP($A14,Korrelation!$D$4:$D$1197,Korrelation!H$4:H$1197,"-",0)="-",0,MATCH(_xlfn.XLOOKUP($A14,Korrelation!$D$4:$D$1197,Korrelation!H$4:H$1197,"",0),DMAV_Dienste!$F$6:$F$140,0))) -> 0 | F14: =IF($A14="","",IF(_xlfn.XLOOKUP($A14,Korrelation!$D$4:$D$1197,Korrelation!I$4:I$1197,"-",0)="-",0,MATCH(_xlfn.XLOOKUP($A14,Korrelation!$D$4:$D$1197,Korrelation!I$4:I$1197,"",0),DMAV_Dienste!$F$6:$F$140,0))) -> 0 | G14: =IF($A14="","",IF(_xlfn.XLOOKUP($A14,Korrelation!$D$4:$D$1197,Korrelation!J$4:J$1197,"-",0)="-",0,MATCH(_xlfn.XLOOKUP($A14,Korrelation!$D$4:$D$1197,Korrelation!J$4:J$1197,"",0),DMAV_Dienste!$F$6:$F$140,0))) -> 0 | H14: =IF($A14="","",IF(_xlfn.XLOOKUP($A14,Korrelation!$D$4:$D$1197,Korrelation!K$4:K$1197,"-",0)="-",0,MATCH(_xlfn.XLOOKUP($A14,Korrelation!$D$4:$D$1197,Korrelation!K$4:K$1197,"",0),'DM01-AV-CH'!$A$6:$A$834,0))) -> 0 | J14: {=IF(B14=0,IF(E14=0,"",HYPERLINK("#"&RIGHT(CELL("adresse",OFFSET(DMAV_Dienste!$M$6,E14-1,0)),LEN(CELL("adresse",OFFSET(DMAV_Dienste!$M$6,E14-1,0)))-FIND("]",CELL("adresse",OFFSET(DMAV_Dienste!$M$6,E14-1,0)))),"Dienst")),HYPERLINK("#"&RIGHT(CELL("adresse",OFFSET(DMAV_Modell!$N$6,B14-1,0)),LEN(CELL("adresse",OFFSET(DMAV_Modell!$N$6,B14-1,0)))-FIND("]",CELL("adresse",OFFSET(DMAV_Modell!$N$6,B14-1,0)))),"Modell"))} -> Modell | K14: {=IF($B14=0,IF($E14=0,"",IF(INDEX(DMAV_Dienste!P$6:P$140,$E14)="","",INDEX(DMAV_Dienste!P$6:P$140,$E14))),IF(INDEX(DMAV_Modell!Q$6:Q$838,$B14)="","",INDEX(DMAV_Modell!Q$6:Q$838,$B14)))} -> IMPORTS | L14: {=IF($B14=0,IF($E14=0,"",IF(INDEX(DMAV_Dienste!O$6:O$140,$E14)="","",INDEX(DMAV_Dienste!O$6:O$140,$E14))),IF(INDEX(DMAV_Modell!P$6:P$838,$B14)="","",INDEX(DMAV_Modell!P$6:P$838,$B14)))} | M14: {=IF($B14=0,IF($E14=0,"",IF(INDEX(DMAV_Dienste!Q$6:Q$140,$E14)="","",INDEX(DMAV_Dienste!Q$6:Q$140,$E14))),IF(INDEX(DMAV_Modell!R$6:R$838,$B14)="","",INDEX(DMAV_Modell!R$6:R$838,$B14)))} -> DMAV_Nomenklatur_V1_1 | N14: {=IF($B14=0,IF($E14=0,"",IF(INDEX(DMAV_Dienste!T$6:T$140,$E14)="","",INDEX(DMAV_Dienste!T$6:T$140,$E14))),IF(INDEX(DMAV_Modell!U$6:U$838,$B14)="","",INDEX(DMAV_Modell!U$6:U$838,$B14)))} | O14: {=IF(C14=0,IF(F14=0,"",HYPERLINK("#"&RIGHT(CELL("adresse",OFFSET(DMAV_Dienste!$M$6,F14-1,0)),LEN(CELL("adresse",OFFSET(DMAV_Dienste!$M$6,F14-1,0)))-FIND("]",CELL("adresse",OFFSET(DMAV_Dienste!$M$6,F14-1,0)))),"Structure")),HYPERLINK("#"&RIGHT(CELL("adresse",OFFSET(DMAV_Modell!$N$6,C14-1,0)),LEN(CELL("adresse",OFFSET(DMAV_Modell!$N$6,C14-1,0)))-FIND("]",CELL("adresse",OFFSET(DMAV_Modell!$N$6,C14-1,0)))),"Structure"))} | P14: {=IF(D14=0,IF(G14=0,"",HYPERLINK("#"&RIGHT(CELL("adresse",OFFSET(DMAV_Dienste!$M$6,G14-1,0)),LEN(CELL("adresse",OFFSET(DMAV_Dienste!$M$6,G14-1,0)))-FIND("]",CELL("adresse",OFFSET(DMAV_Dienste!$M$6,G14-1,0)))),"Substructure")),HYPERLINK("#"&RIGHT(CELL("adresse",OFFSET(DMAV_Modell!$N$6,D14-1,0)),LEN(CELL("adresse",OFFSET(DMAV_Modell!$N$6,D14-1,0)))-FIND("]",CELL("adresse",OFFSET(DMAV_Modell!$N$6,D14-1,0)))),"Substructure"))} | AF14: {=IF(H14=0,"",HYPERLINK("#"&RIGHT(CELL("adresse",OFFSET('DM01-AV-CH'!$G$6,H14-1,0)),LEN(CELL("adresse",OFFSET('DM01-AV-CH'!$G$6,H14-1,0)))-FIND("]",CELL("adresse",OFFSET('DM01-AV-CH'!$G$6,H14-1,0)))),"Modell"))} | AG14: {=IF($H14=0,"",IF(INDEX('DM01-AV-CH'!G$6:G$834,$H14)="","",INDEX('DM01-AV-CH'!G$6:G$834,$H14)))} | AH14: {=IF($H14=0,"",IF(INDEX('DM01-AV-CH'!H$6:H$834,$H14)="","",INDEX('DM01-AV-CH'!H$6:H$834,$H14)))} | AI14: {=IF($H14=0,"",IF(INDEX('DM01-AV-CH'!I$6:I$834,$H14)="","",INDEX('DM01-AV-CH'!I$6:I$834,$H14)))}
A15: 10 | B15: =IF($A15="","",IF(_xlfn.XLOOKUP($A15,Korrelation!$D$4:$D$1197,Korrelation!E$4:E$1197,"-",0)="-",0,MATCH(_xlfn.XLOOKUP($A15,Korrelation!$D$4:$D$1197,Korrelation!E$4:E$1197,"",0),DMAV_Modell!$G$6:$G$677,0))) -> 10 | C15: =IF($A15="","",IF(_xlfn.XLOOKUP($A15,Korrelation!$D$4:$D$1197,Korrelation!F$4:F$1197,"-",0)="-",0,MATCH(_xlfn.XLOOKUP($A15,Korrelation!$D$4:$D$1197,Korrelation!F$4:F$1197,"",0),DMAV_Modell!$G$6:$G$677,0))) -> 0 | D15: =IF($A15="","",IF(_xlfn.XLOOKUP($A15,Korrelation!$D$4:$D$1197,Korrelation!G$4:G$1197,"-",0)="-",0,MATCH(_xlfn.XLOOKUP($A15,Korrelation!$D$4:$D$1197,Korrelation!G$4:G$1197,"",0),DMAV_Modell!$G$6:$G$677,0))) -> 0 | E15: =IF($A15="","",IF(_xlfn.XLOOKUP($A15,Korrelation!$D$4:$D$1197,Korrelation!H$4:H$1197,"-",0)="-",0,MATCH(_xlfn.XLOOKUP($A15,Korrelation!$D$4:$D$1197,Korrelation!H$4:H$1197,"",0),DMAV_Dienste!$F$6:$F$140,0))) -> 0 | F15: =IF($A15="","",IF(_xlfn.XLOOKUP($A15,Korrelation!$D$4:$D$1197,Korrelation!I$4:I$1197,"-",0)="-",0,MATCH(_xlfn.XLOOKUP($A15,Korrelation!$D$4:$D$1197,Korrelation!I$4:I$1197,"",0),DMAV_Dienste!$F$6:$F$140,0))) -> 0 | G15: =IF($A15="","",IF(_xlfn.XLOOKUP($A15,Korrelation!$D$4:$D$1197,Korrelation!J$4:J$1197,"-",0)="-",0,MATCH(_xlfn.XLOOKUP($A15,Korrelation!$D$4:$D$1197,Korrelation!J$4:J$1197,"",0),DMAV_Dienste!$F$6:$F$140,0))) -> 0 | H15: =IF($A15="","",IF(_xlfn.XLOOKUP($A15,Korrelation!$D$4:$D$1197,Korrelation!K$4:K$1197,"-",0)="-",0,MATCH(_xlfn.XLOOKUP($A15,Korrelation!$D$4:$D$1197,Korrelation!K$4:K$1197,"",0),'DM01-AV-CH'!$A$6:$A$834,0))) -> 0 | J15: {=IF(B15=0,IF(E15=0,"",HYPERLINK("#"&RIGHT(CELL("adresse",OFFSET(DMAV_Dienste!$M$6,E15-1,0)),LEN(CELL("adresse",OFFSET(DMAV_Dienste!$M$6,E15-1,0)))-FIND("]",CELL("adresse",OFFSET(DMAV_Dienste!$M$6,E15-1,0)))),"Dienst")),HYPERLINK("#"&RIGHT(CELL("adresse",OFFSET(DMAV_Modell!$N$6,B15-1,0)),LEN(CELL("adresse",OFFSET(DMAV_Modell!$N$6,B15-1,0)))-FIND("]",CELL("adresse",OFFSET(DMAV_Modell!$N$6,B15-1,0)))),"Modell"))} -> Modell | K15: {=IF($B15=0,IF($E15=0,"",IF(INDEX(DMAV_Dienste!P$6:P$140,$E15)="","",INDEX(DMAV_Dienste!P$6:P$140,$E15))),IF(INDEX(DMAV_Modell!Q$6:Q$838,$B15)="","",INDEX(DMAV_Modell!Q$6:Q$838,$B15)))} -> IMPORTS | L15: {=IF($B15=0,IF($E15=0,"",IF(INDEX(DMAV_Dienste!O$6:O$140,$E15)="","",INDEX(DMAV_Dienste!O$6:O$140,$E15))),IF(INDEX(DMAV_Modell!P$6:P$838,$B15)="","",INDEX(DMAV_Modell!P$6:P$838,$B15)))} | M15: {=IF($B15=0,IF($E15=0,"",IF(INDEX(DMAV_Dienste!Q$6:Q$140,$E15)="","",INDEX(DMAV_Dienste!Q$6:Q$140,$E15))),IF(INDEX(DMAV_Modell!R$6:R$838,$B15)="","",INDEX(DMAV_Modell!R$6:R$838,$B15)))} -> DMAV_Rohrleitungen_V1_1 | N15: {=IF($B15=0,IF($E15=0,"",IF(INDEX(DMAV_Dienste!T$6:T$140,$E15)="","",INDEX(DMAV_Dienste!T$6:T$140,$E15))),IF(INDEX(DMAV_Modell!U$6:U$838,$B15)="","",INDEX(DMAV_Modell!U$6:U$838,$B15)))} | O15: {=IF(C15=0,IF(F15=0,"",HYPERLINK("#"&RIGHT(CELL("adresse",OFFSET(DMAV_Dienste!$M$6,F15-1,0)),LEN(CELL("adresse",OFFSET(DMAV_Dienste!$M$6,F15-1,0)))-FIND("]",CELL("adresse",OFFSET(DMAV_Dienste!$M$6,F15-1,0)))),"Structure")),HYPERLINK("#"&RIGHT(CELL("adresse",OFFSET(DMAV_Modell!$N$6,C15-1,0)),LEN(CELL("adresse",OFFSET(DMAV_Modell!$N$6,C15-1,0)))-FIND("]",CELL("adresse",OFFSET(DMAV_Modell!$N$6,C15-1,0)))),"Structure"))} | P15: {=IF(D15=0,IF(G15=0,"",HYPERLINK("#"&RIGHT(CELL("adresse",OFFSET(DMAV_Dienste!$M$6,G15-1,0)),LEN(CELL("adresse",OFFSET(DMAV_Dienste!$M$6,G15-1,0)))-FIND("]",CELL("adresse",OFFSET(DMAV_Dienste!$M$6,G15-1,0)))),"Substructure")),HYPERLINK("#"&RIGHT(CELL("adresse",OFFSET(DMAV_Modell!$N$6,D15-1,0)),LEN(CELL("adresse",OFFSET(DMAV_Modell!$N$6,D15-1,0)))-FIND("]",CELL("adresse",OFFSET(DMAV_Modell!$N$6,D15-1,0)))),"Substructure"))} | AF15: {=IF(H15=0,"",HYPERLINK("#"&RIGHT(CELL("adresse",OFFSET('DM01-AV-CH'!$G$6,H15-1,0)),LEN(CELL("adresse",OFFSET('DM01-AV-CH'!$G$6,H15-1,0)))-FIND("]",CELL("adresse",OFFSET('DM01-AV-CH'!$G$6,H15-1,0)))),"Modell"))} | AG15: {=IF($H15=0,"",IF(INDEX('DM01-AV-CH'!G$6:G$834,$H15)="","",INDEX('DM01-AV-CH'!G$6:G$834,$H15)))} | AH15: {=IF($H15=0,"",IF(INDEX('DM01-AV-CH'!H$6:H$834,$H15)="","",INDEX('DM01-AV-CH'!H$6:H$834,$H15)))} | AI15: {=IF($H15=0,"",IF(INDEX('DM01-AV-CH'!I$6:I$834,$H15)="","",INDEX('DM01-AV-CH'!I$6:I$834,$H15)))}
A16: 11 | B16: =IF($A16="","",IF(_xlfn.XLOOKUP($A16,Korrelation!$D$4:$D$1197,Korrelation!E$4:E$1197,"-",0)="-",0,MATCH(_xlfn.XLOOKUP($A16,Korrelation!$D$4:$D$1197,Korrelation!E$4:E$1197,"",0),DMAV_Modell!$G$6:$G$677,0))) -> 11 | C16: =IF($A16="","",IF(_xlfn.XLOOKUP($A16,Korrelation!$D$4:$D$1197,Korrelation!F$4:F$1197,"-",0)="-",0,MATCH(_xlfn.XLOOKUP($A16,Korrelation!$D$4:$D$1197,Korrelation!F$4:F$1197,"",0),DMAV_Modell!$G$6:$G$677,0))) -> 0 | D16: =IF($A16="","",IF(_xlfn.XLOOKUP($A16,Korrelation!$D$4:$D$1197,Korrelation!G$4:G$1197,"-",0)="-",0,MATCH(_xlfn.XLOOKUP($A16,Korrelation!$D$4:$D$1197,Korrelation!G$4:G$1197,"",0),DMAV_Modell!$G$6:$G$677,0))) -> 0 | E16: =IF($A16="","",IF(_xlfn.XLOOKUP($A16,Korrelation!$D$4:$D$1197,Korrelation!H$4:H$1197,"-",0)="-",0,MATCH(_xlfn.XLOOKUP($A16,Korrelation!$D$4:$D$1197,Korrelation!H$4:H$1197,"",0),DMAV_Dienste!$F$6:$F$140,0))) -> 0 | F16: =IF($A16="","",IF(_xlfn.XLOOKUP($A16,Korrelation!$D$4:$D$1197,Korrelation!I$4:I$1197,"-",0)="-",0,MATCH(_xlfn.XLOOKUP($A16,Korrelation!$D$4:$D$1197,Korrelation!I$4:I$1197,"",0),DMAV_Dienste!$F$6:$F$140,0))) -> 0 | G16: =IF($A16="","",IF(_xlfn.XLOOKUP($A16,Korrelation!$D$4:$D$1197,Korrelation!J$4:J$1197,"-",0)="-",0,MATCH(_xlfn.XLOOKUP($A16,Korrelation!$D$4:$D$1197,Korrelation!J$4:J$1197,"",0),DMAV_Dienste!$F$6:$F$140,0))) -> 0 | H16: =IF($A16="","",IF(_xlfn.XLOOKUP($A16,Korrelation!$D$4:$D$1197,Korrelation!K$4:K$1197,"-",0)="-",0,MATCH(_xlfn.XLOOKUP($A16,Korrelation!$D$4:$D$1197,Korrelation!K$4:K$1197,"",0),'DM01-AV-CH'!$A$6:$A$834,0))) -> 0 | J16: {=IF(B16=0,IF(E16=0,"",HYPERLINK("#"&RIGHT(CELL("adresse",OFFSET(DMAV_Dienste!$M$6,E16-1,0)),LEN(CELL("adresse",OFFSET(DMAV_Dienste!$M$6,E16-1,0)))-FIND("]",CELL("adresse",OFFSET(DMAV_Dienste!$M$6,E16-1,0)))),"Dienst")),HYPERLINK("#"&RIGHT(CELL("adresse",OFFSET(DMAV_Modell!$N$6,B16-1,0)),LEN(CELL("adresse",OFFSET(DMAV_Modell!$N$6,B16-1,0)))-FIND("]",CELL("adresse",OFFSET(DMAV_Modell!$N$6,B16-1,0)))),"Modell"))} -> Modell | K16: {=IF($B16=0,IF($E16=0,"",IF(INDEX(DMAV_Dienste!P$6:P$140,$E16)="","",INDEX(DMAV_Dienste!P$6:P$140,$E16))),IF(INDEX(DMAV_Modell!Q$6:Q$838,$B16)="","",INDEX(DMAV_Modell!Q$6:Q$838,$B16)))} -> IMPORTS | L16: {=IF($B16=0,IF($E16=0,"",IF(INDEX(DMAV_Dienste!O$6:O$140,$E16)="","",INDEX(DMAV_Dienste!O$6:O$140,$E16))),IF(INDEX(DMAV_Modell!P$6:P$838,$B16)="","",INDEX(DMAV_Modell!P$6:P$838,$B16)))} | M16: {=IF($B16=0,IF($E16=0,"",IF(INDEX(DMAV_Dienste!Q$6:Q$140,$E16)="","",INDEX(DMAV_Dienste!Q$6:Q$140,$E16))),IF(INDEX(DMAV_Modell!R$6:R$838,$B16)="","",INDEX(DMAV_Modell!R$6:R$838,$B16)))} -> DMAV_Toleranzstufen_V1_1 | N16: {=IF($B16=0,IF($E16=0,"",IF(INDEX(DMAV_Dienste!T$6:T$140,$E16)="","",INDEX(DMAV_Dienste!T$6:T$140,$E16))),IF(INDEX(DMAV_Modell!U$6:U$838,$B16)="","",INDEX(DMAV_Modell!U$6:U$838,$B16)))} | O16: {=IF(C16=0,IF(F16=0,"",HYPERLINK("#"&RIGHT(CELL("adresse",OFFSET(DMAV_Dienste!$M$6,F16-1,0)),LEN(CELL("adresse",OFFSET(DMAV_Dienste!$M$6,F16-1,0)))-FIND("]",CELL("adresse",OFFSET(DMAV_Dienste!$M$6,F16-1,0)))),"Structure")),HYPERLINK("#"&RIGHT(CELL("adresse",OFFSET(DMAV_Modell!$N$6,C16-1,0)),LEN(CELL("adresse",OFFSET(DMAV_Modell!$N$6,C16-1,0)))-FIND("]",CELL("adresse",OFFSET(DMAV_Modell!$N$6,C16-1,0)))),"Structure"))} | P16: {=IF(D16=0,IF(G16=0,"",HYPERLINK("#"&RIGHT(CELL("adresse",OFFSET(DMAV_Dienste!$M$6,G16-1,0)),LEN(CELL("adresse",OFFSET(DMAV_Dienste!$M$6,G16-1,0)))-FIND("]",CELL("adresse",OFFSET(DMAV_Dienste!$M$6,G16-1,0)))),"Substructure")),HYPERLINK("#"&RIGHT(CELL("adresse",OFFSET(DMAV_Modell!$N$6,D16-1,0)),LEN(CELL("adresse",OFFSET(DMAV_Modell!$N$6,D16-1,0)))-FIND("]",CELL("adresse",OFFSET(DMAV_Modell!$N$6,D16-1,0)))),"Substructure"))} | AF16: {=IF(H16=0,"",HYPERLINK("#"&RIGHT(CELL("adresse",OFFSET('DM01-AV-CH'!$G$6,H16-1,0)),LEN(CELL("adresse",OFFSET('DM01-AV-CH'!$G$6,H16-1,0)))-FIND("]",CELL("adresse",OFFSET('DM01-AV-CH'!$G$6,H16-1,0)))),"Modell"))} | AG16: {=IF($H16=0,"",IF(INDEX('DM01-AV-CH'!G$6:G$834,$H16)="","",INDEX('DM01-AV-CH'!G$6:G$834,$H16)))} | AH16: {=IF($H16=0,"",IF(INDEX('DM01-AV-CH'!H$6:H$834,$H16)="","",INDEX('DM01-AV-CH'!H$6:H$834,$H16)))} | AI16: {=IF($H16=0,"",IF(INDEX('DM01-AV-CH'!I$6:I$834,$H16)="","",INDEX('DM01-AV-CH'!I$6:I$834,$H16)))}
A17: 12 | B17: =IF($A17="","",IF(_xlfn.XLOOKUP($A17,Korrelation!$D$4:$D$1197,Korrelation!E$4:E$1197,"-",0)="-",0,MATCH(_xlfn.XLOOKUP($A17,Korrelation!$D$4:$D$1197,Korrelation!E$4:E$1197,"",0),DMAV_Modell!$G$6:$G$677,0))) -> 12 | C17: =IF($A17="","",IF(_xlfn.XLOOKUP($A17,Korrelation!$D$4:$D$1197,Korrelation!F$4:F$1197,"-",0)="-",0,MATCH(_xlfn.XLOOKUP($A17,Korrelation!$D$4:$D$1197,Korrelation!F$4:F$1197,"",0),DMAV_Modell!$G$6:$G$677,0))) -> 0 | D17: =IF($A17="","",IF(_xlfn.XLOOKUP($A17,Korrelation!$D$4:$D$1197,Korrelation!G$4:G$1197,"-",0)="-",0,MATCH(_xlfn.XLOOKUP($A17,Korrelation!$D$4:$D$1197,Korrelation!G$4:G$1197,"",0),DMAV_Modell!$G$6:$G$677,0))) -> 0 | E17: =IF($A17="","",IF(_xlfn.XLOOKUP($A17,Korrelation!$D$4:$D$1197,Korrelation!H$4:H$1197,"-",0)="-",0,MATCH(_xlfn.XLOOKUP($A17,Korrelation!$D$4:$D$1197,Korrelation!H$4:H$1197,"",0),DMAV_Dienste!$F$6:$F$140,0))) -> 0 | F17: =IF($A17="","",IF(_xlfn.XLOOKUP($A17,Korrelation!$D$4:$D$1197,Korrelation!I$4:I$1197,"-",0)="-",0,MATCH(_xlfn.XLOOKUP($A17,Korrelation!$D$4:$D$1197,Korrelation!I$4:I$1197,"",0),DMAV_Dienste!$F$6:$F$140,0))) -> 0 | G17: =IF($A17="","",IF(_xlfn.XLOOKUP($A17,Korrelation!$D$4:$D$1197,Korrelation!J$4:J$1197,"-",0)="-",0,MATCH(_xlfn.XLOOKUP($A17,Korrelation!$D$4:$D$1197,Korrelation!J$4:J$1197,"",0),DMAV_Dienste!$F$6:$F$140,0))) -> 0 | H17: =IF($A17="","",IF(_xlfn.XLOOKUP($A17,Korrelation!$D$4:$D$1197,Korrelation!K$4:K$1197,"-",0)="-",0,MATCH(_xlfn.XLOOKUP($A17,Korrelation!$D$4:$D$1197,Korrelation!K$4:K$1197,"",0),'DM01-AV-CH'!$A$6:$A$834,0))) -> 0 | J17: {=IF(B17=0,IF(E17=0,"",HYPERLINK("#"&RIGHT(CELL("adresse",OFFSET(DMAV_Dienste!$M$6,E17-1,0)),LEN(CELL("adresse",OFFSET(DMAV_Dienste!$M$6,E17-1,0)))-FIND("]",CELL("adresse",OFFSET(DMAV_Dienste!$M$6,E17-1,0)))),"Dienst")),HYPERLINK("#"&RIGHT(CELL("adresse",OFFSET(DMAV_Modell!$N$6,B17-1,0)),LEN(CELL("adresse",OFFSET(DMAV_Modell!$N$6,B17-1,0)))-FIND("]",CELL("adresse",OFFSET(DMAV_Modell!$N$6,B17-1,0)))),"Modell"))} -> Modell | K17: {=IF($B17=0,IF($E17=0,"",IF(INDEX(DMAV_Dienste!P$6:P$140,$E17)="","",INDEX(DMAV_Dienste!P$6:P$140,$E17))),IF(INDEX(DMAV_Modell!Q$6:Q$838,$B17)="","",INDEX(DMAV_Modell!Q$6:Q$838,$B17)))} -> IMPORTS | L17: {=IF($B17=0,IF($E17=0,"",IF(INDEX(DMAV_Dienste!O$6:O$140,$E17)="","",INDEX(DMAV_Dienste!O$6:O$140,$E17))),IF(INDEX(DMAV_Modell!P$6:P$838,$B17)="","",INDEX(DMAV_Modell!P$6:P$838,$B17)))} | M17: {=IF($B17=0,IF($E17=0,"",IF(INDEX(DMAV_Dienste!Q$6:Q$140,$E17)="","",INDEX(DMAV_Dienste!Q$6:Q$140,$E17))),IF(INDEX(DMAV_Modell!R$6:R$838,$B17)="","",INDEX(DMAV_Modell!R$6:R$838,$B17)))} -> DMAVSUP_UntereinheitGrundbuch_V1_1 | N17: {=IF($B17=0,IF($E17=0,"",IF(INDEX(DMAV_Dienste!T$6:T$140,$E17)="","",INDEX(DMAV_Dienste!T$6:T$140,$E17))),IF(INDEX(DMAV_Modell!U$6:U$838,$B17)="","",INDEX(DMAV_Modell!U$6:U$838,$B17)))} | O17: {=IF(C17=0,IF(F17=0,"",HYPERLINK("#"&RIGHT(CELL("adresse",OFFSET(DMAV_Dienste!$M$6,F17-1,0)),LEN(CELL("adresse",OFFSET(DMAV_Dienste!$M$6,F17-1,0)))-FIND("]",CELL("adresse",OFFSET(DMAV_Dienste!$M$6,F17-1,0)))),"Structure")),HYPERLINK("#"&RIGHT(CELL("adresse",OFFSET(DMAV_Modell!$N$6,C17-1,0)),LEN(CELL("adresse",OFFSET(DMAV_Modell!$N$6,C17-1,0)))-FIND("]",CELL("adresse",OFFSET(DMAV_Modell!$N$6,C17-1,0)))),"Structure"))} | P17: {=IF(D17=0,IF(G17=0,"",HYPERLINK("#"&RIGHT(CELL("adresse",OFFSET(DMAV_Dienste!$M$6,G17-1,0)),LEN(CELL("adresse",OFFSET(DMAV_Dienste!$M$6,G17-1,0)))-FIND("]",CELL("adresse",OFFSET(DMAV_Dienste!$M$6,G17-1,0)))),"Substructure")),HYPERLINK("#"&RIGHT(CELL("adresse",OFFSET(DMAV_Modell!$N$6,D17-1,0)),LEN(CELL("adresse",OFFSET(DMAV_Modell!$N$6,D17-1,0)))-FIND("]",CELL("adresse",OFFSET(DMAV_Modell!$N$6,D17-1,0)))),"Substructure"))} | AF17: {=IF(H17=0,"",HYPERLINK("#"&RIGHT(CELL("adresse",OFFSET('DM01-AV-CH'!$G$6,H17-1,0)),LEN(CELL("adresse",OFFSET('DM01-AV-CH'!$G$6,H17-1,0)))-FIND("]",CELL("adresse",OFFSET('DM01-AV-CH'!$G$6,H17-1,0)))),"Modell"))} | AG17: {=IF($H17=0,"",IF(INDEX('DM01-AV-CH'!G$6:G$834,$H17)="","",INDEX('DM01-AV-CH'!G$6:G$834,$H17)))} | AH17: {=IF($H17=0,"",IF(INDEX('DM01-AV-CH'!H$6:H$834,$H17)="","",INDEX('DM01-AV-CH'!H$6:H$834,$H17)))} | AI17: {=IF($H17=0,"",IF(INDEX('DM01-AV-CH'!I$6:I$834,$H17)="","",INDEX('DM01-AV-CH'!I$6:I$834,$H17)))}
... A50: 45 | B50: =IF($A50="","",IF(_xlfn.XLOOKUP($A50,Korrelation!$D$4:$D$1197,Korrelation!E$4:E$1197,"-",0)="-",0,MATCH(_xlfn.XLOOKUP($A50,Korrelation!$D$4:$D$1197,Korrelation!E$4:E$1197,"",0),DMAV_Modell!$G$6:$G$677,0))) -> 40 | C50: =IF($A50="","",IF(_xlfn.XLOOKUP($A50,Korrelation!$D$4:$D$1197,Korrelation!F$4:F$1197,"-",0)="-",0,MATCH(_xlfn.XLOOKUP($A50,Korrelation!$D$4:$D$1197,Korrelation!F$4:F$1197,"",0),DMAV_Modell!$G$6:$G$677,0))) -> 0 | D50: =IF($A50="","",IF(_xlfn.XLOOKUP($A50,Korrelation!$D$4:$D$1197,Korrelation!G$4:G$1197,"-",0)="-",0,MATCH(_xlfn.XLOOKUP($A50,Korrelation!$D$4:$D$1197,Korrelation!G$4:G$1197,"",0),DMAV_Modell!$G$6:$G$677,0))) -> 0 | E50: =IF($A50="","",IF(_xlfn.XLOOKUP($A50,Korrelation!$D$4:$D$1197,Korrelation!H$4:H$1197,"-",0)="-",0,MATCH(_xlfn.XLOOKUP($A50,Korrelation!$D$4:$D$1197,Korrelation!H$4:H$1197,"",0),DMAV_Dienste!$F$6:$F$140,0))) -> 0 | F50: =IF($A50="","",IF(_xlfn.XLOOKUP($A50,Korrelation!$D$4:$D$1197,Korrelation!I$4:I$1197,"-",0)="-",0,MATCH(_xlfn.XLOOKUP($A50,Korrelation!$D$4:$D$1197,Korrelation!I$4:I$1197,"",0),DMAV_Dienste!$F$6:$F$140,0))) -> 0 | G50: =IF($A50="","",IF(_xlfn.XLOOKUP($A50,Korrelation!$D$4:$D$1197,Korrelation!J$4:J$1197,"-",0)="-",0,MATCH(_xlfn.XLOOKUP($A50,Korrelation!$D$4:$D$1197,Korrelation!J$4:J$1197,"",0),DMAV_Dienste!$F$6:$F$140,0))) -> 0 | H50: =IF($A50="","",IF(_xlfn.XLOOKUP($A50,Korrelation!$D$4:$D$1197,Korrelation!K$4:K$1197,"-",0)="-",0,MATCH(_xlfn.XLOOKUP($A50,Korrelation!$D$4:$D$1197,Korrelation!K$4:K$1197,"",0),'DM01-AV-CH'!$A$6:$A$834,0))) -> 4 | J50: {=IF(B50=0,IF(E50=0,"",HYPERLINK("#"&RIGHT(CELL("adresse",OFFSET(DMAV_Dienste!$M$6,E50-1,0)),LEN(CELL("adresse",OFFSET(DMAV_Dienste!$M$6,E50-1,0)))-FIND("]",CELL("adresse",OFFSET(DMAV_Dienste!$M$6,E50-1,0)))),"Dienst")),HYPERLINK("#"&RIGHT(CELL("adresse",OFFSET(DMAV_Modell!$N$6,B50-1,0)),LEN(CELL("adresse",OFFSET(DMAV_Modell!$N$6,B50-1,0)))-FIND("]",CELL("adresse",OFFSET(DMAV_Modell!$N$6,B50-1,0)))),"Modell"))} -> Modell | K50: {=IF($B50=0,IF($E50=0,"",IF(INDEX(DMAV_Dienste!P$6:P$140,$E50)="","",INDEX(DMAV_Dienste!P$6:P$140,$E50))),IF(INDEX(DMAV_Modell!Q$6:Q$838,$B50)="","",INDEX(DMAV_Modell!Q$6:Q$838,$B50)))} -> DOMAIN | L50: {=IF($B50=0,IF($E50=0,"",IF(INDEX(DMAV_Dienste!O$6:O$140,$E50)="","",INDEX(DMAV_Dienste!O$6:O$140,$E50))),IF(INDEX(DMAV_Modell!P$6:P$838,$B50)="","",INDEX(DMAV_Modell!P$6:P$838,$B50)))} | M50: {=IF($B50=0,IF($E50=0,"",IF(INDEX(DMAV_Dienste!Q$6:Q$140,$E50)="","",INDEX(DMAV_Dienste!Q$6:Q$140,$E50))),IF(INDEX(DMAV_Modell!R$6:R$838,$B50)="","",INDEX(DMAV_Modell!R$6:R$838,$B50)))} -> Genauigkeit | N50: {=IF($B50=0,IF($E50=0,"",IF(INDEX(DMAV_Dienste!T$6:T$140,$E50)="","",INDEX(DMAV_Dienste!T$6:T$140,$E50))),IF(INDEX(DMAV_Modell!U$6:U$838,$B50)="","",INDEX(DMAV_Modell!U$6:U$838,$B50)))} | O50: {=IF(C50=0,IF(F50=0,"",HYPERLINK("#"&RIGHT(CELL("adresse",OFFSET(DMAV_Dienste!$M$6,F50-1,0)),LEN(CELL("adresse",OFFSET(DMAV_Dienste!$M$6,F50-1,0)))-FIND("]",CELL("adresse",OFFSET(DMAV_Dienste!$M$6,F50-1,0)))),"Structure")),HYPERLINK("#"&RIGHT(CELL("adresse",OFFSET(DMAV_Modell!$N$6,C50-1,0)),LEN(CELL("adresse",OFFSET(DMAV_Modell!$N$6,C50-1,0)))-FIND("]",CELL("adresse",OFFSET(DMAV_Modell!$N$6,C50-1,0)))),"Structure"))} | P50: {=IF(D50=0,IF(G50=0,"",HYPERLINK("#"&RIGHT(CELL("adresse",OFFSET(DMAV_Dienste!$M$6,G50-1,0)),LEN(CELL("adresse",OFFSET(DMAV_Dienste!$M$6,G50-1,0)))-FIND("]",CELL("adresse",OFFSET(DMAV_Dienste!$M$6,G50-1,0)))),"Substructure")),HYPERLINK("#"&RIGHT(CELL("adresse",OFFSET(DMAV_Modell!$N$6,D50-1,0)),LEN(CELL("adresse",OFFSET(DMAV_Modell!$N$6,D50-1,0)))-FIND("]",CELL("adresse",OFFSET(DMAV_Modell!$N$6,D50-1,0)))),"Substructure"))} | AF50: {=IF(H50=0,"",HYPERLINK("#"&RIGHT(CELL("adresse",OFFSET('DM01-AV-CH'!$G$6,H50-1,0)),LEN(CELL("adresse",OFFSET('DM01-AV-CH'!$G$6,H50-1,0)))-FIND("]",CELL("adresse",OFFSET('DM01-AV-CH'!$G$6,H50-1,0)))),"Modell"))} -> Modell | AG50: {=IF($H50=0,"",IF(INDEX('DM01-AV-CH'!G$6:G$834,$H50)="","",INDEX('DM01-AV-CH'!G$6:G$834,$H50)))} -> Allgemein | AH50: {=IF($H50=0,"",IF(INDEX('DM01-AV-CH'!H$6:H$834,$H50)="","",INDEX('DM01-AV-CH'!H$6:H$834,$H50)))} | AI50: {=IF($H50=0,"",IF(INDEX('DM01-AV-CH'!I$6:I$834,$H50)="","",INDEX('DM01-AV-CH'!I$6:I$834,$H50)))} -> Genauigkeit
A51: 46 | B51: =IF($A51="","",IF(_xlfn.XLOOKUP($A51,Korrelation!$D$4:$D$1197,Korrelation!E$4:E$1197,"-",0)="-",0,MATCH(_xlfn.XLOOKUP($A51,Korrelation!$D$4:$D$1197,Korrelation!E$4:E$1197,"",0),DMAV_Modell!$G$6:$G$677,0))) -> 41 | C51: =IF($A51="","",IF(_xlfn.XLOOKUP($A51,Korrelation!$D$4:$D$1197,Korrelation!F$4:F$1197,"-",0)="-",0,MATCH(_xlfn.XLOOKUP($A51,Korrelation!$D$4:$D$1197,Korrelation!F$4:F$1197,"",0),DMAV_Modell!$G$6:$G$677,0))) -> 0 | D51: =IF($A51="","",IF(_xlfn.XLOOKUP($A51,Korrelation!$D$4:$D$1197,Korrelation!G$4:G$1197,"-",0)="-",0,MATCH(_xlfn.XLOOKUP($A51,Korrelation!$D$4:$D$1197,Korrelation!G$4:G$1197,"",0),DMAV_Modell!$G$6:$G$677,0))) -> 0 | E51: =IF($A51="","",IF(_xlfn.XLOOKUP($A51,Korrelation!$D$4:$D$1197,Korrelation!H$4:H$1197,"-",0)="-",0,MATCH(_xlfn.XLOOKUP($A51,Korrelation!$D$4:$D$1197,Korrelation!H$4:H$1197,"",0),DMAV_Dienste!$F$6:$F$140,0))) -> 0 | F51: =IF($A51="","",IF(_xlfn.XLOOKUP($A51,Korrelation!$D$4:$D$1197,Korrelation!I$4:I$1197,"-",0)="-",0,MATCH(_xlfn.XLOOKUP($A51,Korrelation!$D$4:$D$1197,Korrelation!I$4:I$1197,"",0),DMAV_Dienste!$F$6:$F$140,0))) -> 0 | G51: =IF($A51="","",IF(_xlfn.XLOOKUP($A51,Korrelation!$D$4:$D$1197,Korrelation!J$4:J$1197,"-",0)="-",0,MATCH(_xlfn.XLOOKUP($A51,Korrelation!$D$4:$D$1197,Korrelation!J$4:J$1197,"",0),DMAV_Dienste!$F$6:$F$140,0))) -> 0 | H51: =IF($A51="","",IF(_xlfn.XLOOKUP($A51,Korrelation!$D$4:$D$1197,Korrelation!K$4:K$1197,"-",0)="-",0,MATCH(_xlfn.XLOOKUP($A51,Korrelation!$D$4:$D$1197,Korrelation!K$4:K$1197,"",0),'DM01-AV-CH'!$A$6:$A$834,0))) -> 5 | J51: {=IF(B51=0,IF(E51=0,"",HYPERLINK("#"&RIGHT(CELL("adresse",OFFSET(DMAV_Dienste!$M$6,E51-1,0)),LEN(CELL("adresse",OFFSET(DMAV_Dienste!$M$6,E51-1,0)))-FIND("]",CELL("adresse",OFFSET(DMAV_Dienste!$M$6,E51-1,0)))),"Dienst")),HYPERLINK("#"&RIGHT(CELL("adresse",OFFSET(DMAV_Modell!$N$6,B51-1,0)),LEN(CELL("adresse",OFFSET(DMAV_Modell!$N$6,B51-1,0)))-FIND("]",CELL("adresse",OFFSET(DMAV_Modell!$N$6,B51-1,0)))),"Modell"))} -> Modell | K51: {=IF($B51=0,IF($E51=0,"",IF(INDEX(DMAV_Dienste!P$6:P$140,$E51)="","",INDEX(DMAV_Dienste!P$6:P$140,$E51))),IF(INDEX(DMAV_Modell!Q$6:Q$838,$B51)="","",INDEX(DMAV_Modell!Q$6:Q$838,$B51)))} -> DOMAIN | L51: {=IF($B51=0,IF($E51=0,"",IF(INDEX(DMAV_Dienste!O$6:O$140,$E51)="","",INDEX(DMAV_Dienste!O$6:O$140,$E51))),IF(INDEX(DMAV_Modell!P$6:P$838,$B51)="","",INDEX(DMAV_Modell!P$6:P$838,$B51)))} | M51: {=IF($B51=0,IF($E51=0,"",IF(INDEX(DMAV_Dienste!Q$6:Q$140,$E51)="","",INDEX(DMAV_Dienste!Q$6:Q$140,$E51))),IF(INDEX(DMAV_Modell!R$6:R$838,$B51)="","",INDEX(DMAV_Modell!R$6:R$838,$B51)))} -> Zuverlaessigkeit | N51: {=IF($B51=0,IF($E51=0,"",IF(INDEX(DMAV_Dienste!T$6:T$140,$E51)="","",INDEX(DMAV_Dienste!T$6:T$140,$E51))),IF(INDEX(DMAV_Modell!U$6:U$838,$B51)="","",INDEX(DMAV_Modell!U$6:U$838,$B51)))} | O51: {=IF(C51=0,IF(F51=0,"",HYPERLINK("#"&RIGHT(CELL("adresse",OFFSET(DMAV_Dienste!$M$6,F51-1,0)),LEN(CELL("adresse",OFFSET(DMAV_Dienste!$M$6,F51-1,0)))-FIND("]",CELL("adresse",OFFSET(DMAV_Dienste!$M$6,F51-1,0)))),"Structure")),HYPERLINK("#"&RIGHT(CELL("adresse",OFFSET(DMAV_Modell!$N$6,C51-1,0)),LEN(CELL("adresse",OFFSET(DMAV_Modell!$N$6,C51-1,0)))-FIND("]",CELL("adresse",OFFSET(DMAV_Modell!$N$6,C51-1,0)))),"Structure"))} | P51: {=IF(D51=0,IF(G51=0,"",HYPERLINK("#"&RIGHT(CELL("adresse",OFFSET(DMAV_Dienste!$M$6,G51-1,0)),LEN(CELL("adresse",OFFSET(DMAV_Dienste!$M$6,G51-1,0)))-FIND("]",CELL("adresse",OFFSET(DMAV_Dienste!$M$6,G51-1,0)))),"Substructure")),HYPERLINK("#"&RIGHT(CELL("adresse",OFFSET(DMAV_Modell!$N$6,D51-1,0)),LEN(CELL("adresse",OFFSET(DMAV_Modell!$N$6,D51-1,0)))-FIND("]",CELL("adresse",OFFSET(DMAV_Modell!$N$6,D51-1,0)))),"Substructure"))} | R51: ja = TRUE | AD51: TRUE = ja | AF51: {=IF(H51=0,"",HYPERLINK("#"&RIGHT(CELL("adresse",OFFSET('DM01-AV-CH'!$G$6,H51-1,0)),LEN(CELL("adresse",OFFSET('DM01-AV-CH'!$G$6,H51-1,0)))-FIND("]",CELL("adresse",OFFSET('DM01-AV-CH'!$G$6,H51-1,0)))),"Modell"))} -> Modell | AG51: {=IF($H51=0,"",IF(INDEX('DM01-AV-CH'!G$6:G$834,$H51)="","",INDEX('DM01-AV-CH'!G$6:G$834,$H51)))} -> Allgemein | AH51: {=IF($H51=0,"",IF(INDEX('DM01-AV-CH'!H$6:H$834,$H51)="","",INDEX('DM01-AV-CH'!H$6:H$834,$H51)))} | AI51: {=IF($H51=0,"",IF(INDEX('DM01-AV-CH'!I$6:I$834,$H51)="","",INDEX('DM01-AV-CH'!I$6:I$834,$H51)))} -> Zuverlaessigkeit
A52: 47 | B52: =IF($A52="","",IF(_xlfn.XLOOKUP($A52,Korrelation!$D$4:$D$1197,Korrelation!E$4:E$1197,"-",0)="-",0,MATCH(_xlfn.XLOOKUP($A52,Korrelation!$D$4:$D$1197,Korrelation!E$4:E$1197,"",0),DMAV_Modell!$G$6:$G$677,0))) -> 41 | C52: =IF($A52="","",IF(_xlfn.XLOOKUP($A52,Korrelation!$D$4:$D$1197,Korrelation!F$4:F$1197,"-",0)="-",0,MATCH(_xlfn.XLOOKUP($A52,Korrelation!$D$4:$D$1197,Korrelation!F$4:F$1197,"",0),DMAV_Modell!$G$6:$G$677,0))) -> 0 | D52: =IF($A52="","",IF(_xlfn.XLOOKUP($A52,Korrelation!$D$4:$D$1197,Korrelation!G$4:G$1197,"-",0)="-",0,MATCH(_xlfn.XLOOKUP($A52,Korrelation!$D$4:$D$1197,Korrelation!G$4:G$1197,"",0),DMAV_Modell!$G$6:$G$677,0))) -> 0 | E52: =IF($A52="","",IF(_xlfn.XLOOKUP($A52,Korrelation!$D$4:$D$1197,Korrelation!H$4:H$1197,"-",0)="-",0,MATCH(_xlfn.XLOOKUP($A52,Korrelation!$D$4:$D$1197,Korrelation!H$4:H$1197,"",0),DMAV_Dienste!$F$6:$F$140,0))) -> 0 | F52: =IF($A52="","",IF(_xlfn.XLOOKUP($A52,Korrelation!$D$4:$D$1197,Korrelation!I$4:I$1197,"-",0)="-",0,MATCH(_xlfn.XLOOKUP($A52,Korrelation!$D$4:$D$1197,Korrelation!I$4:I$1197,"",0),DMAV_Dienste!$F$6:$F$140,0))) -> 0 | G52: =IF($A52="","",IF(_xlfn.XLOOKUP($A52,Korrelation!$D$4:$D$1197,Korrelation!J$4:J$1197,"-",0)="-",0,MATCH(_xlfn.XLOOKUP($A52,Korrelation!$D$4:$D$1197,Korrelation!J$4:J$1197,"",0),DMAV_Dienste!$F$6:$F$140,0))) -> 0 | H52: =IF($A52="","",IF(_xlfn.XLOOKUP($A52,Korrelation!$D$4:$D$1197,Korrelation!K$4:K$1197,"-",0)="-",0,MATCH(_xlfn.XLOOKUP($A52,Korrelation!$D$4:$D$1197,Korrelation!K$4:K$1197,"",0),'DM01-AV-CH'!$A$6:$A$834,0))) -> 6 | J52: {=IF(B52=0,IF(E52=0,"",HYPERLINK("#"&RIGHT(CELL("adresse",OFFSET(DMAV_Dienste!$M$6,E52-1,0)),LEN(CELL("adresse",OFFSET(DMAV_Dienste!$M$6,E52-1,0)))-FIND("]",CELL("adresse",OFFSET(DMAV_Dienste!$M$6,E52-1,0)))),"Dienst")),HYPERLINK("#"&RIGHT(CELL("adresse",OFFSET(DMAV_Modell!$N$6,B52-1,0)),LEN(CELL("adresse",OFFSET(DMAV_Modell!$N$6,B52-1,0)))-FIND("]",CELL("adresse",OFFSET(DMAV_Modell!$N$6,B52-1,0)))),"Modell"))} -> Modell | K52: {=IF($B52=0,IF($E52=0,"",IF(INDEX(DMAV_Dienste!P$6:P$140,$E52)="","",INDEX(DMAV_Dienste!P$6:P$140,$E52))),IF(INDEX(DMAV_Modell!Q$6:Q$838,$B52)="","",INDEX(DMAV_Modell!Q$6:Q$838,$B52)))} -> DOMAIN | L52: {=IF($B52=0,IF($E52=0,"",IF(INDEX(DMAV_Dienste!O$6:O$140,$E52)="","",INDEX(DMAV_Dienste!O$6:O$140,$E52))),IF(INDEX(DMAV_Modell!P$6:P$838,$B52)="","",INDEX(DMAV_Modell!P$6:P$838,$B52)))} | M52: {=IF($B52=0,IF($E52=0,"",IF(INDEX(DMAV_Dienste!Q$6:Q$140,$E52)="","",INDEX(DMAV_Dienste!Q$6:Q$140,$E52))),IF(INDEX(DMAV_Modell!R$6:R$838,$B52)="","",INDEX(DMAV_Modell!R$6:R$838,$B52)))} -> Zuverlaessigkeit | N52: {=IF($B52=0,IF($E52=0,"",IF(INDEX(DMAV_Dienste!T$6:T$140,$E52)="","",INDEX(DMAV_Dienste!T$6:T$140,$E52))),IF(INDEX(DMAV_Modell!U$6:U$838,$B52)="","",INDEX(DMAV_Modell!U$6:U$838,$B52)))} | O52: {=IF(C52=0,IF(F52=0,"",HYPERLINK("#"&RIGHT(CELL("adresse",OFFSET(DMAV_Dienste!$M$6,F52-1,0)),LEN(CELL("adresse",OFFSET(DMAV_Dienste!$M$6,F52-1,0)))-FIND("]",CELL("adresse",OFFSET(DMAV_Dienste!$M$6,F52-1,0)))),"Structure")),HYPERLINK("#"&RIGHT(CELL("adresse",OFFSET(DMAV_Modell!$N$6,C52-1,0)),LEN(CELL("adresse",OFFSET(DMAV_Modell!$N$6,C52-1,0)))-FIND("]",CELL("adresse",OFFSET(DMAV_Modell!$N$6,C52-1,0)))),"Structure"))} | P52: {=IF(D52=0,IF(G52=0,"",HYPERLINK("#"&RIGHT(CELL("adresse",OFFSET(DMAV_Dienste!$M$6,G52-1,0)),LEN(CELL("adresse",OFFSET(DMAV_Dienste!$M$6,G52-1,0)))-FIND("]",CELL("adresse",OFFSET(DMAV_Dienste!$M$6,G52-1,0)))),"Substructure")),HYPERLINK("#"&RIGHT(CELL("adresse",OFFSET(DMAV_Modell!$N$6,D52-1,0)),LEN(CELL("adresse",OFFSET(DMAV_Modell!$N$6,D52-1,0)))-FIND("]",CELL("adresse",OFFSET(DMAV_Modell!$N$6,D52-1,0)))),"Substructure"))} | R52: nein = FALSE | AD52: FALSE = nein | AF52: {=IF(H52=0,"",HYPERLINK("#"&RIGHT(CELL("adresse",OFFSET('DM01-AV-CH'!$G$6,H52-1,0)),LEN(CELL("adresse",OFFSET('DM01-AV-CH'!$G$6,H52-1,0)))-FIND("]",CELL("adresse",OFFSET('DM01-AV-CH'!$G$6,H52-1,0)))),"Modell"))} -> Modell | AG52: {=IF($H52=0,"",IF(INDEX('DM01-AV-CH'!G$6:G$834,$H52)="","",INDEX('DM01-AV-CH'!G$6:G$834,$H52)))} -> Allgemein | AH52: {=IF($H52=0,"",IF(INDEX('DM01-AV-CH'!H$6:H$834,$H52)="","",INDEX('DM01-AV-CH'!H$6:H$834,$H52)))} | AI52: {=IF($H52=0,"",IF(INDEX('DM01-AV-CH'!I$6:I$834,$H52)="","",INDEX('DM01-AV-CH'!I$6:I$834,$H52)))} -> Zuverlaessigkeit
A53: 48 | B53: =IF($A53="","",IF(_xlfn.XLOOKUP($A53,Korrelation!$D$4:$D$1197,Korrelation!E$4:E$1197,"-",0)="-",0,MATCH(_xlfn.XLOOKUP($A53,Korrelation!$D$4:$D$1197,Korrelation!E$4:E$1197,"",0),DMAV_Modell!$G$6:$G$677,0))) -> 0 | C53: =IF($A53="","",IF(_xlfn.XLOOKUP($A53,Korrelation!$D$4:$D$1197,Korrelation!F$4:F$1197,"-",0)="-",0,MATCH(_xlfn.XLOOKUP($A53,Korrelation!$D$4:$D$1197,Korrelation!F$4:F$1197,"",0),DMAV_Modell!$G$6:$G$677,0))) -> 0 | D53: =IF($A53="","",IF(_xlfn.XLOOKUP($A53,Korrelation!$D$4:$D$1197,Korrelation!G$4:G$1197,"-",0)="-",0,MATCH(_xlfn.XLOOKUP($A53,Korrelation!$D$4:$D$1197,Korrelation!G$4:G$1197,"",0),DMAV_Modell!$G$6:$G$677,0))) -> 0 | E53: =IF($A53="","",IF(_xlfn.XLOOKUP($A53,Korrelation!$D$4:$D$1197,Korrelation!H$4:H$1197,"-",0)="-",0,MATCH(_xlfn.XLOOKUP($A53,Korrelation!$D$4:$D$1197,Korrelation!H$4:H$1197,"",0),DMAV_Dienste!$F$6:$F$140,0))) -> 0 | F53: =IF($A53="","",IF(_xlfn.XLOOKUP($A53,Korrelation!$D$4:$D$1197,Korrelation!I$4:I$1197,"-",0)="-",0,MATCH(_xlfn.XLOOKUP($A53,Korrelation!$D$4:$D$1197,Korrelation!I$4:I$1197,"",0),DMAV_Dienste!$F$6:$F$140,0))) -> 0 | G53: =IF($A53="","",IF(_xlfn.XLOOKUP($A53,Korrelation!$D$4:$D$1197,Korrelation!J$4:J$1197,"-",0)="-",0,MATCH(_xlfn.XLOOKUP($A53,Korrelation!$D$4:$D$1197,Korrelation!J$4:J$1197,"",0),DMAV_Dienste!$F$6:$F$140,0))) -> 0 | H53: =IF($A53="","",IF(_xlfn.XLOOKUP($A53,Korrelation!$D$4:$D$1197,Korrelation!K$4:K$1197,"-",0)="-",0,MATCH(_xlfn.XLOOKUP($A53,Korrelation!$D$4:$D$1197,Korrelation!K$4:K$1197,"",0),'DM01-AV-CH'!$A$6:$A$834,0))) -> 7 | J53: {=IF(B53=0,IF(E53=0,"",HYPERLINK("#"&RIGHT(CELL("adresse",OFFSET(DMAV_Dienste!$M$6,E53-1,0)),LEN(CELL("adresse",OFFSET(DMAV_Dienste!$M$6,E53-1,0)))-FIND("]",CELL("adresse",OFFSET(DMAV_Dienste!$M$6,E53-1,0)))),"Dienst")),HYPERLINK("#"&RIGHT(CELL("adresse",OFFSET(DMAV_Modell!$N$6,B53-1,0)),LEN(CELL("adresse",OFFSET(DMAV_Modell!$N$6,B53-1,0)))-FIND("]",CELL("adresse",OFFSET(DMAV_Modell!$N$6,B53-1,0)))),"Modell"))} | K53: {=IF($B53=0,IF($E53=0,"",IF(INDEX(DMAV_Dienste!P$6:P$140,$E53)="","",INDEX(DMAV_Dienste!P$6:P$140,$E53))),IF(INDEX(DMAV_Modell!Q$6:Q$838,$B53)="","",INDEX(DMAV_Modell!Q$6:Q$838,$B53)))} | L53: {=IF($B53=0,IF($E53=0,"",IF(INDEX(DMAV_Dienste!O$6:O$140,$E53)="","",INDEX(DMAV_Dienste!O$6:O$140,$E53))),IF(INDEX(DMAV_Modell!P$6:P$838,$B53)="","",INDEX(DMAV_Modell!P$6:P$838,$B53)))} | M53: {=IF($B53=0,IF($E53=0,"",IF(INDEX(DMAV_Dienste!Q$6:Q$140,$E53)="","",INDEX(DMAV_Dienste!Q$6:Q$140,$E53))),IF(INDEX(DMAV_Modell!R$6:R$838,$B53)="","",INDEX(DMAV_Modell!R$6:R$838,$B53)))} | N53: {=IF($B53=0,IF($E53=0,"",IF(INDEX(DMAV_Dienste!T$6:T$140,$E53)="","",INDEX(DMAV_Dienste!T$6:T$140,$E53))),IF(INDEX(DMAV_Modell!U$6:U$838,$B53)="","",INDEX(DMAV_Modell!U$6:U$838,$B53)))} | O53: {=IF(C53=0,IF(F53=0,"",HYPERLINK("#"&RIGHT(CELL("adresse",OFFSET(DMAV_Dienste!$M$6,F53-1,0)),LEN(CELL("adresse",OFFSET(DMAV_Dienste!$M$6,F53-1,0)))-FIND("]",CELL("adresse",OFFSET(DMAV_Dienste!$M$6,F53-1,0)))),"Structure")),HYPERLINK("#"&RIGHT(CELL("adresse",OFFSET(DMAV_Modell!$N$6,C53-1,0)),LEN(CELL("adresse",OFFSET(DMAV_Modell!$N$6,C53-1,0)))-FIND("]",CELL("adresse",OFFSET(DMAV_Modell!$N$6,C53-1,0)))),"Structure"))} | P53: {=IF(D53=0,IF(G53=0,"",HYPERLINK("#"&RIGHT(CELL("adresse",OFFSET(DMAV_Dienste!$M$6,G53-1,0)),LEN(CELL("adresse",OFFSET(DMAV_Dienste!$M$6,G53-1,0)))-FIND("]",CELL("adresse",OFFSET(DMAV_Dienste!$M$6,G53-1,0)))),"Substructure")),HYPERLINK("#"&RIGHT(CELL("adresse",OFFSET(DMAV_Modell!$N$6,D53-1,0)),LEN(CELL("adresse",OFFSET(DMAV_Modell!$N$6,D53-1,0)))-FIND("]",CELL("adresse",OFFSET(DMAV_Modell!$N$6,D53-1,0)))),"Substructure"))} | AF53: {=IF(H53=0,"",HYPERLINK("#"&RIGHT(CELL("adresse",OFFSET('DM01-AV-CH'!$G$6,H53-1,0)),LEN(CELL("adresse",OFFSET('DM01-AV-CH'!$G$6,H53-1,0)))-FIND("]",CELL("adresse",OFFSET('DM01-AV-CH'!$G$6,H53-1,0)))),"Modell"))} -> Modell | AG53: {=IF($H53=0,"",IF(INDEX('DM01-AV-CH'!G$6:G$834,$H53)="","",INDEX('DM01-AV-CH'!G$6:G$834,$H53)))} -> Allgemein | AH53: {=IF($H53=0,"",IF(INDEX('DM01-AV-CH'!H$6:H$834,$H53)="","",INDEX('DM01-AV-CH'!H$6:H$834,$H53)))} | AI53: {=IF($H53=0,"",IF(INDEX('DM01-AV-CH'!I$6:I$834,$H53)="","",INDEX('DM01-AV-CH'!I$6:I$834,$H53)))} -> Status
A54: 49 | B54: =IF($A54="","",IF(_xlfn.XLOOKUP($A54,Korrelation!$D$4:$D$1197,Korrelation!E$4:E$1197,"-",0)="-",0,MATCH(_xlfn.XLOOKUP($A54,Korrelation!$D$4:$D$1197,Korrelation!E$4:E$1197,"",0),DMAV_Modell!$G$6:$G$677,0))) -> 0 | C54: =IF($A54="","",IF(_xlfn.XLOOKUP($A54,Korrelation!$D$4:$D$1197,Korrelation!F$4:F$1197,"-",0)="-",0,MATCH(_xlfn.XLOOKUP($A54,Korrelation!$D$4:$D$1197,Korrelation!F$4:F$1197,"",0),DMAV_Modell!$G$6:$G$677,0))) -> 0 | D54: =IF($A54="","",IF(_xlfn.XLOOKUP($A54,Korrelation!$D$4:$D$1197,Korrelation!G$4:G$1197,"-",0)="-",0,MATCH(_xlfn.XLOOKUP($A54,Korrelation!$D$4:$D$1197,Korrelation!G$4:G$1197,"",0),DMAV_Modell!$G$6:$G$677,0))) -> 0 | E54: =IF($A54="","",IF(_xlfn.XLOOKUP($A54,Korrelation!$D$4:$D$1197,Korrelation!H$4:H$1197,"-",0)="-",0,MATCH(_xlfn.XLOOKUP($A54,Korrelation!$D$4:$D$1197,Korrelation!H$4:H$1197,"",0),DMAV_Dienste!$F$6:$F$140,0))) -> 0 | F54: =IF($A54="","",IF(_xlfn.XLOOKUP($A54,Korrelation!$D$4:$D$1197,Korrelation!I$4:I$1197,"-",0)="-",0,MATCH(_xlfn.XLOOKUP($A54,Korrelation!$D$4:$D$1197,Korrelation!I$4:I$1197,"",0),DMAV_Dienste!$F$6:$F$140,0))) -> 0 | G54: =IF($A54="","",IF(_xlfn.XLOOKUP($A54,Korrelation!$D$4:$D$1197,Korrelation!J$4:J$1197,"-",0)="-",0,MATCH(_xlfn.XLOOKUP($A54,Korrelation!$D$4:$D$1197,Korrelation!J$4:J$1197,"",0),DMAV_Dienste!$F$6:$F$140,0))) -> 0 | H54: =IF($A54="","",IF(_xlfn.XLOOKUP($A54,Korrelation!$D$4:$D$1197,Korrelation!K$4:K$1197,"-",0)="-",0,MATCH(_xlfn.XLOOKUP($A54,Korrelation!$D$4:$D$1197,Korrelation!K$4:K$1197,"",0),'DM01-AV-CH'!$A$6:$A$834,0))) -> 8 | J54: {=IF(B54=0,IF(E54=0,"",HYPERLINK("#"&RIGHT(CELL("adresse",OFFSET(DMAV_Dienste!$M$6,E54-1,0)),LEN(CELL("adresse",OFFSET(DMAV_Dienste!$M$6,E54-1,0)))-FIND("]",CELL("adresse",OFFSET(DMAV_Dienste!$M$6,E54-1,0)))),"Dienst")),HYPERLINK("#"&RIGHT(CELL("adresse",OFFSET(DMAV_Modell!$N$6,B54-1,0)),LEN(CELL("adresse",OFFSET(DMAV_Modell!$N$6,B54-1,0)))-FIND("]",CELL("adresse",OFFSET(DMAV_Modell!$N$6,B54-1,0)))),"Modell"))} | K54: {=IF($B54=0,IF($E54=0,"",IF(INDEX(DMAV_Dienste!P$6:P$140,$E54)="","",INDEX(DMAV_Dienste!P$6:P$140,$E54))),IF(INDEX(DMAV_Modell!Q$6:Q$838,$B54)="","",INDEX(DMAV_Modell!Q$6:Q$838,$B54)))} | L54: {=IF($B54=0,IF($E54=0,"",IF(INDEX(DMAV_Dienste!O$6:O$140,$E54)="","",INDEX(DMAV_Dienste!O$6:O$140,$E54))),IF(INDEX(DMAV_Modell!P$6:P$838,$B54)="","",INDEX(DMAV_Modell!P$6:P$838,$B54)))} | M54: {=IF($B54=0,IF($E54=0,"",IF(INDEX(DMAV_Dienste!Q$6:Q$140,$E54)="","",INDEX(DMAV_Dienste!Q$6:Q$140,$E54))),IF(INDEX(DMAV_Modell!R$6:R$838,$B54)="","",INDEX(DMAV_Modell!R$6:R$838,$B54)))} | N54: {=IF($B54=0,IF($E54=0,"",IF(INDEX(DMAV_Dienste!T$6:T$140,$E54)="","",INDEX(DMAV_Dienste!T$6:T$140,$E54))),IF(INDEX(DMAV_Modell!U$6:U$838,$B54)="","",INDEX(DMAV_Modell!U$6:U$838,$B54)))} | O54: {=IF(C54=0,IF(F54=0,"",HYPERLINK("#"&RIGHT(CELL("adresse",OFFSET(DMAV_Dienste!$M$6,F54-1,0)),LEN(CELL("adresse",OFFSET(DMAV_Dienste!$M$6,F54-1,0)))-FIND("]",CELL("adresse",OFFSET(DMAV_Dienste!$M$6,F54-1,0)))),"Structure")),HYPERLINK("#"&RIGHT(CELL("adresse",OFFSET(DMAV_Modell!$N$6,C54-1,0)),LEN(CELL("adresse",OFFSET(DMAV_Modell!$N$6,C54-1,0)))-FIND("]",CELL("adresse",OFFSET(DMAV_Modell!$N$6,C54-1,0)))),"Structure"))} | P54: {=IF(D54=0,IF(G54=0,"",HYPERLINK("#"&RIGHT(CELL("adresse",OFFSET(DMAV_Dienste!$M$6,G54-1,0)),LEN(CELL("adresse",OFFSET(DMAV_Dienste!$M$6,G54-1,0)))-FIND("]",CELL("adresse",OFFSET(DMAV_Dienste!$M$6,G54-1,0)))),"Substructure")),HYPERLINK("#"&RIGHT(CELL("adresse",OFFSET(DMAV_Modell!$N$6,D54-1,0)),LEN(CELL("adresse",OFFSET(DMAV_Modell!$N$6,D54-1,0)))-FIND("]",CELL("adresse",OFFSET(DMAV_Modell!$N$6,D54-1,0)))),"Substructure"))} | AF54: {=IF(H54=0,"",HYPERLINK("#"&RIGHT(CELL("adresse",OFFSET('DM01-AV-CH'!$G$6,H54-1,0)),LEN(CELL("adresse",OFFSET('DM01-AV-CH'!$G$6,H54-1,0)))-FIND("]",CELL("adresse",OFFSET('DM01-AV-CH'!$G$6,H54-1,0)))),"Modell"))} -> Modell | AG54: {=IF($H54=0,"",IF(INDEX('DM01-AV-CH'!G$6:G$834,$H54)="","",INDEX('DM01-AV-CH'!G$6:G$834,$H54)))} -> Allgemein | AH54: {=IF($H54=0,"",IF(INDEX('DM01-AV-CH'!H$6:H$834,$H54)="","",INDEX('DM01-AV-CH'!H$6:H$834,$H54)))} | AI54: {=IF($H54=0,"",IF(INDEX('DM01-AV-CH'!I$6:I$834,$H54)="","",INDEX('DM01-AV-CH'!I$6:I$834,$H54)))} -> Status
A55: 50 | B55: =IF($A55="","",IF(_xlfn.XLOOKUP($A55,Korrelation!$D$4:$D$1197,Korrelation!E$4:E$1197,"-",0)="-",0,MATCH(_xlfn.XLOOKUP($A55,Korrelation!$D$4:$D$1197,Korrelation!E$4:E$1197,"",0),DMAV_Modell!$G$6:$G$677,0))) -> 42 | C55: =IF($A55="","",IF(_xlfn.XLOOKUP($A55,Korrelation!$D$4:$D$1197,Korrelation!F$4:F$1197,"-",0)="-",0,MATCH(_xlfn.XLOOKUP($A55,Korrelation!$D$4:$D$1197,Korrelation!F$4:F$1197,"",0),DMAV_Modell!$G$6:$G$677,0))) -> 0 | D55: =IF($A55="","",IF(_xlfn.XLOOKUP($A55,Korrelation!$D$4:$D$1197,Korrelation!G$4:G$1197,"-",0)="-",0,MATCH(_xlfn.XLOOKUP($A55,Korrelation!$D$4:$D$1197,Korrelation!G$4:G$1197,"",0),DMAV_Modell!$G$6:$G$677,0))) -> 0 | E55: =IF($A55="","",IF(_xlfn.XLOOKUP($A55,Korrelation!$D$4:$D$1197,Korrelation!H$4:H$1197,"-",0)="-",0,MATCH(_xlfn.XLOOKUP($A55,Korrelation!$D$4:$D$1197,Korrelation!H$4:H$1197,"",0),DMAV_Dienste!$F$6:$F$140,0))) -> 0 | F55: =IF($A55="","",IF(_xlfn.XLOOKUP($A55,Korrelation!$D$4:$D$1197,Korrelation!I$4:I$1197,"-",0)="-",0,MATCH(_xlfn.XLOOKUP($A55,Korrelation!$D$4:$D$1197,Korrelation!I$4:I$1197,"",0),DMAV_Dienste!$F$6:$F$140,0))) -> 0 | G55: =IF($A55="","",IF(_xlfn.XLOOKUP($A55,Korrelation!$D$4:$D$1197,Korrelation!J$4:J$1197,"-",0)="-",0,MATCH(_xlfn.XLOOKUP($A55,Korrelation!$D$4:$D$1197,Korrelation!J$4:J$1197,"",0),DMAV_Dienste!$F$6:$F$140,0))) -> 0 | H55: =IF($A55="","",IF(_xlfn.XLOOKUP($A55,Korrelation!$D$4:$D$1197,Korrelation!K$4:K$1197,"-",0)="-",0,MATCH(_xlfn.XLOOKUP($A55,Korrelation!$D$4:$D$1197,Korrelation!K$4:K$1197,"",0),'DM01-AV-CH'!$A$6:$A$834,0))) -> 9 | J55: {=IF(B55=0,IF(E55=0,"",HYPERLINK("#"&RIGHT(CELL("adresse",OFFSET(DMAV_Dienste!$M$6,E55-1,0)),LEN(CELL("adresse",OFFSET(DMAV_Dienste!$M$6,E55-1,0)))-FIND("]",CELL("adresse",OFFSET(DMAV_Dienste!$M$6,E55-1,0)))),"Dienst")),HYPERLINK("#"&RIGHT(CELL("adresse",OFFSET(DMAV_Modell!$N$6,B55-1,0)),LEN(CELL("adresse",OFFSET(DMAV_Modell!$N$6,B55-1,0)))-FIND("]",CELL("adresse",OFFSET(DMAV_Modell!$N$6,B55-1,0)))),"Modell"))} -> Modell | K55: {=IF($B55=0,IF($E55=0,"",IF(INDEX(DMAV_Dienste!P$6:P$140,$E55)="","",INDEX(DMAV_Dienste!P$6:P$140,$E55))),IF(INDEX(DMAV_Modell!Q$6:Q$838,$B55)="","",INDEX(DMAV_Modell!Q$6:Q$838,$B55)))} -> DOMAIN | L55: {=IF($B55=0,IF($E55=0,"",IF(INDEX(DMAV_Dienste!O$6:O$140,$E55)="","",INDEX(DMAV_Dienste!O$6:O$140,$E55))),IF(INDEX(DMAV_Modell!P$6:P$838,$B55)="","",INDEX(DMAV_Modell!P$6:P$838,$B55)))} | M55: {=IF($B55=0,IF($E55=0,"",IF(INDEX(DMAV_Dienste!Q$6:Q$140,$E55)="","",INDEX(DMAV_Dienste!Q$6:Q$140,$E55))),IF(INDEX(DMAV_Modell!R$6:R$838,$B55)="","",INDEX(DMAV_Modell!R$6:R$838,$B55)))} -> Qualitaetsstandard | N55: {=IF($B55=0,IF($E55=0,"",IF(INDEX(DMAV_Dienste!T$6:T$140,$E55)="","",INDEX(DMAV_Dienste!T$6:T$140,$E55))),IF(INDEX(DMAV_Modell!U$6:U$838,$B55)="","",INDEX(DMAV_Modell!U$6:U$838,$B55)))} | O55: {=IF(C55=0,IF(F55=0,"",HYPERLINK("#"&RIGHT(CELL("adresse",OFFSET(DMAV_Dienste!$M$6,F55-1,0)),LEN(CELL("adresse",OFFSET(DMAV_Dienste!$M$6,F55-1,0)))-FIND("]",CELL("adresse",OFFSET(DMAV_Dienste!$M$6,F55-1,0)))),"Structure")),HYPERLINK("#"&RIGHT(CELL("adresse",OFFSET(DMAV_Modell!$N$6,C55-1,0)),LEN(CELL("adresse",OFFSET(DMAV_Modell!$N$6,C55-1,0)))-FIND("]",CELL("adresse",OFFSET(DMAV_Modell!$N$6,C55-1,0)))),"Structure"))} | P55: {=IF(D55=0,IF(G55=0,"",HYPERLINK("#"&RIGHT(CELL("adresse",OFFSET(DMAV_Dienste!$M$6,G55-1,0)),LEN(CELL("adresse",OFFSET(DMAV_Dienste!$M$6,G55-1,0)))-FIND("]",CELL("adresse",OFFSET(DMAV_Dienste!$M$6,G55-1,0)))),"Substructure")),HYPERLINK("#"&RIGHT(CELL("adresse",OFFSET(DMAV_Modell!$N$6,D55-1,0)),LEN(CELL("adresse",OFFSET(DMAV_Modell!$N$6,D55-1,0)))-FIND("]",CELL("adresse",OFFSET(DMAV_Modell!$N$6,D55-1,0)))),"Substructure"))} | AF55: {=IF(H55=0,"",HYPERLINK("#"&RIGHT(CELL("adresse",OFFSET('DM01-AV-CH'!$G$6,H55-1,0)),LEN(CELL("adresse",OFFSET('DM01-AV-CH'!$G$6,H55-1,0)))-FIND("]",CELL("adresse",OFFSET('DM01-AV-CH'!$G$6,H55-1,0)))),"Modell"))} -> Modell | AG55: {=IF($H55=0,"",IF(INDEX('DM01-AV-CH'!G$6:G$834,$H55)="","",INDEX('DM01-AV-CH'!G$6:G$834,$H55)))} -> Allgemein | AH55: {=IF($H55=0,"",IF(INDEX('DM01-AV-CH'!H$6:H$834,$H55)="","",INDEX('DM01-AV-CH'!H$6:H$834,$H55)))} | AI55: {=IF($H55=0,"",IF(INDEX('DM01-AV-CH'!I$6:I$834,$H55)="","",INDEX('DM01-AV-CH'!I$6:I$834,$H55)))} -> Qualitaetsstandard
A56: 51 | B56: =IF($A56="","",IF(_xlfn.XLOOKUP($A56,Korrelation!$D$4:$D$1197,Korrelation!E$4:E$1197,"-",0)="-",0,MATCH(_xlfn.XLOOKUP($A56,Korrelation!$D$4:$D$1197,Korrelation!E$4:E$1197,"",0),DMAV_Modell!$G$6:$G$677,0))) -> 0 | C56: =IF($A56="","",IF(_xlfn.XLOOKUP($A56,Korrelation!$D$4:$D$1197,Korrelation!F$4:F$1197,"-",0)="-",0,MATCH(_xlfn.XLOOKUP($A56,Korrelation!$D$4:$D$1197,Korrelation!F$4:F$1197,"",0),DMAV_Modell!$G$6:$G$677,0))) -> 0 | D56: =IF($A56="","",IF(_xlfn.XLOOKUP($A56,Korrelation!$D$4:$D$1197,Korrelation!G$4:G$1197,"-",0)="-",0,MATCH(_xlfn.XLOOKUP($A56,Korrelation!$D$4:$D$1197,Korrelation!G$4:G$1197,"",0),DMAV_Modell!$G$6:$G$677,0))) -> 0 | E56: =IF($A56="","",IF(_xlfn.XLOOKUP($A56,Korrelation!$D$4:$D$1197,Korrelation!H$4:H$1197,"-",0)="-",0,MATCH(_xlfn.XLOOKUP($A56,Korrelation!$D$4:$D$1197,Korrelation!H$4:H$1197,"",0),DMAV_Dienste!$F$6:$F$140,0))) -> 0 | F56: =IF($A56="","",IF(_xlfn.XLOOKUP($A56,Korrelation!$D$4:$D$1197,Korrelation!I$4:I$1197,"-",0)="-",0,MATCH(_xlfn.XLOOKUP($A56,Korrelation!$D$4:$D$1197,Korrelation!I$4:I$1197,"",0),DMAV_Dienste!$F$6:$F$140,0))) -> 0 | G56: =IF($A56="","",IF(_xlfn.XLOOKUP($A56,Korrelation!$D$4:$D$1197,Korrelation!J$4:J$1197,"-",0)="-",0,MATCH(_xlfn.XLOOKUP($A56,Korrelation!$D$4:$D$1197,Korrelation!J$4:J$1197,"",0),DMAV_Dienste!$F$6:$F$140,0))) -> 0 | H56: =IF($A56="","",IF(_xlfn.XLOOKUP($A56,Korrelation!$D$4:$D$1197,Korrelation!K$4:K$1197,"-",0)="-",0,MATCH(_xlfn.XLOOKUP($A56,Korrelation!$D$4:$D$1197,Korrelation!K$4:K$1197,"",0),'DM01-AV-CH'!$A$6:$A$834,0))) -> 10 | J56: {=IF(B56=0,IF(E56=0,"",HYPERLINK("#"&RIGHT(CELL("adresse",OFFSET(DMAV_Dienste!$M$6,E56-1,0)),LEN(CELL("adresse",OFFSET(DMAV_Dienste!$M$6,E56-1,0)))-FIND("]",CELL("adresse",OFFSET(DMAV_Dienste!$M$6,E56-1,0)))),"Dienst")),HYPERLINK("#"&RIGHT(CELL("adresse",OFFSET(DMAV_Modell!$N$6,B56-1,0)),LEN(CELL("adresse",OFFSET(DMAV_Modell!$N$6,B56-1,0)))-FIND("]",CELL("adresse",OFFSET(DMAV_Modell!$N$6,B56-1,0)))),"Modell"))} | K56: {=IF($B56=0,IF($E56=0,"",IF(INDEX(DMAV_Dienste!P$6:P$140,$E56)="","",INDEX(DMAV_Dienste!P$6:P$140,$E56))),IF(INDEX(DMAV_Modell!Q$6:Q$838,$B56)="","",INDEX(DMAV_Modell!Q$6:Q$838,$B56)))} | L56: {=IF($B56=0,IF($E56=0,"",IF(INDEX(DMAV_Dienste!O$6:O$140,$E56)="","",INDEX(DMAV_Dienste!O$6:O$140,$E56))),IF(INDEX(DMAV_Modell!P$6:P$838,$B56)="","",INDEX(DMAV_Modell!P$6:P$838,$B56)))} | M56: {=IF($B56=0,IF($E56=0,"",IF(INDEX(DMAV_Dienste!Q$6:Q$140,$E56)="","",INDEX(DMAV_Dienste!Q$6:Q$140,$E56))),IF(INDEX(DMAV_Modell!R$6:R$838,$B56)="","",INDEX(DMAV_Modell!R$6:R$838,$B56)))} | N56: {=IF($B56=0,IF($E56=0,"",IF(INDEX(DMAV_Dienste!T$6:T$140,$E56)="","",INDEX(DMAV_Dienste!T$6:T$140,$E56))),IF(INDEX(DMAV_Modell!U$6:U$838,$B56)="","",INDEX(DMAV_Modell!U$6:U$838,$B56)))} | O56: {=IF(C56=0,IF(F56=0,"",HYPERLINK("#"&RIGHT(CELL("adresse",OFFSET(DMAV_Dienste!$M$6,F56-1,0)),LEN(CELL("adresse",OFFSET(DMAV_Dienste!$M$6,F56-1,0)))-FIND("]",CELL("adresse",OFFSET(DMAV_Dienste!$M$6,F56-1,0)))),"Structure")),HYPERLINK("#"&RIGHT(CELL("adresse",OFFSET(DMAV_Modell!$N$6,C56-1,0)),LEN(CELL("adresse",OFFSET(DMAV_Modell!$N$6,C56-1,0)))-FIND("]",CELL("adresse",OFFSET(DMAV_Modell!$N$6,C56-1,0)))),"Structure"))} | P56: {=IF(D56=0,IF(G56=0,"",HYPERLINK("#"&RIGHT(CELL("adresse",OFFSET(DMAV_Dienste!$M$6,G56-1,0)),LEN(CELL("adresse",OFFSET(DMAV_Dienste!$M$6,G56-1,0)))-FIND("]",CELL("adresse",OFFSET(DMAV_Dienste!$M$6,G56-1,0)))),"Substructure")),HYPERLINK("#"&RIGHT(CELL("adresse",OFFSET(DMAV_Modell!$N$6,D56-1,0)),LEN(CELL("adresse",OFFSET(DMAV_Modell!$N$6,D56-1,0)))-FIND("]",CELL("adresse",OFFSET(DMAV_Modell!$N$6,D56-1,0)))),"Substructure"))} | AF56: {=IF(H56=0,"",HYPERLINK("#"&RIGHT(CELL("adresse",OFFSET('DM01-AV-CH'!$G$6,H56-1,0)),LEN(CELL("adresse",OFFSET('DM01-AV-CH'!$G$6,H56-1,0)))-FIND("]",CELL("adresse",OFFSET('DM01-AV-CH'!$G$6,H56-1,0)))),"Modell"))} -> Modell | AG56: {=IF($H56=0,"",IF(INDEX('DM01-AV-CH'!G$6:G$834,$H56)="","",INDEX('DM01-AV-CH'!G$6:G$834,$H56)))} -> Allgemein | AH56: {=IF($H56=0,"",IF(INDEX('DM01-AV-CH'!H$6:H$834,$H56)="","",INDEX('DM01-AV-CH'!H$6:H$834,$H56)))} | AI56: {=IF($H56=0,"",IF(INDEX('DM01-AV-CH'!I$6:I$834,$H56)="","",INDEX('DM01-AV-CH'!I$6:I$834,$H56)))} -> Qualitaetsstandard
A57: 52 | B57: =IF($A57="","",IF(_xlfn.XLOOKUP($A57,Korrelation!$D$4:$D$1197,Korrelation!E$4:E$1197,"-",0)="-",0,MATCH(_xlfn.XLOOKUP($A57,Korrelation!$D$4:$D$1197,Korrelation!E$4:E$1197,"",0),DMAV_Modell!$G$6:$G$677,0))) -> 43 | C57: =IF($A57="","",IF(_xlfn.XLOOKUP($A57,Korrelation!$D$4:$D$1197,Korrelation!F$4:F$1197,"-",0)="-",0,MATCH(_xlfn.XLOOKUP($A57,Korrelation!$D$4:$D$1197,Korrelation!F$4:F$1197,"",0),DMAV_Modell!$G$6:$G$677,0))) -> 0 | D57: =IF($A57="","",IF(_xlfn.XLOOKUP($A57,Korrelation!$D$4:$D$1197,Korrelation!G$4:G$1197,"-",0)="-",0,MATCH(_xlfn.XLOOKUP($A57,Korrelation!$D$4:$D$1197,Korrelation!G$4:G$1197,"",0),DMAV_Modell!$G$6:$G$677,0))) -> 0 | E57: =IF($A57="","",IF(_xlfn.XLOOKUP($A57,Korrelation!$D$4:$D$1197,Korrelation!H$4:H$1197,"-",0)="-",0,MATCH(_xlfn.XLOOKUP($A57,Korrelation!$D$4:$D$1197,Korrelation!H$4:H$1197,"",0),DMAV_Dienste!$F$6:$F$140,0))) -> 0 | F57: =IF($A57="","",IF(_xlfn.XLOOKUP($A57,Korrelation!$D$4:$D$1197,Korrelation!I$4:I$1197,"-",0)="-",0,MATCH(_xlfn.XLOOKUP($A57,Korrelation!$D$4:$D$1197,Korrelation!I$4:I$1197,"",0),DMAV_Dienste!$F$6:$F$140,0))) -> 0 | G57: =IF($A57="","",IF(_xlfn.XLOOKUP($A57,Korrelation!$D$4:$D$1197,Korrelation!J$4:J$1197,"-",0)="-",0,MATCH(_xlfn.XLOOKUP($A57,Korrelation!$D$4:$D$1197,Korrelation!J$4:J$1197,"",0),DMAV_Dienste!$F$6:$F$140,0))) -> 0 | H57: =IF($A57="","",IF(_xlfn.XLOOKUP($A57,Korrelation!$D$4:$D$1197,Korrelation!K$4:K$1197,"-",0)="-",0,MATCH(_xlfn.XLOOKUP($A57,Korrelation!$D$4:$D$1197,Korrelation!K$4:K$1197,"",0),'DM01-AV-CH'!$A$6:$A$834,0))) -> 11 | J57: {=IF(B57=0,IF(E57=0,"",HYPERLINK("#"&RIGHT(CELL("adresse",OFFSET(DMAV_Dienste!$M$6,E57-1,0)),LEN(CELL("adresse",OFFSET(DMAV_Dienste!$M$6,E57-1,0)))-FIND("]",CELL("adresse",OFFSET(DMAV_Dienste!$M$6,E57-1,0)))),"Dienst")),HYPERLINK("#"&RIGHT(CELL("adresse",OFFSET(DMAV_Modell!$N$6,B57-1,0)),LEN(CELL("adresse",OFFSET(DMAV_Modell!$N$6,B57-1,0)))-FIND("]",CELL("adresse",OFFSET(DMAV_Modell!$N$6,B57-1,0)))),"Modell"))} -> Modell | K57: {=IF($B57=0,IF($E57=0,"",IF(INDEX(DMAV_Dienste!P$6:P$140,$E57)="","",INDEX(DMAV_Dienste!P$6:P$140,$E57))),IF(INDEX(DMAV_Modell!Q$6:Q$838,$B57)="","",INDEX(DMAV_Modell!Q$6:Q$838,$B57)))} -> DOMAIN | L57: {=IF($B57=0,IF($E57=0,"",IF(INDEX(DMAV_Dienste!O$6:O$140,$E57)="","",INDEX(DMAV_Dienste!O$6:O$140,$E57))),IF(INDEX(DMAV_Modell!P$6:P$838,$B57)="","",INDEX(DMAV_Modell!P$6:P$838,$B57)))} | M57: {=IF($B57=0,IF($E57=0,"",IF(INDEX(DMAV_Dienste!Q$6:Q$140,$E57)="","",INDEX(DMAV_Dienste!Q$6:Q$140,$E57))),IF(INDEX(DMAV_Modell!R$6:R$838,$B57)="","",INDEX(DMAV_Modell!R$6:R$838,$B57)))} -> Qualitaetsstandard | N57: {=IF($B57=0,IF($E57=0,"",IF(INDEX(DMAV_Dienste!T$6:T$140,$E57)="","",INDEX(DMAV_Dienste!T$6:T$140,$E57))),IF(INDEX(DMAV_Modell!U$6:U$838,$B57)="","",INDEX(DMAV_Modell!U$6:U$838,$B57)))} | O57: {=IF(C57=0,IF(F57=0,"",HYPERLINK("#"&RIGHT(CELL("adresse",OFFSET(DMAV_Dienste!$M$6,F57-1,0)),LEN(CELL("adresse",OFFSET(DMAV_Dienste!$M$6,F57-1,0)))-FIND("]",CELL("adresse",OFFSET(DMAV_Dienste!$M$6,F57-1,0)))),"Structure")),HYPERLINK("#"&RIGHT(CELL("adresse",OFFSET(DMAV_Modell!$N$6,C57-1,0)),LEN(CELL("adresse",OFFSET(DMAV_Modell!$N$6,C57-1,0)))-FIND("]",CELL("adresse",OFFSET(DMAV_Modell!$N$6,C57-1,0)))),"Structure"))} | P57: {=IF(D57=0,IF(G57=0,"",HYPERLINK("#"&RIGHT(CELL("adresse",OFFSET(DMAV_Dienste!$M$6,G57-1,0)),LEN(CELL("adresse",OFFSET(DMAV_Dienste!$M$6,G57-1,0)))-FIND("]",CELL("adresse",OFFSET(DMAV_Dienste!$M$6,G57-1,0)))),"Substructure")),HYPERLINK("#"&RIGHT(CELL("adresse",OFFSET(DMAV_Modell!$N$6,D57-1,0)),LEN(CELL("adresse",OFFSET(DMAV_Modell!$N$6,D57-1,0)))-FIND("]",CELL("adresse",OFFSET(DMAV_Modell!$N$6,D57-1,0)))),"Substructure"))} | AF57: {=IF(H57=0,"",HYPERLINK("#"&RIGHT(CELL("adresse",OFFSET('DM01-AV-CH'!$G$6,H57-1,0)),LEN(CELL("adresse",OFFSET('DM01-AV-CH'!$G$6,H57-1,0)))-FIND("]",CELL("adresse",OFFSET('DM01-AV-CH'!$G$6,H57-1,0)))),"Modell"))} -> Modell | AG57: {=IF($H57=0,"",IF(INDEX('DM01-AV-CH'!G$6:G$834,$H57)="","",INDEX('DM01-AV-CH'!G$6:G$834,$H57)))} -> Allgemein | AH57: {=IF($H57=0,"",IF(INDEX('DM01-AV-CH'!H$6:H$834,$H57)="","",INDEX('DM01-AV-CH'!H$6:H$834,$H57)))} | AI57: {=IF($H57=0,"",IF(INDEX('DM01-AV-CH'!I$6:I$834,$H57)="","",INDEX('DM01-AV-CH'!I$6:I$834,$H57)))} -> Qualitaetsstandard
A58: 53 | B58: =IF($A58="","",IF(_xlfn.XLOOKUP($A58,Korrelation!$D$4:$D$1197,Korrelation!E$4:E$1197,"-",0)="-",0,MATCH(_xlfn.XLOOKUP($A58,Korrelation!$D$4:$D$1197,Korrelation!E$4:E$1197,"",0),DMAV_Modell!$G$6:$G$677,0))) -> 0 | C58: =IF($A58="","",IF(_xlfn.XLOOKUP($A58,Korrelation!$D$4:$D$1197,Korrelation!F$4:F$1197,"-",0)="-",0,MATCH(_xlfn.XLOOKUP($A58,Korrelation!$D$4:$D$1197,Korrelation!F$4:F$1197,"",0),DMAV_Modell!$G$6:$G$677,0))) -> 0 | D58: =IF($A58="","",IF(_xlfn.XLOOKUP($A58,Korrelation!$D$4:$D$1197,Korrelation!G$4:G$1197,"-",0)="-",0,MATCH(_xlfn.XLOOKUP($A58,Korrelation!$D$4:$D$1197,Korrelation!G$4:G$1197,"",0),DMAV_Modell!$G$6:$G$677,0))) -> 0 | E58: =IF($A58="","",IF(_xlfn.XLOOKUP($A58,Korrelation!$D$4:$D$1197,Korrelation!H$4:H$1197,"-",0)="-",0,MATCH(_xlfn.XLOOKUP($A58,Korrelation!$D$4:$D$1197,Korrelation!H$4:H$1197,"",0),DMAV_Dienste!$F$6:$F$140,0))) -> 0 | F58: =IF($A58="","",IF(_xlfn.XLOOKUP($A58,Korrelation!$D$4:$D$1197,Korrelation!I$4:I$1197,"-",0)="-",0,MATCH(_xlfn.XLOOKUP($A58,Korrelation!$D$4:$D$1197,Korrelation!I$4:I$1197,"",0),DMAV_Dienste!$F$6:$F$140,0))) -> 0 | G58: =IF($A58="","",IF(_xlfn.XLOOKUP($A58,Korrelation!$D$4:$D$1197,Korrelation!J$4:J$1197,"-",0)="-",0,MATCH(_xlfn.XLOOKUP($A58,Korrelation!$D$4:$D$1197,Korrelation!J$4:J$1197,"",0),DMAV_Dienste!$F$6:$F$140,0))) -> 0 | H58: =IF($A58="","",IF(_xlfn.XLOOKUP($A58,Korrelation!$D$4:$D$1197,Korrelation!K$4:K$1197,"-",0)="-",0,MATCH(_xlfn.XLOOKUP($A58,Korrelation!$D$4:$D$1197,Korrelation!K$4:K$1197,"",0),'DM01-AV-CH'!$A$6:$A$834,0))) -> 12 | J58: {=IF(B58=0,IF(E58=0,"",HYPERLINK("#"&RIGHT(CELL("adresse",OFFSET(DMAV_Dienste!$M$6,E58-1,0)),LEN(CELL("adresse",OFFSET(DMAV_Dienste!$M$6,E58-1,0)))-FIND("]",CELL("adresse",OFFSET(DMAV_Dienste!$M$6,E58-1,0)))),"Dienst")),HYPERLINK("#"&RIGHT(CELL("adresse",OFFSET(DMAV_Modell!$N$6,B58-1,0)),LEN(CELL("adresse",OFFSET(DMAV_Modell!$N$6,B58-1,0)))-FIND("]",CELL("adresse",OFFSET(DMAV_Modell!$N$6,B58-1,0)))),"Modell"))} | K58: {=IF($B58=0,IF($E58=0,"",IF(INDEX(DMAV_Dienste!P$6:P$140,$E58)="","",INDEX(DMAV_Dienste!P$6:P$140,$E58))),IF(INDEX(DMAV_Modell!Q$6:Q$838,$B58)="","",INDEX(DMAV_Modell!Q$6:Q$838,$B58)))} | L58: {=IF($B58=0,IF($E58=0,"",IF(INDEX(DMAV_Dienste!O$6:O$140,$E58)="","",INDEX(DMAV_Dienste!O$6:O$140,$E58))),IF(INDEX(DMAV_Modell!P$6:P$838,$B58)="","",INDEX(DMAV_Modell!P$6:P$838,$B58)))} | M58: {=IF($B58=0,IF($E58=0,"",IF(INDEX(DMAV_Dienste!Q$6:Q$140,$E58)="","",INDEX(DMAV_Dienste!Q$6:Q$140,$E58))),IF(INDEX(DMAV_Modell!R$6:R$838,$B58)="","",INDEX(DMAV_Modell!R$6:R$838,$B58)))} | N58: {=IF($B58=0,IF($E58=0,"",IF(INDEX(DMAV_Dienste!T$6:T$140,$E58)="","",INDEX(DMAV_Dienste!T$6:T$140,$E58))),IF(INDEX(DMAV_Modell!U$6:U$838,$B58)="","",INDEX(DMAV_Modell!U$6:U$838,$B58)))} | O58: {=IF(C58=0,IF(F58=0,"",HYPERLINK("#"&RIGHT(CELL("adresse",OFFSET(DMAV_Dienste!$M$6,F58-1,0)),LEN(CELL("adresse",OFFSET(DMAV_Dienste!$M$6,F58-1,0)))-FIND("]",CELL("adresse",OFFSET(DMAV_Dienste!$M$6,F58-1,0)))),"Structure")),HYPERLINK("#"&RIGHT(CELL("adresse",OFFSET(DMAV_Modell!$N$6,C58-1,0)),LEN(CELL("adresse",OFFSET(DMAV_Modell!$N$6,C58-1,0)))-FIND("]",CELL("adresse",OFFSET(DMAV_Modell!$N$6,C58-1,0)))),"Structure"))} | P58: {=IF(D58=0,IF(G58=0,"",HYPERLINK("#"&RIGHT(CELL("adresse",OFFSET(DMAV_Dienste!$M$6,G58-1,0)),LEN(CELL("adresse",OFFSET(DMAV_Dienste!$M$6,G58-1,0)))-FIND("]",CELL("adresse",OFFSET(DMAV_Dienste!$M$6,G58-1,0)))),"Substructure")),HYPERLINK("#"&RIGHT(CELL("adresse",OFFSET(DMAV_Modell!$N$6,D58-1,0)),LEN(CELL("adresse",OFFSET(DMAV_Modell!$N$6,D58-1,0)))-FIND("]",CELL("adresse",OFFSET(DMAV_Modell!$N$6,D58-1,0)))),"Substructure"))} | AF58: {=IF(H58=0,"",HYPERLINK("#"&RIGHT(CELL("adresse",OFFSET('DM01-AV-CH'!$G$6,H58-1,0)),LEN(CELL("adresse",OFFSET('DM01-AV-CH'!$G$6,H58-1,0)))-FIND("]",CELL("adresse",OFFSET('DM01-AV-CH'!$G$6,H58-1,0)))),"Modell"))} -> Modell | AG58: {=IF($H58=0,"",IF(INDEX('DM01-AV-CH'!G$6:G$834,$H58)="","",INDEX('DM01-AV-CH'!G$6:G$834,$H58)))} -> Allgemein | AH58: {=IF($H58=0,"",IF(INDEX('DM01-AV-CH'!H$6:H$834,$H58)="","",INDEX('DM01-AV-CH'!H$6:H$834,$H58)))} | AI58: {=IF($H58=0,"",IF(INDEX('DM01-AV-CH'!I$6:I$834,$H58)="","",INDEX('DM01-AV-CH'!I$6:I$834,$H58)))} -> Qualitaetsstandard
A59: 54 | B59: =IF($A59="","",IF(_xlfn.XLOOKUP($A59,Korrelation!$D$4:$D$1197,Korrelation!E$4:E$1197,"-",0)="-",0,MATCH(_xlfn.XLOOKUP($A59,Korrelation!$D$4:$D$1197,Korrelation!E$4:E$1197,"",0),DMAV_Modell!$G$6:$G$677,0))) -> 0 | C59: =IF($A59="","",IF(_xlfn.XLOOKUP($A59,Korrelation!$D$4:$D$1197,Korrelation!F$4:F$1197,"-",0)="-",0,MATCH(_xlfn.XLOOKUP($A59,Korrelation!$D$4:$D$1197,Korrelation!F$4:F$1197,"",0),DMAV_Modell!$G$6:$G$677,0))) -> 0 | D59: =IF($A59="","",IF(_xlfn.XLOOKUP($A59,Korrelation!$D$4:$D$1197,Korrelation!G$4:G$1197,"-",0)="-",0,MATCH(_xlfn.XLOOKUP($A59,Korrelation!$D$4:$D$1197,Korrelation!G$4:G$1197,"",0),DMAV_Modell!$G$6:$G$677,0))) -> 0 | E59: =IF($A59="","",IF(_xlfn.XLOOKUP($A59,Korrelation!$D$4:$D$1197,Korrelation!H$4:H$1197,"-",0)="-",0,MATCH(_xlfn.XLOOKUP($A59,Korrelation!$D$4:$D$1197,Korrelation!H$4:H$1197,"",0),DMAV_Dienste!$F$6:$F$140,0))) -> 0 | F59: =IF($A59="","",IF(_xlfn.XLOOKUP($A59,Korrelation!$D$4:$D$1197,Korrelation!I$4:I$1197,"-",0)="-",0,MATCH(_xlfn.XLOOKUP($A59,Korrelation!$D$4:$D$1197,Korrelation!I$4:I$1197,"",0),DMAV_Dienste!$F$6:$F$140,0))) -> 0 | G59: =IF($A59="","",IF(_xlfn.XLOOKUP($A59,Korrelation!$D$4:$D$1197,Korrelation!J$4:J$1197,"-",0)="-",0,MATCH(_xlfn.XLOOKUP($A59,Korrelation!$D$4:$D$1197,Korrelation!J$4:J$1197,"",0),DMAV_Dienste!$F$6:$F$140,0))) -> 0 | H59: =IF($A59="","",IF(_xlfn.XLOOKUP($A59,Korrelation!$D$4:$D$1197,Korrelation!K$4:K$1197,"-",0)="-",0,MATCH(_xlfn.XLOOKUP($A59,Korrelation!$D$4:$D$1197,Korrelation!K$4:K$1197,"",0),'DM01-AV-CH'!$A$6:$A$834,0))) -> 13 | J59: {=IF(B59=0,IF(E59=0,"",HYPERLINK("#"&RIGHT(CELL("adresse",OFFSET(DMAV_Dienste!$M$6,E59-1,0)),LEN(CELL("adresse",OFFSET(DMAV_Dienste!$M$6,E59-1,0)))-FIND("]",CELL("adresse",OFFSET(DMAV_Dienste!$M$6,E59-1,0)))),"Dienst")),HYPERLINK("#"&RIGHT(CELL("adresse",OFFSET(DMAV_Modell!$N$6,B59-1,0)),LEN(CELL("adresse",OFFSET(DMAV_Modell!$N$6,B59-1,0)))-FIND("]",CELL("adresse",OFFSET(DMAV_Modell!$N$6,B59-1,0)))),"Modell"))} | K59: {=IF($B59=0,IF($E59=0,"",IF(INDEX(DMAV_Dienste!P$6:P$140,$E59)="","",INDEX(DMAV_Dienste!P$6:P$140,$E59))),IF(INDEX(DMAV_Modell!Q$6:Q$838,$B59)="","",INDEX(DMAV_Modell!Q$6:Q$838,$B59)))} | L59: {=IF($B59=0,IF($E59=0,"",IF(INDEX(DMAV_Dienste!O$6:O$140,$E59)="","",INDEX(DMAV_Dienste!O$6:O$140,$E59))),IF(INDEX(DMAV_Modell!P$6:P$838,$B59)="","",INDEX(DMAV_Modell!P$6:P$838,$B59)))} | M59: {=IF($B59=0,IF($E59=0,"",IF(INDEX(DMAV_Dienste!Q$6:Q$140,$E59)="","",INDEX(DMAV_Dienste!Q$6:Q$140,$E59))),IF(INDEX(DMAV_Modell!R$6:R$838,$B59)="","",INDEX(DMAV_Modell!R$6:R$838,$B59)))} | N59: {=IF($B59=0,IF($E59=0,"",IF(INDEX(DMAV_Dienste!T$6:T$140,$E59)="","",INDEX(DMAV_Dienste!T$6:T$140,$E59))),IF(INDEX(DMAV_Modell!U$6:U$838,$B59)="","",INDEX(DMAV_Modell!U$6:U$838,$B59)))} | O59: {=IF(C59=0,IF(F59=0,"",HYPERLINK("#"&RIGHT(CELL("adresse",OFFSET(DMAV_Dienste!$M$6,F59-1,0)),LEN(CELL("adresse",OFFSET(DMAV_Dienste!$M$6,F59-1,0)))-FIND("]",CELL("adresse",OFFSET(DMAV_Dienste!$M$6,F59-1,0)))),"Structure")),HYPERLINK("#"&RIGHT(CELL("adresse",OFFSET(DMAV_Modell!$N$6,C59-1,0)),LEN(CELL("adresse",OFFSET(DMAV_Modell!$N$6,C59-1,0)))-FIND("]",CELL("adresse",OFFSET(DMAV_Modell!$N$6,C59-1,0)))),"Structure"))} | P59: {=IF(D59=0,IF(G59=0,"",HYPERLINK("#"&RIGHT(CELL("adresse",OFFSET(DMAV_Dienste!$M$6,G59-1,0)),LEN(CELL("adresse",OFFSET(DMAV_Dienste!$M$6,G59-1,0)))-FIND("]",CELL("adresse",OFFSET(DMAV_Dienste!$M$6,G59-1,0)))),"Substructure")),HYPERLINK("#"&RIGHT(CELL("adresse",OFFSET(DMAV_Modell!$N$6,D59-1,0)),LEN(CELL("adresse",OFFSET(DMAV_Modell!$N$6,D59-1,0)))-FIND("]",CELL("adresse",OFFSET(DMAV_Modell!$N$6,D59-1,0)))),"Substructure"))} | AF59: {=IF(H59=0,"",HYPERLINK("#"&RIGHT(CELL("adresse",OFFSET('DM01-AV-CH'!$G$6,H59-1,0)),LEN(CELL("adresse",OFFSET('DM01-AV-CH'!$G$6,H59-1,0)))-FIND("]",CELL("adresse",OFFSET('DM01-AV-CH'!$G$6,H59-1,0)))),"Modell"))} -> Modell | AG59: {=IF($H59=0,"",IF(INDEX('DM01-AV-CH'!G$6:G$834,$H59)="","",INDEX('DM01-AV-CH'!G$6:G$834,$H59)))} -> Allgemein | AH59: {=IF($H59=0,"",IF(INDEX('DM01-AV-CH'!H$6:H$834,$H59)="","",INDEX('DM01-AV-CH'!H$6:H$834,$H59)))} | AI59: {=IF($H59=0,"",IF(INDEX('DM01-AV-CH'!I$6:I$834,$H59)="","",INDEX('DM01-AV-CH'!I$6:I$834,$H59)))} -> Qualitaetsstandard
A60: 55 | B60: =IF($A60="","",IF(_xlfn.XLOOKUP($A60,Korrelation!$D$4:$D$1197,Korrelation!E$4:E$1197,"-",0)="-",0,MATCH(_xlfn.XLOOKUP($A60,Korrelation!$D$4:$D$1197,Korrelation!E$4:E$1197,"",0),DMAV_Modell!$G$6:$G$677,0))) -> 44 | C60: =IF($A60="","",IF(_xlfn.XLOOKUP($A60,Korrelation!$D$4:$D$1197,Korrelation!F$4:F$1197,"-",0)="-",0,MATCH(_xlfn.XLOOKUP($A60,Korrelation!$D$4:$D$1197,Korrelation!F$4:F$1197,"",0),DMAV_Modell!$G$6:$G$677,0))) -> 0 | D60: =IF($A60="","",IF(_xlfn.XLOOKUP($A60,Korrelation!$D$4:$D$1197,Korrelation!G$4:G$1197,"-",0)="-",0,MATCH(_xlfn.XLOOKUP($A60,Korrelation!$D$4:$D$1197,Korrelation!G$4:G$1197,"",0),DMAV_Modell!$G$6:$G$677,0))) -> 0 | E60: =IF($A60="","",IF(_xlfn.XLOOKUP($A60,Korrelation!$D$4:$D$1197,Korrelation!H$4:H$1197,"-",0)="-",0,MATCH(_xlfn.XLOOKUP($A60,Korrelation!$D$4:$D$1197,Korrelation!H$4:H$1197,"",0),DMAV_Dienste!$F$6:$F$140,0))) -> 0 | F60: =IF($A60="","",IF(_xlfn.XLOOKUP($A60,Korrelation!$D$4:$D$1197,Korrelation!I$4:I$1197,"-",0)="-",0,MATCH(_xlfn.XLOOKUP($A60,Korrelation!$D$4:$D$1197,Korrelation!I$4:I$1197,"",0),DMAV_Dienste!$F$6:$F$140,0))) -> 0 | G60: =IF($A60="","",IF(_xlfn.XLOOKUP($A60,Korrelation!$D$4:$D$1197,Korrelation!J$4:J$1197,"-",0)="-",0,MATCH(_xlfn.XLOOKUP($A60,Korrelation!$D$4:$D$1197,Korrelation!J$4:J$1197,"",0),DMAV_Dienste!$F$6:$F$140,0))) -> 0 | H60: =IF($A60="","",IF(_xlfn.XLOOKUP($A60,Korrelation!$D$4:$D$1197,Korrelation!K$4:K$1197,"-",0)="-",0,MATCH(_xlfn.XLOOKUP($A60,Korrelation!$D$4:$D$1197,Korrelation!K$4:K$1197,"",0),'DM01-AV-CH'!$A$6:$A$834,0))) -> 0 | J60: {=IF(B60=0,IF(E60=0,"",HYPERLINK("#"&RIGHT(CELL("adresse",OFFSET(DMAV_Dienste!$M$6,E60-1,0)),LEN(CELL("adresse",OFFSET(DMAV_Dienste!$M$6,E60-1,0)))-FIND("]",CELL("adresse",OFFSET(DMAV_Dienste!$M$6,E60-1,0)))),"Dienst")),HYPERLINK("#"&RIGHT(CELL("adresse",OFFSET(DMAV_Modell!$N$6,B60-1,0)),LEN(CELL("adresse",OFFSET(DMAV_Modell!$N$6,B60-1,0)))-FIND("]",CELL("adresse",OFFSET(DMAV_Modell!$N$6,B60-1,0)))),"Modell"))} -> Modell | K60: {=IF($B60=0,IF($E60=0,"",IF(INDEX(DMAV_Dienste!P$6:P$140,$E60)="","",INDEX(DMAV_Dienste!P$6:P$140,$E60))),IF(INDEX(DMAV_Modell!Q$6:Q$838,$B60)="","",INDEX(DMAV_Modell!Q$6:Q$838,$B60)))} -> FUNCTION | L60: {=IF($B60=0,IF($E60=0,"",IF(INDEX(DMAV_Dienste!O$6:O$140,$E60)="","",INDEX(DMAV_Dienste!O$6:O$140,$E60))),IF(INDEX(DMAV_Modell!P$6:P$838,$B60)="","",INDEX(DMAV_Modell!P$6:P$838,$B60)))} | M60: {=IF($B60=0,IF($E60=0,"",IF(INDEX(DMAV_Dienste!Q$6:Q$140,$E60)="","",INDEX(DMAV_Dienste!Q$6:Q$140,$E60))),IF(INDEX(DMAV_Modell!R$6:R$838,$B60)="","",INDEX(DMAV_Modell!R$6:R$838,$B60)))} -> covers | N60: {=IF($B60=0,IF($E60=0,"",IF(INDEX(DMAV_Dienste!T$6:T$140,$E60)="","",INDEX(DMAV_Dienste!T$6:T$140,$E60))),IF(INDEX(DMAV_Modell!U$6:U$838,$B60)="","",INDEX(DMAV_Modell!U$6:U$838,$B60)))} -> SurfaceObjects: CLASS; SurfaceAttr: ATTRIBUTE; MultiLineObject: ANYSTRUCTURE; MultiLineAttr: ATTRIBUTE | O60: {=IF(C60=0,IF(F60=0,"",HYPERLINK("#"&RIGHT(CELL("adresse",OFFSET(DMAV_Dienste!$M$6,F60-1,0)),LEN(CELL("adresse",OFFSET(DMAV_Dienste!$M$6,F60-1,0)))-FIND("]",CELL("adresse",OFFSET(DMAV_Dienste!$M$6,F60-1,0)))),"Structure")),HYPERLINK("#"&RIGHT(CELL("adresse",OFFSET(DMAV_Modell!$N$6,C60-1,0)),LEN(CELL("adresse",OFFSET(DMAV_Modell!$N$6,C60-1,0)))-FIND("]",CELL("adresse",OFFSET(DMAV_Modell!$N$6,C60-1,0)))),"Structure"))} | P60: {=IF(D60=0,IF(G60=0,"",HYPERLINK("#"&RIGHT(CELL("adresse",OFFSET(DMAV_Dienste!$M$6,G60-1,0)),LEN(CELL("adresse",OFFSET(DMAV_Dienste!$M$6,G60-1,0)))-FIND("]",CELL("adresse",OFFSET(DMAV_Dienste!$M$6,G60-1,0)))),"Substructure")),HYPERLINK("#"&RIGHT(CELL("adresse",OFFSET(DMAV_Modell!$N$6,D60-1,0)),LEN(CELL("adresse",OFFSET(DMAV_Modell!$N$6,D60-1,0)))-FIND("]",CELL("adresse",OFFSET(DMAV_Modell!$N$6,D60-1,0)))),"Substructure"))} | AF60: {=IF(H60=0,"",HYPERLINK("#"&RIGHT(CELL("adresse",OFFSET('DM01-AV-CH'!$G$6,H60-1,0)),LEN(CELL("adresse",OFFSET('DM01-AV-CH'!$G$6,H60-1,0)))-FIND("]",CELL("adresse",OFFSET('DM01-AV-CH'!$G$6,H60-1,0)))),"Modell"))} | AG60: {=IF($H60=0,"",IF(INDEX('DM01-AV-CH'!G$6:G$834,$H60)="","",INDEX('DM01-AV-CH'!G$6:G$834,$H60)))} | AH60: {=IF($H60=0,"",IF(INDEX('DM01-AV-CH'!H$6:H$834,$H60)="","",INDEX('DM01-AV-CH'!H$6:H$834,$H60)))} | AI60: {=IF($H60=0,"",IF(INDEX('DM01-AV-CH'!I$6:I$834,$H60)="","",INDEX('DM01-AV-CH'!I$6:I$834,$H60)))}
A61: 56 | B61: =IF($A61="","",IF(_xlfn.XLOOKUP($A61,Korrelation!$D$4:$D$1197,Korrelation!E$4:E$1197,"-",0)="-",0,MATCH(_xlfn.XLOOKUP($A61,Korrelation!$D$4:$D$1197,Korrelation!E$4:E$1197,"",0),DMAV_Modell!$G$6:$G$677,0))) -> 45 | C61: =IF($A61="","",IF(_xlfn.XLOOKUP($A61,Korrelation!$D$4:$D$1197,Korrelation!F$4:F$1197,"-",0)="-",0,MATCH(_xlfn.XLOOKUP($A61,Korrelation!$D$4:$D$1197,Korrelation!F$4:F$1197,"",0),DMAV_Modell!$G$6:$G$677,0))) -> 0 | D61: =IF($A61="","",IF(_xlfn.XLOOKUP($A61,Korrelation!$D$4:$D$1197,Korrelation!G$4:G$1197,"-",0)="-",0,MATCH(_xlfn.XLOOKUP($A61,Korrelation!$D$4:$D$1197,Korrelation!G$4:G$1197,"",0),DMAV_Modell!$G$6:$G$677,0))) -> 0 | E61: =IF($A61="","",IF(_xlfn.XLOOKUP($A61,Korrelation!$D$4:$D$1197,Korrelation!H$4:H$1197,"-",0)="-",0,MATCH(_xlfn.XLOOKUP($A61,Korrelation!$D$4:$D$1197,Korrelation!H$4:H$1197,"",0),DMAV_Dienste!$F$6:$F$140,0))) -> 0 | F61: =IF($A61="","",IF(_xlfn.XLOOKUP($A61,Korrelation!$D$4:$D$1197,Korrelation!I$4:I$1197,"-",0)="-",0,MATCH(_xlfn.XLOOKUP($A61,Korrelation!$D$4:$D$1197,Korrelation!I$4:I$1197,"",0),DMAV_Dienste!$F$6:$F$140,0))) -> 0 | G61: =IF($A61="","",IF(_xlfn.XLOOKUP($A61,Korrelation!$D$4:$D$1197,Korrelation!J$4:J$1197,"-",0)="-",0,MATCH(_xlfn.XLOOKUP($A61,Korrelation!$D$4:$D$1197,Korrelation!J$4:J$1197,"",0),DMAV_Dienste!$F$6:$F$140,0))) -> 0 | H61: =IF($A61="","",IF(_xlfn.XLOOKUP($A61,Korrelation!$D$4:$D$1197,Korrelation!K$4:K$1197,"-",0)="-",0,MATCH(_xlfn.XLOOKUP($A61,Korrelation!$D$4:$D$1197,Korrelation!K$4:K$1197,"",0),'DM01-AV-CH'!$A$6:$A$834,0))) -> 21 | J61: {=IF(B61=0,IF(E61=0,"",HYPERLINK("#"&RIGHT(CELL("adresse",OFFSET(DMAV_Dienste!$M$6,E61-1,0)),LEN(CELL("adresse",OFFSET(DMAV_Dienste!$M$6,E61-1,0)))-FIND("]",CELL("adresse",OFFSET(DMAV_Dienste!$M$6,E61-1,0)))),"Dienst")),HYPERLINK("#"&RIGHT(CELL("adresse",OFFSET(DMAV_Modell!$N$6,B61-1,0)),LEN(CELL("adresse",OFFSET(DMAV_Modell!$N$6,B61-1,0)))-FIND("]",CELL("adresse",OFFSET(DMAV_Modell!$N$6,B61-1,0)))),"Modell"))} -> Modell | K61: {=IF($B61=0,IF($E61=0,"",IF(INDEX(DMAV_Dienste!P$6:P$140,$E61)="","",INDEX(DMAV_Dienste!P$6:P$140,$E61))),IF(INDEX(DMAV_Modell!Q$6:Q$838,$B61)="","",INDEX(DMAV_Modell!Q$6:Q$838,$B61)))} -> DOMAIN | L61: {=IF($B61=0,IF($E61=0,"",IF(INDEX(DMAV_Dienste!O$6:O$140,$E61)="","",INDEX(DMAV_Dienste!O$6:O$140,$E61))),IF(INDEX(DMAV_Modell!P$6:P$838,$B61)="","",INDEX(DMAV_Modell!P$6:P$838,$B61)))} | M61: {=IF($B61=0,IF($E61=0,"",IF(INDEX(DMAV_Dienste!Q$6:Q$140,$E61)="","",INDEX(DMAV_Dienste!Q$6:Q$140,$E61))),IF(INDEX(DMAV_Modell!R$6:R$838,$B61)="","",INDEX(DMAV_Modell!R$6:R$838,$B61)))} -> Versicherungsart | N61: {=IF($B61=0,IF($E61=0,"",IF(INDEX(DMAV_Dienste!T$6:T$140,$E61)="","",INDEX(DMAV_Dienste!T$6:T$140,$E61))),IF(INDEX(DMAV_Modell!U$6:U$838,$B61)="","",INDEX(DMAV_Modell!U$6:U$838,$B61)))} | O61: {=IF(C61=0,IF(F61=0,"",HYPERLINK("#"&RIGHT(CELL("adresse",OFFSET(DMAV_Dienste!$M$6,F61-1,0)),LEN(CELL("adresse",OFFSET(DMAV_Dienste!$M$6,F61-1,0)))-FIND("]",CELL("adresse",OFFSET(DMAV_Dienste!$M$6,F61-1,0)))),"Structure")),HYPERLINK("#"&RIGHT(CELL("adresse",OFFSET(DMAV_Modell!$N$6,C61-1,0)),LEN(CELL("adresse",OFFSET(DMAV_Modell!$N$6,C61-1,0)))-FIND("]",CELL("adresse",OFFSET(DMAV_Modell!$N$6,C61-1,0)))),"Structure"))} | P61: {=IF(D61=0,IF(G61=0,"",HYPERLINK("#"&RIGHT(CELL("adresse",OFFSET(DMAV_Dienste!$M$6,G61-1,0)),LEN(CELL("adresse",OFFSET(DMAV_Dienste!$M$6,G61-1,0)))-FIND("]",CELL("adresse",OFFSET(DMAV_Dienste!$M$6,G61-1,0)))),"Substructure")),HYPERLINK("#"&RIGHT(CELL("adresse",OFFSET(DMAV_Modell!$N$6,D61-1,0)),LEN(CELL("adresse",OFFSET(DMAV_Modell!$N$6,D61-1,0)))-FIND("]",CELL("adresse",OFFSET(DMAV_Modell!$N$6,D61-1,0)))),"Substructure"))} | AF61: {=IF(H61=0,"",HYPERLINK("#"&RIGHT(CELL("adresse",OFFSET('DM01-AV-CH'!$G$6,H61-1,0)),LEN(CELL("adresse",OFFSET('DM01-AV-CH'!$G$6,H61-1,0)))-FIND("]",CELL("adresse",OFFSET('DM01-AV-CH'!$G$6,H61-1,0)))),"Modell"))} -> Modell | AG61: {=IF($H61=0,"",IF(INDEX('DM01-AV-CH'!G$6:G$834,$H61)="","",INDEX('DM01-AV-CH'!G$6:G$834,$H61)))} -> Allgemein | AH61: {=IF($H61=0,"",IF(INDEX('DM01-AV-CH'!H$6:H$834,$H61)="","",INDEX('DM01-AV-CH'!H$6:H$834,$H61)))} | AI61: {=IF($H61=0,"",IF(INDEX('DM01-AV-CH'!I$6:I$834,$H61)="","",INDEX('DM01-AV-CH'!I$6:I$834,$H61)))} -> Versicherungsart
A62: 57 | B62: =IF($A62="","",IF(_xlfn.XLOOKUP($A62,Korrelation!$D$4:$D$1197,Korrelation!E$4:E$1197,"-",0)="-",0,MATCH(_xlfn.XLOOKUP($A62,Korrelation!$D$4:$D$1197,Korrelation!E$4:E$1197,"",0),DMAV_Modell!$G$6:$G$677,0))) -> 46 | C62: =IF($A62="","",IF(_xlfn.XLOOKUP($A62,Korrelation!$D$4:$D$1197,Korrelation!F$4:F$1197,"-",0)="-",0,MATCH(_xlfn.XLOOKUP($A62,Korrelation!$D$4:$D$1197,Korrelation!F$4:F$1197,"",0),DMAV_Modell!$G$6:$G$677,0))) -> 0 | D62: =IF($A62="","",IF(_xlfn.XLOOKUP($A62,Korrelation!$D$4:$D$1197,Korrelation!G$4:G$1197,"-",0)="-",0,MATCH(_xlfn.XLOOKUP($A62,Korrelation!$D$4:$D$1197,Korrelation!G$4:G$1197,"",0),DMAV_Modell!$G$6:$G$677,0))) -> 0 | E62: =IF($A62="","",IF(_xlfn.XLOOKUP($A62,Korrelation!$D$4:$D$1197,Korrelation!H$4:H$1197,"-",0)="-",0,MATCH(_xlfn.XLOOKUP($A62,Korrelation!$D$4:$D$1197,Korrelation!H$4:H$1197,"",0),DMAV_Dienste!$F$6:$F$140,0))) -> 0 | F62: =IF($A62="","",IF(_xlfn.XLOOKUP($A62,Korrelation!$D$4:$D$1197,Korrelation!I$4:I$1197,"-",0)="-",0,MATCH(_xlfn.XLOOKUP($A62,Korrelation!$D$4:$D$1197,Korrelation!I$4:I$1197,"",0),DMAV_Dienste!$F$6:$F$140,0))) -> 0 | G62: =IF($A62="","",IF(_xlfn.XLOOKUP($A62,Korrelation!$D$4:$D$1197,Korrelation!J$4:J$1197,"-",0)="-",0,MATCH(_xlfn.XLOOKUP($A62,Korrelation!$D$4:$D$1197,Korrelation!J$4:J$1197,"",0),DMAV_Dienste!$F$6:$F$140,0))) -> 0 | H62: =IF($A62="","",IF(_xlfn.XLOOKUP($A62,Korrelation!$D$4:$D$1197,Korrelation!K$4:K$1197,"-",0)="-",0,MATCH(_xlfn.XLOOKUP($A62,Korrelation!$D$4:$D$1197,Korrelation!K$4:K$1197,"",0),'DM01-AV-CH'!$A$6:$A$834,0))) -> 22 | J62: {=IF(B62=0,IF(E62=0,"",HYPERLINK("#"&RIGHT(CELL("adresse",OFFSET(DMAV_Dienste!$M$6,E62-1,0)),LEN(CELL("adresse",OFFSET(DMAV_Dienste!$M$6,E62-1,0)))-FIND("]",CELL("adresse",OFFSET(DMAV_Dienste!$M$6,E62-1,0)))),"Dienst")),HYPERLINK("#"&RIGHT(CELL("adresse",OFFSET(DMAV_Modell!$N$6,B62-1,0)),LEN(CELL("adresse",OFFSET(DMAV_Modell!$N$6,B62-1,0)))-FIND("]",CELL("adresse",OFFSET(DMAV_Modell!$N$6,B62-1,0)))),"Modell"))} -> Modell | K62: {=IF($B62=0,IF($E62=0,"",IF(INDEX(DMAV_Dienste!P$6:P$140,$E62)="","",INDEX(DMAV_Dienste!P$6:P$140,$E62))),IF(INDEX(DMAV_Modell!Q$6:Q$838,$B62)="","",INDEX(DMAV_Modell!Q$6:Q$838,$B62)))} -> DOMAIN | L62: {=IF($B62=0,IF($E62=0,"",IF(INDEX(DMAV_Dienste!O$6:O$140,$E62)="","",INDEX(DMAV_Dienste!O$6:O$140,$E62))),IF(INDEX(DMAV_Modell!P$6:P$838,$B62)="","",INDEX(DMAV_Modell!P$6:P$838,$B62)))} | M62: {=IF($B62=0,IF($E62=0,"",IF(INDEX(DMAV_Dienste!Q$6:Q$140,$E62)="","",INDEX(DMAV_Dienste!Q$6:Q$140,$E62))),IF(INDEX(DMAV_Modell!R$6:R$838,$B62)="","",INDEX(DMAV_Modell!R$6:R$838,$B62)))} -> Versicherungsart | N62: {=IF($B62=0,IF($E62=0,"",IF(INDEX(DMAV_Dienste!T$6:T$140,$E62)="","",INDEX(DMAV_Dienste!T$6:T$140,$E62))),IF(INDEX(DMAV_Modell!U$6:U$838,$B62)="","",INDEX(DMAV_Modell!U$6:U$838,$B62)))} | O62: {=IF(C62=0,IF(F62=0,"",HYPERLINK("#"&RIGHT(CELL("adresse",OFFSET(DMAV_Dienste!$M$6,F62-1,0)),LEN(CELL("adresse",OFFSET(DMAV_Dienste!$M$6,F62-1,0)))-FIND("]",CELL("adresse",OFFSET(DMAV_Dienste!$M$6,F62-1,0)))),"Structure")),HYPERLINK("#"&RIGHT(CELL("adresse",OFFSET(DMAV_Modell!$N$6,C62-1,0)),LEN(CELL("adresse",OFFSET(DMAV_Modell!$N$6,C62-1,0)))-FIND("]",CELL("adresse",OFFSET(DMAV_Modell!$N$6,C62-1,0)))),"Structure"))} | P62: {=IF(D62=0,IF(G62=0,"",HYPERLINK("#"&RIGHT(CELL("adresse",OFFSET(DMAV_Dienste!$M$6,G62-1,0)),LEN(CELL("adresse",OFFSET(DMAV_Dienste!$M$6,G62-1,0)))-FIND("]",CELL("adresse",OFFSET(DMAV_Dienste!$M$6,G62-1,0)))),"Substructure")),HYPERLINK("#"&RIGHT(CELL("adresse",OFFSET(DMAV_Modell!$N$6,D62-1,0)),LEN(CELL("adresse",OFFSET(DMAV_Modell!$N$6,D62-1,0)))-FIND("]",CELL("adresse",OFFSET(DMAV_Modell!$N$6,D62-1,0)))),"Substructure"))} | AF62: {=IF(H62=0,"",HYPERLINK("#"&RIGHT(CELL("adresse",OFFSET('DM01-AV-CH'!$G$6,H62-1,0)),LEN(CELL("adresse",OFFSET('DM01-AV-CH'!$G$6,H62-1,0)))-FIND("]",CELL("adresse",OFFSET('DM01-AV-CH'!$G$6,H62-1,0)))),"Modell"))} -> Modell | AG62: {=IF($H62=0,"",IF(INDEX('DM01-AV-CH'!G$6:G$834,$H62)="","",INDEX('DM01-AV-CH'!G$6:G$834,$H62)))} -> Allgemein | AH62: {=IF($H62=0,"",IF(INDEX('DM01-AV-CH'!H$6:H$834,$H62)="","",INDEX('DM01-AV-CH'!H$6:H$834,$H62)))} | AI62: {=IF($H62=0,"",IF(INDEX('DM01-AV-CH'!I$6:I$834,$H62)="","",INDEX('DM01-AV-CH'!I$6:I$834,$H62)))} -> Versicherungsart
A63: 58 | B63: =IF($A63="","",IF(_xlfn.XLOOKUP($A63,Korrelation!$D$4:$D$1197,Korrelation!E$4:E$1197,"-",0)="-",0,MATCH(_xlfn.XLOOKUP($A63,Korrelation!$D$4:$D$1197,Korrelation!E$4:E$1197,"",0),DMAV_Modell!$G$6:$G$677,0))) -> 47 | C63: =IF($A63="","",IF(_xlfn.XLOOKUP($A63,Korrelation!$D$4:$D$1197,Korrelation!F$4:F$1197,"-",0)="-",0,MATCH(_xlfn.XLOOKUP($A63,Korrelation!$D$4:$D$1197,Korrelation!F$4:F$1197,"",0),DMAV_Modell!$G$6:$G$677,0))) -> 0 | D63: =IF($A63="","",IF(_xlfn.XLOOKUP($A63,Korrelation!$D$4:$D$1197,Korrelation!G$4:G$1197,"-",0)="-",0,MATCH(_xlfn.XLOOKUP($A63,Korrelation!$D$4:$D$1197,Korrelation!G$4:G$1197,"",0),DMAV_Modell!$G$6:$G$677,0))) -> 0 | E63: =IF($A63="","",IF(_xlfn.XLOOKUP($A63,Korrelation!$D$4:$D$1197,Korrelation!H$4:H$1197,"-",0)="-",0,MATCH(_xlfn.XLOOKUP($A63,Korrelation!$D$4:$D$1197,Korrelation!H$4:H$1197,"",0),DMAV_Dienste!$F$6:$F$140,0))) -> 0 | F63: =IF($A63="","",IF(_xlfn.XLOOKUP($A63,Korrelation!$D$4:$D$1197,Korrelation!I$4:I$1197,"-",0)="-",0,MATCH(_xlfn.XLOOKUP($A63,Korrelation!$D$4:$D$1197,Korrelation!I$4:I$1197,"",0),DMAV_Dienste!$F$6:$F$140,0))) -> 0 | G63: =IF($A63="","",IF(_xlfn.XLOOKUP($A63,Korrelation!$D$4:$D$1197,Korrelation!J$4:J$1197,"-",0)="-",0,MATCH(_xlfn.XLOOKUP($A63,Korrelation!$D$4:$D$1197,Korrelation!J$4:J$1197,"",0),DMAV_Dienste!$F$6:$F$140,0))) -> 0 | H63: =IF($A63="","",IF(_xlfn.XLOOKUP($A63,Korrelation!$D$4:$D$1197,Korrelation!K$4:K$1197,"-",0)="-",0,MATCH(_xlfn.XLOOKUP($A63,Korrelation!$D$4:$D$1197,Korrelation!K$4:K$1197,"",0),'DM01-AV-CH'!$A$6:$A$834,0))) -> 23 | J63: {=IF(B63=0,IF(E63=0,"",HYPERLINK("#"&RIGHT(CELL("adresse",OFFSET(DMAV_Dienste!$M$6,E63-1,0)),LEN(CELL("adresse",OFFSET(DMAV_Dienste!$M$6,E63-1,0)))-FIND("]",CELL("adresse",OFFSET(DMAV_Dienste!$M$6,E63-1,0)))),"Dienst")),HYPERLINK("#"&RIGHT(CELL("adresse",OFFSET(DMAV_Modell!$N$6,B63-1,0)),LEN(CELL("adresse",OFFSET(DMAV_Modell!$N$6,B63-1,0)))-FIND("]",CELL("adresse",OFFSET(DMAV_Modell!$N$6,B63-1,0)))),"Modell"))} -> Modell | K63: {=IF($B63=0,IF($E63=0,"",IF(INDEX(DMAV_Dienste!P$6:P$140,$E63)="","",INDEX(DMAV_Dienste!P$6:P$140,$E63))),IF(INDEX(DMAV_Modell!Q$6:Q$838,$B63)="","",INDEX(DMAV_Modell!Q$6:Q$838,$B63)))} -> DOMAIN | L63: {=IF($B63=0,IF($E63=0,"",IF(INDEX(DMAV_Dienste!O$6:O$140,$E63)="","",INDEX(DMAV_Dienste!O$6:O$140,$E63))),IF(INDEX(DMAV_Modell!P$6:P$838,$B63)="","",INDEX(DMAV_Modell!P$6:P$838,$B63)))} | M63: {=IF($B63=0,IF($E63=0,"",IF(INDEX(DMAV_Dienste!Q$6:Q$140,$E63)="","",INDEX(DMAV_Dienste!Q$6:Q$140,$E63))),IF(INDEX(DMAV_Modell!R$6:R$838,$B63)="","",INDEX(DMAV_Modell!R$6:R$838,$B63)))} -> Versicherungsart | N63: {=IF($B63=0,IF($E63=0,"",IF(INDEX(DMAV_Dienste!T$6:T$140,$E63)="","",INDEX(DMAV_Dienste!T$6:T$140,$E63))),IF(INDEX(DMAV_Modell!U$6:U$838,$B63)="","",INDEX(DMAV_Modell!U$6:U$838,$B63)))} | O63: {=IF(C63=0,IF(F63=0,"",HYPERLINK("#"&RIGHT(CELL("adresse",OFFSET(DMAV_Dienste!$M$6,F63-1,0)),LEN(CELL("adresse",OFFSET(DMAV_Dienste!$M$6,F63-1,0)))-FIND("]",CELL("adresse",OFFSET(DMAV_Dienste!$M$6,F63-1,0)))),"Structure")),HYPERLINK("#"&RIGHT(CELL("adresse",OFFSET(DMAV_Modell!$N$6,C63-1,0)),LEN(CELL("adresse",OFFSET(DMAV_Modell!$N$6,C63-1,0)))-FIND("]",CELL("adresse",OFFSET(DMAV_Modell!$N$6,C63-1,0)))),"Structure"))} | P63: {=IF(D63=0,IF(G63=0,"",HYPERLINK("#"&RIGHT(CELL("adresse",OFFSET(DMAV_Dienste!$M$6,G63-1,0)),LEN(CELL("adresse",OFFSET(DMAV_Dienste!$M$6,G63-1,0)))-FIND("]",CELL("adresse",OFFSET(DMAV_Dienste!$M$6,G63-1,0)))),"Substructure")),HYPERLINK("#"&RIGHT(CELL("adresse",OFFSET(DMAV_Modell!$N$6,D63-1,0)),LEN(CELL("adresse",OFFSET(DMAV_Modell!$N$6,D63-1,0)))-FIND("]",CELL("adresse",OFFSET(DMAV_Modell!$N$6,D63-1,0)))),"Substructure"))} | AF63: {=IF(H63=0,"",HYPERLINK("#"&RIGHT(CELL("adresse",OFFSET('DM01-AV-CH'!$G$6,H63-1,0)),LEN(CELL("adresse",OFFSET('DM01-AV-CH'!$G$6,H63-1,0)))-FIND("]",CELL("adresse",OFFSET('DM01-AV-CH'!$G$6,H63-1,0)))),"Modell"))} -> Modell | AG63: {=IF($H63=0,"",IF(INDEX('DM01-AV-CH'!G$6:G$834,$H63)="","",INDEX('DM01-AV-CH'!G$6:G$834,$H63)))} -> Allgemein | AH63: {=IF($H63=0,"",IF(INDEX('DM01-AV-CH'!H$6:H$834,$H63)="","",INDEX('DM01-AV-CH'!H$6:H$834,$H63)))} | AI63: {=IF($H63=0,"",IF(INDEX('DM01-AV-CH'!I$6:I$834,$H63)="","",INDEX('DM01-AV-CH'!I$6:I$834,$H63)))} -> Versicherungsart
A64: 59 | B64: =IF($A64="","",IF(_xlfn.XLOOKUP($A64,Korrelation!$D$4:$D$1197,Korrelation!E$4:E$1197,"-",0)="-",0,MATCH(_xlfn.XLOOKUP($A64,Korrelation!$D$4:$D$1197,Korrelation!E$4:E$1197,"",0),DMAV_Modell!$G$6:$G$677,0))) -> 48 | C64: =IF($A64="","",IF(_xlfn.XLOOKUP($A64,Korrelation!$D$4:$D$1197,Korrelation!F$4:F$1197,"-",0)="-",0,MATCH(_xlfn.XLOOKUP($A64,Korrelation!$D$4:$D$1197,Korrelation!F$4:F$1197,"",0),DMAV_Modell!$G$6:$G$677,0))) -> 0 | D64: =IF($A64="","",IF(_xlfn.XLOOKUP($A64,Korrelation!$D$4:$D$1197,Korrelation!G$4:G$1197,"-",0)="-",0,MATCH(_xlfn.XLOOKUP($A64,Korrelation!$D$4:$D$1197,Korrelation!G$4:G$1197,"",0),DMAV_Modell!$G$6:$G$677,0))) -> 0 | E64: =IF($A64="","",IF(_xlfn.XLOOKUP($A64,Korrelation!$D$4:$D$1197,Korrelation!H$4:H$1197,"-",0)="-",0,MATCH(_xlfn.XLOOKUP($A64,Korrelation!$D$4:$D$1197,Korrelation!H$4:H$1197,"",0),DMAV_Dienste!$F$6:$F$140,0))) -> 0 | F64: =IF($A64="","",IF(_xlfn.XLOOKUP($A64,Korrelation!$D$4:$D$1197,Korrelation!I$4:I$1197,"-",0)="-",0,MATCH(_xlfn.XLOOKUP($A64,Korrelation!$D$4:$D$1197,Korrelation!I$4:I$1197,"",0),DMAV_Dienste!$F$6:$F$140,0))) -> 0 | G64: =IF($A64="","",IF(_xlfn.XLOOKUP($A64,Korrelation!$D$4:$D$1197,Korrelation!J$4:J$1197,"-",0)="-",0,MATCH(_xlfn.XLOOKUP($A64,Korrelation!$D$4:$D$1197,Korrelation!J$4:J$1197,"",0),DMAV_Dienste!$F$6:$F$140,0))) -> 0 | H64: =IF($A64="","",IF(_xlfn.XLOOKUP($A64,Korrelation!$D$4:$D$1197,Korrelation!K$4:K$1197,"-",0)="-",0,MATCH(_xlfn.XLOOKUP($A64,Korrelation!$D$4:$D$1197,Korrelation!K$4:K$1197,"",0),'DM01-AV-CH'!$A$6:$A$834,0))) -> 24 | J64: {=IF(B64=0,IF(E64=0,"",HYPERLINK("#"&RIGHT(CELL("adresse",OFFSET(DMAV_Dienste!$M$6,E64-1,0)),LEN(CELL("adresse",OFFSET(DMAV_Dienste!$M$6,E64-1,0)))-FIND("]",CELL("adresse",OFFSET(DMAV_Dienste!$M$6,E64-1,0)))),"Dienst")),HYPERLINK("#"&RIGHT(CELL("adresse",OFFSET(DMAV_Modell!$N$6,B64-1,0)),LEN(CELL("adresse",OFFSET(DMAV_Modell!$N$6,B64-1,0)))-FIND("]",CELL("adresse",OFFSET(DMAV_Modell!$N$6,B64-1,0)))),"Modell"))} -> Modell | K64: {=IF($B64=0,IF($E64=0,"",IF(INDEX(DMAV_Dienste!P$6:P$140,$E64)="","",INDEX(DMAV_Dienste!P$6:P$140,$E64))),IF(INDEX(DMAV_Modell!Q$6:Q$838,$B64)="","",INDEX(DMAV_Modell!Q$6:Q$838,$B64)))} -> DOMAIN | L64: {=IF($B64=0,IF($E64=0,"",IF(INDEX(DMAV_Dienste!O$6:O$140,$E64)="","",INDEX(DMAV_Dienste!O$6:O$140,$E64))),IF(INDEX(DMAV_Modell!P$6:P$838,$B64)="","",INDEX(DMAV_Modell!P$6:P$838,$B64)))} | M64: {=IF($B64=0,IF($E64=0,"",IF(INDEX(DMAV_Dienste!Q$6:Q$140,$E64)="","",INDEX(DMAV_Dienste!Q$6:Q$140,$E64))),IF(INDEX(DMAV_Modell!R$6:R$838,$B64)="","",INDEX(DMAV_Modell!R$6:R$838,$B64)))} -> Versicherungsart | N64: {=IF($B64=0,IF($E64=0,"",IF(INDEX(DMAV_Dienste!T$6:T$140,$E64)="","",INDEX(DMAV_Dienste!T$6:T$140,$E64))),IF(INDEX(DMAV_Modell!U$6:U$838,$B64)="","",INDEX(DMAV_Modell!U$6:U$838,$B64)))} | O64: {=IF(C64=0,IF(F64=0,"",HYPERLINK("#"&RIGHT(CELL("adresse",OFFSET(DMAV_Dienste!$M$6,F64-1,0)),LEN(CELL("adresse",OFFSET(DMAV_Dienste!$M$6,F64-1,0)))-FIND("]",CELL("adresse",OFFSET(DMAV_Dienste!$M$6,F64-1,0)))),"Structure")),HYPERLINK("#"&RIGHT(CELL("adresse",OFFSET(DMAV_Modell!$N$6,C64-1,0)),LEN(CELL("adresse",OFFSET(DMAV_Modell!$N$6,C64-1,0)))-FIND("]",CELL("adresse",OFFSET(DMAV_Modell!$N$6,C64-1,0)))),"Structure"))} | P64: {=IF(D64=0,IF(G64=0,"",HYPERLINK("#"&RIGHT(CELL("adresse",OFFSET(DMAV_Dienste!$M$6,G64-1,0)),LEN(CELL("adresse",OFFSET(DMAV_Dienste!$M$6,G64-1,0)))-FIND("]",CELL("adresse",OFFSET(DMAV_Dienste!$M$6,G64-1,0)))),"Substructure")),HYPERLINK("#"&RIGHT(CELL("adresse",OFFSET(DMAV_Modell!$N$6,D64-1,0)),LEN(CELL("adresse",OFFSET(DMAV_Modell!$N$6,D64-1,0)))-FIND("]",CELL("adresse",OFFSET(DMAV_Modell!$N$6,D64-1,0)))),"Substructure"))} | AF64: {=IF(H64=0,"",HYPERLINK("#"&RIGHT(CELL("adresse",OFFSET('DM01-AV-CH'!$G$6,H64-1,0)),LEN(CELL("adresse",OFFSET('DM01-AV-CH'!$G$6,H64-1,0)))-FIND("]",CELL("adresse",OFFSET('DM01-AV-CH'!$G$6,H64-1,0)))),"Modell"))} -> Modell | AG64: {=IF($H64=0,"",IF(INDEX('DM01-AV-CH'!G$6:G$834,$H64)="","",INDEX('DM01-AV-CH'!G$6:G$834,$H64)))} -> Allgemein | AH64: {=IF($H64=0,"",IF(INDEX('DM01-AV-CH'!H$6:H$834,$H64)="","",INDEX('DM01-AV-CH'!H$6:H$834,$H64)))} | AI64: {=IF($H64=0,"",IF(INDEX('DM01-AV-CH'!I$6:I$834,$H64)="","",INDEX('DM01-AV-CH'!I$6:I$834,$H64)))} -> Versicherungsart
... A80: 75 | B80: =IF($A80="","",IF(_xlfn.XLOOKUP($A80,Korrelation!$D$4:$D$1197,Korrelation!E$4:E$1197,"-",0)="-",0,MATCH(_xlfn.XLOOKUP($A80,Korrelation!$D$4:$D$1197,Korrelation!E$4:E$1197,"",0),DMAV_Modell!$G$6:$G$677,0))) -> 0 | C80: =IF($A80="","",IF(_xlfn.XLOOKUP($A80,Korrelation!$D$4:$D$1197,Korrelation!F$4:F$1197,"-",0)="-",0,MATCH(_xlfn.XLOOKUP($A80,Korrelation!$D$4:$D$1197,Korrelation!F$4:F$1197,"",0),DMAV_Modell!$G$6:$G$677,0))) -> 0 | D80: =IF($A80="","",IF(_xlfn.XLOOKUP($A80,Korrelation!$D$4:$D$1197,Korrelation!G$4:G$1197,"-",0)="-",0,MATCH(_xlfn.XLOOKUP($A80,Korrelation!$D$4:$D$1197,Korrelation!G$4:G$1197,"",0),DMAV_Modell!$G$6:$G$677,0))) -> 0 | E80: =IF($A80="","",IF(_xlfn.XLOOKUP($A80,Korrelation!$D$4:$D$1197,Korrelation!H$4:H$1197,"-",0)="-",0,MATCH(_xlfn.XLOOKUP($A80,Korrelation!$D$4:$D$1197,Korrelation!H$4:H$1197,"",0),DMAV_Dienste!$F$6:$F$140,0))) -> 3 | F80: =IF($A80="","",IF(_xlfn.XLOOKUP($A80,Korrelation!$D$4:$D$1197,Korrelation!I$4:I$1197,"-",0)="-",0,MATCH(_xlfn.XLOOKUP($A80,Korrelation!$D$4:$D$1197,Korrelation!I$4:I$1197,"",0),DMAV_Dienste!$F$6:$F$140,0))) -> 0 | G80: =IF($A80="","",IF(_xlfn.XLOOKUP($A80,Korrelation!$D$4:$D$1197,Korrelation!J$4:J$1197,"-",0)="-",0,MATCH(_xlfn.XLOOKUP($A80,Korrelation!$D$4:$D$1197,Korrelation!J$4:J$1197,"",0),DMAV_Dienste!$F$6:$F$140,0))) -> 0 | H80: =IF($A80="","",IF(_xlfn.XLOOKUP($A80,Korrelation!$D$4:$D$1197,Korrelation!K$4:K$1197,"-",0)="-",0,MATCH(_xlfn.XLOOKUP($A80,Korrelation!$D$4:$D$1197,Korrelation!K$4:K$1197,"",0),'DM01-AV-CH'!$A$6:$A$834,0))) -> 0 | J80: {=IF(B80=0,IF(E80=0,"",HYPERLINK("#"&RIGHT(CELL("adresse",OFFSET(DMAV_Dienste!$M$6,E80-1,0)),LEN(CELL("adresse",OFFSET(DMAV_Dienste!$M$6,E80-1,0)))-FIND("]",CELL("adresse",OFFSET(DMAV_Dienste!$M$6,E80-1,0)))),"Dienst")),HYPERLINK("#"&RIGHT(CELL("adresse",OFFSET(DMAV_Modell!$N$6,B80-1,0)),LEN(CELL("adresse",OFFSET(DMAV_Modell!$N$6,B80-1,0)))-FIND("]",CELL("adresse",OFFSET(DMAV_Modell!$N$6,B80-1,0)))),"Modell"))} -> Dienst | K80: {=IF($B80=0,IF($E80=0,"",IF(INDEX(DMAV_Dienste!P$6:P$140,$E80)="","",INDEX(DMAV_Dienste!P$6:P$140,$E80))),IF(INDEX(DMAV_Modell!Q$6:Q$838,$B80)="","",INDEX(DMAV_Modell!Q$6:Q$838,$B80)))} -> IMPORTS | L80: {=IF($B80=0,IF($E80=0,"",IF(INDEX(DMAV_Dienste!O$6:O$140,$E80)="","",INDEX(DMAV_Dienste!O$6:O$140,$E80))),IF(INDEX(DMAV_Modell!P$6:P$838,$B80)="","",INDEX(DMAV_Modell!P$6:P$838,$B80)))} | M80: {=IF($B80=0,IF($E80=0,"",IF(INDEX(DMAV_Dienste!Q$6:Q$140,$E80)="","",INDEX(DMAV_Dienste!Q$6:Q$140,$E80))),IF(INDEX(DMAV_Modell!R$6:R$838,$B80)="","",INDEX(DMAV_Modell!R$6:R$838,$B80)))} -> DMAVTYM_Qualitaet_V1_0 | N80: {=IF($B80=0,IF($E80=0,"",IF(INDEX(DMAV_Dienste!T$6:T$140,$E80)="","",INDEX(DMAV_Dienste!T$6:T$140,$E80))),IF(INDEX(DMAV_Modell!U$6:U$838,$B80)="","",INDEX(DMAV_Modell!U$6:U$838,$B80)))} | O80: {=IF(C80=0,IF(F80=0,"",HYPERLINK("#"&RIGHT(CELL("adresse",OFFSET(DMAV_Dienste!$M$6,F80-1,0)),LEN(CELL("adresse",OFFSET(DMAV_Dienste!$M$6,F80-1,0)))-FIND("]",CELL("adresse",OFFSET(DMAV_Dienste!$M$6,F80-1,0)))),"Structure")),HYPERLINK("#"&RIGHT(CELL("adresse",OFFSET(DMAV_Modell!$N$6,C80-1,0)),LEN(CELL("adresse",OFFSET(DMAV_Modell!$N$6,C80-1,0)))-FIND("]",CELL("adresse",OFFSET(DMAV_Modell!$N$6,C80-1,0)))),"Structure"))} | P80: {=IF(D80=0,IF(G80=0,"",HYPERLINK("#"&RIGHT(CELL("adresse",OFFSET(DMAV_Dienste!$M$6,G80-1,0)),LEN(CELL("adresse",OFFSET(DMAV_Dienste!$M$6,G80-1,0)))-FIND("]",CELL("adresse",OFFSET(DMAV_Dienste!$M$6,G80-1,0)))),"Substructure")),HYPERLINK("#"&RIGHT(CELL("adresse",OFFSET(DMAV_Modell!$N$6,D80-1,0)),LEN(CELL("adresse",OFFSET(DMAV_Modell!$N$6,D80-1,0)))-FIND("]",CELL("adresse",OFFSET(DMAV_Modell!$N$6,D80-1,0)))),"Substructure"))} | AF80: {=IF(H80=0,"",HYPERLINK("#"&RIGHT(CELL("adresse",OFFSET('DM01-AV-CH'!$G$6,H80-1,0)),LEN(CELL("adresse",OFFSET('DM01-AV-CH'!$G$6,H80-1,0)))-FIND("]",CELL("adresse",OFFSET('DM01-AV-CH'!$G$6,H80-1,0)))),"Modell"))} | AG80: {=IF($H80=0,"",IF(INDEX('DM01-AV-CH'!G$6:G$834,$H80)="","",INDEX('DM01-AV-CH'!G$6:G$834,$H80)))} | AH80: {=IF($H80=0,"",IF(INDEX('DM01-AV-CH'!H$6:H$834,$H80)="","",INDEX('DM01-AV-CH'!H$6:H$834,$H80)))} | AI80: {=IF($H80=0,"",IF(INDEX('DM01-AV-CH'!I$6:I$834,$H80)="","",INDEX('DM01-AV-CH'!I$6:I$834,$H80)))}
A81: 76 | B81: =IF($A81="","",IF(_xlfn.XLOOKUP($A81,Korrelation!$D$4:$D$1197,Korrelation!E$4:E$1197,"-",0)="-",0,MATCH(_xlfn.XLOOKUP($A81,Korrelation!$D$4:$D$1197,Korrelation!E$4:E$1197,"",0),DMAV_Modell!$G$6:$G$677,0))) -> 0 | C81: =IF($A81="","",IF(_xlfn.XLOOKUP($A81,Korrelation!$D$4:$D$1197,Korrelation!F$4:F$1197,"-",0)="-",0,MATCH(_xlfn.XLOOKUP($A81,Korrelation!$D$4:$D$1197,Korrelation!F$4:F$1197,"",0),DMAV_Modell!$G$6:$G$677,0))) -> 0 | D81: =IF($A81="","",IF(_xlfn.XLOOKUP($A81,Korrelation!$D$4:$D$1197,Korrelation!G$4:G$1197,"-",0)="-",0,MATCH(_xlfn.XLOOKUP($A81,Korrelation!$D$4:$D$1197,Korrelation!G$4:G$1197,"",0),DMAV_Modell!$G$6:$G$677,0))) -> 0 | E81: =IF($A81="","",IF(_xlfn.XLOOKUP($A81,Korrelation!$D$4:$D$1197,Korrelation!H$4:H$1197,"-",0)="-",0,MATCH(_xlfn.XLOOKUP($A81,Korrelation!$D$4:$D$1197,Korrelation!H$4:H$1197,"",0),DMAV_Dienste!$F$6:$F$140,0))) -> 0 | F81: =IF($A81="","",IF(_xlfn.XLOOKUP($A81,Korrelation!$D$4:$D$1197,Korrelation!I$4:I$1197,"-",0)="-",0,MATCH(_xlfn.XLOOKUP($A81,Korrelation!$D$4:$D$1197,Korrelation!I$4:I$1197,"",0),DMAV_Dienste!$F$6:$F$140,0))) -> 0 | G81: =IF($A81="","",IF(_xlfn.XLOOKUP($A81,Korrelation!$D$4:$D$1197,Korrelation!J$4:J$1197,"-",0)="-",0,MATCH(_xlfn.XLOOKUP($A81,Korrelation!$D$4:$D$1197,Korrelation!J$4:J$1197,"",0),DMAV_Dienste!$F$6:$F$140,0))) -> 0 | H81: =IF($A81="","",IF(_xlfn.XLOOKUP($A81,Korrelation!$D$4:$D$1197,Korrelation!K$4:K$1197,"-",0)="-",0,MATCH(_xlfn.XLOOKUP($A81,Korrelation!$D$4:$D$1197,Korrelation!K$4:K$1197,"",0),'DM01-AV-CH'!$A$6:$A$834,0))) -> 37 | J81: {=IF(B81=0,IF(E81=0,"",HYPERLINK("#"&RIGHT(CELL("adresse",OFFSET(DMAV_Dienste!$M$6,E81-1,0)),LEN(CELL("adresse",OFFSET(DMAV_Dienste!$M$6,E81-1,0)))-FIND("]",CELL("adresse",OFFSET(DMAV_Dienste!$M$6,E81-1,0)))),"Dienst")),HYPERLINK("#"&RIGHT(CELL("adresse",OFFSET(DMAV_Modell!$N$6,B81-1,0)),LEN(CELL("adresse",OFFSET(DMAV_Modell!$N$6,B81-1,0)))-FIND("]",CELL("adresse",OFFSET(DMAV_Modell!$N$6,B81-1,0)))),"Modell"))} | K81: {=IF($B81=0,IF($E81=0,"",IF(INDEX(DMAV_Dienste!P$6:P$140,$E81)="","",INDEX(DMAV_Dienste!P$6:P$140,$E81))),IF(INDEX(DMAV_Modell!Q$6:Q$838,$B81)="","",INDEX(DMAV_Modell!Q$6:Q$838,$B81)))} | L81: {=IF($B81=0,IF($E81=0,"",IF(INDEX(DMAV_Dienste!O$6:O$140,$E81)="","",INDEX(DMAV_Dienste!O$6:O$140,$E81))),IF(INDEX(DMAV_Modell!P$6:P$838,$B81)="","",INDEX(DMAV_Modell!P$6:P$838,$B81)))} | M81: {=IF($B81=0,IF($E81=0,"",IF(INDEX(DMAV_Dienste!Q$6:Q$140,$E81)="","",INDEX(DMAV_Dienste!Q$6:Q$140,$E81))),IF(INDEX(DMAV_Modell!R$6:R$838,$B81)="","",INDEX(DMAV_Modell!R$6:R$838,$B81)))} | N81: {=IF($B81=0,IF($E81=0,"",IF(INDEX(DMAV_Dienste!T$6:T$140,$E81)="","",INDEX(DMAV_Dienste!T$6:T$140,$E81))),IF(INDEX(DMAV_Modell!U$6:U$838,$B81)="","",INDEX(DMAV_Modell!U$6:U$838,$B81)))} | O81: {=IF(C81=0,IF(F81=0,"",HYPERLINK("#"&RIGHT(CELL("adresse",OFFSET(DMAV_Dienste!$M$6,F81-1,0)),LEN(CELL("adresse",OFFSET(DMAV_Dienste!$M$6,F81-1,0)))-FIND("]",CELL("adresse",OFFSET(DMAV_Dienste!$M$6,F81-1,0)))),"Structure")),HYPERLINK("#"&RIGHT(CELL("adresse",OFFSET(DMAV_Modell!$N$6,C81-1,0)),LEN(CELL("adresse",OFFSET(DMAV_Modell!$N$6,C81-1,0)))-FIND("]",CELL("adresse",OFFSET(DMAV_Modell!$N$6,C81-1,0)))),"Structure"))} | P81: {=IF(D81=0,IF(G81=0,"",HYPERLINK("#"&RIGHT(CELL("adresse",OFFSET(DMAV_Dienste!$M$6,G81-1,0)),LEN(CELL("adresse",OFFSET(DMAV_Dienste!$M$6,G81-1,0)))-FIND("]",CELL("adresse",OFFSET(DMAV_Dienste!$M$6,G81-1,0)))),"Substructure")),HYPERLINK("#"&RIGHT(CELL("adresse",OFFSET(DMAV_Modell!$N$6,D81-1,0)),LEN(CELL("adresse",OFFSET(DMAV_Modell!$N$6,D81-1,0)))-FIND("]",CELL("adresse",OFFSET(DMAV_Modell!$N$6,D81-1,0)))),"Substructure"))} | AB81: FixpunkteKategorie1.LFP1Nachfuehrung.NBIdent = [geltender NBIdent], FixpunkteKategorie1.LFP1Nachfuehrung.Identifikator = Zeitstempel{Format:YYYYMMDDHHMMSS}, FixpunkteKategorie1.LFP1Nachfuehrung.Beschreibung = "Bezug_durch_Dienst", FixpunkteKategorie1.LFP1Nachfuehrung.GueltigerEintrag = Datum | AF81: {=IF(H81=0,"",HYPERLINK("#"&RIGHT(CELL("adresse",OFFSET('DM01-AV-CH'!$G$6,H81-1,0)),LEN(CELL("adresse",OFFSET('DM01-AV-CH'!$G$6,H81-1,0)))-FIND("]",CELL("adresse",OFFSET('DM01-AV-CH'!$G$6,H81-1,0)))),"Modell"))} -> Modell | AG81: {=IF($H81=0,"",IF(INDEX('DM01-AV-CH'!G$6:G$834,$H81)="","",INDEX('DM01-AV-CH'!G$6:G$834,$H81)))} -> FixpunkteKategorie1 | AH81: {=IF($H81=0,"",IF(INDEX('DM01-AV-CH'!H$6:H$834,$H81)="","",INDEX('DM01-AV-CH'!H$6:H$834,$H81)))} -> LFP1Nachfuehrung | AI81: {=IF($H81=0,"",IF(INDEX('DM01-AV-CH'!I$6:I$834,$H81)="","",INDEX('DM01-AV-CH'!I$6:I$834,$H81)))} -> NBIdent
A82: 77 | B82: =IF($A82="","",IF(_xlfn.XLOOKUP($A82,Korrelation!$D$4:$D$1197,Korrelation!E$4:E$1197,"-",0)="-",0,MATCH(_xlfn.XLOOKUP($A82,Korrelation!$D$4:$D$1197,Korrelation!E$4:E$1197,"",0),DMAV_Modell!$G$6:$G$677,0))) -> 0 | C82: =IF($A82="","",IF(_xlfn.XLOOKUP($A82,Korrelation!$D$4:$D$1197,Korrelation!F$4:F$1197,"-",0)="-",0,MATCH(_xlfn.XLOOKUP($A82,Korrelation!$D$4:$D$1197,Korrelation!F$4:F$1197,"",0),DMAV_Modell!$G$6:$G$677,0))) -> 0 | D82: =IF($A82="","",IF(_xlfn.XLOOKUP($A82,Korrelation!$D$4:$D$1197,Korrelation!G$4:G$1197,"-",0)="-",0,MATCH(_xlfn.XLOOKUP($A82,Korrelation!$D$4:$D$1197,Korrelation!G$4:G$1197,"",0),DMAV_Modell!$G$6:$G$677,0))) -> 0 | E82: =IF($A82="","",IF(_xlfn.XLOOKUP($A82,Korrelation!$D$4:$D$1197,Korrelation!H$4:H$1197,"-",0)="-",0,MATCH(_xlfn.XLOOKUP($A82,Korrelation!$D$4:$D$1197,Korrelation!H$4:H$1197,"",0),DMAV_Dienste!$F$6:$F$140,0))) -> 0 | F82: =IF($A82="","",IF(_xlfn.XLOOKUP($A82,Korrelation!$D$4:$D$1197,Korrelation!I$4:I$1197,"-",0)="-",0,MATCH(_xlfn.XLOOKUP($A82,Korrelation!$D$4:$D$1197,Korrelation!I$4:I$1197,"",0),DMAV_Dienste!$F$6:$F$140,0))) -> 0 | G82: =IF($A82="","",IF(_xlfn.XLOOKUP($A82,Korrelation!$D$4:$D$1197,Korrelation!J$4:J$1197,"-",0)="-",0,MATCH(_xlfn.XLOOKUP($A82,Korrelation!$D$4:$D$1197,Korrelation!J$4:J$1197,"",0),DMAV_Dienste!$F$6:$F$140,0))) -> 0 | H82: =IF($A82="","",IF(_xlfn.XLOOKUP($A82,Korrelation!$D$4:$D$1197,Korrelation!K$4:K$1197,"-",0)="-",0,MATCH(_xlfn.XLOOKUP($A82,Korrelation!$D$4:$D$1197,Korrelation!K$4:K$1197,"",0),'DM01-AV-CH'!$A$6:$A$834,0))) -> 38 | J82: {=IF(B82=0,IF(E82=0,"",HYPERLINK("#"&RIGHT(CELL("adresse",OFFSET(DMAV_Dienste!$M$6,E82-1,0)),LEN(CELL("adresse",OFFSET(DMAV_Dienste!$M$6,E82-1,0)))-FIND("]",CELL("adresse",OFFSET(DMAV_Dienste!$M$6,E82-1,0)))),"Dienst")),HYPERLINK("#"&RIGHT(CELL("adresse",OFFSET(DMAV_Modell!$N$6,B82-1,0)),LEN(CELL("adresse",OFFSET(DMAV_Modell!$N$6,B82-1,0)))-FIND("]",CELL("adresse",OFFSET(DMAV_Modell!$N$6,B82-1,0)))),"Modell"))} | K82: {=IF($B82=0,IF($E82=0,"",IF(INDEX(DMAV_Dienste!P$6:P$140,$E82)="","",INDEX(DMAV_Dienste!P$6:P$140,$E82))),IF(INDEX(DMAV_Modell!Q$6:Q$838,$B82)="","",INDEX(DMAV_Modell!Q$6:Q$838,$B82)))} | L82: {=IF($B82=0,IF($E82=0,"",IF(INDEX(DMAV_Dienste!O$6:O$140,$E82)="","",INDEX(DMAV_Dienste!O$6:O$140,$E82))),IF(INDEX(DMAV_Modell!P$6:P$838,$B82)="","",INDEX(DMAV_Modell!P$6:P$838,$B82)))} | M82: {=IF($B82=0,IF($E82=0,"",IF(INDEX(DMAV_Dienste!Q$6:Q$140,$E82)="","",INDEX(DMAV_Dienste!Q$6:Q$140,$E82))),IF(INDEX(DMAV_Modell!R$6:R$838,$B82)="","",INDEX(DMAV_Modell!R$6:R$838,$B82)))} | N82: {=IF($B82=0,IF($E82=0,"",IF(INDEX(DMAV_Dienste!T$6:T$140,$E82)="","",INDEX(DMAV_Dienste!T$6:T$140,$E82))),IF(INDEX(DMAV_Modell!U$6:U$838,$B82)="","",INDEX(DMAV_Modell!U$6:U$838,$B82)))} | O82: {=IF(C82=0,IF(F82=0,"",HYPERLINK("#"&RIGHT(CELL("adresse",OFFSET(DMAV_Dienste!$M$6,F82-1,0)),LEN(CELL("adresse",OFFSET(DMAV_Dienste!$M$6,F82-1,0)))-FIND("]",CELL("adresse",OFFSET(DMAV_Dienste!$M$6,F82-1,0)))),"Structure")),HYPERLINK("#"&RIGHT(CELL("adresse",OFFSET(DMAV_Modell!$N$6,C82-1,0)),LEN(CELL("adresse",OFFSET(DMAV_Modell!$N$6,C82-1,0)))-FIND("]",CELL("adresse",OFFSET(DMAV_Modell!$N$6,C82-1,0)))),"Structure"))} | P82: {=IF(D82=0,IF(G82=0,"",HYPERLINK("#"&RIGHT(CELL("adresse",OFFSET(DMAV_Dienste!$M$6,G82-1,0)),LEN(CELL("adresse",OFFSET(DMAV_Dienste!$M$6,G82-1,0)))-FIND("]",CELL("adresse",OFFSET(DMAV_Dienste!$M$6,G82-1,0)))),"Substructure")),HYPERLINK("#"&RIGHT(CELL("adresse",OFFSET(DMAV_Modell!$N$6,D82-1,0)),LEN(CELL("adresse",OFFSET(DMAV_Modell!$N$6,D82-1,0)))-FIND("]",CELL("adresse",OFFSET(DMAV_Modell!$N$6,D82-1,0)))),"Substructure"))} | AB82: FixpunkteKategorie1.LFP1Nachfuehrung.NBIdent = [geltender NBIdent], FixpunkteKategorie1.LFP1Nachfuehrung.Identifikator = Zeitstempel{Format:YYYYMMDDHHMMSS}, FixpunkteKategorie1.LFP1Nachfuehrung.Beschreibung = "Bezug_durch_Dienst", FixpunkteKategorie1.LFP1Nachfuehrung.GueltigerEintrag = Datum | AF82: {=IF(H82=0,"",HYPERLINK("#"&RIGHT(CELL("adresse",OFFSET('DM01-AV-CH'!$G$6,H82-1,0)),LEN(CELL("adresse",OFFSET('DM01-AV-CH'!$G$6,H82-1,0)))-FIND("]",CELL("adresse",OFFSET('DM01-AV-CH'!$G$6,H82-1,0)))),"Modell"))} -> Modell | AG82: {=IF($H82=0,"",IF(INDEX('DM01-AV-CH'!G$6:G$834,$H82)="","",INDEX('DM01-AV-CH'!G$6:G$834,$H82)))} -> FixpunkteKategorie1 | AH82: {=IF($H82=0,"",IF(INDEX('DM01-AV-CH'!H$6:H$834,$H82)="","",INDEX('DM01-AV-CH'!H$6:H$834,$H82)))} -> LFP1Nachfuehrung | AI82: {=IF($H82=0,"",IF(INDEX('DM01-AV-CH'!I$6:I$834,$H82)="","",INDEX('DM01-AV-CH'!I$6:I$834,$H82)))} -> Identifikator
A83: 78 | B83: =IF($A83="","",IF(_xlfn.XLOOKUP($A83,Korrelation!$D$4:$D$1197,Korrelation!E$4:E$1197,"-",0)="-",0,MATCH(_xlfn.XLOOKUP($A83,Korrelation!$D$4:$D$1197,Korrelation!E$4:E$1197,"",0),DMAV_Modell!$G$6:$G$677,0))) -> 0 | C83: =IF($A83="","",IF(_xlfn.XLOOKUP($A83,Korrelation!$D$4:$D$1197,Korrelation!F$4:F$1197,"-",0)="-",0,MATCH(_xlfn.XLOOKUP($A83,Korrelation!$D$4:$D$1197,Korrelation!F$4:F$1197,"",0),DMAV_Modell!$G$6:$G$677,0))) -> 0 | D83: =IF($A83="","",IF(_xlfn.XLOOKUP($A83,Korrelation!$D$4:$D$1197,Korrelation!G$4:G$1197,"-",0)="-",0,MATCH(_xlfn.XLOOKUP($A83,Korrelation!$D$4:$D$1197,Korrelation!G$4:G$1197,"",0),DMAV_Modell!$G$6:$G$677,0))) -> 0 | E83: =IF($A83="","",IF(_xlfn.XLOOKUP($A83,Korrelation!$D$4:$D$1197,Korrelation!H$4:H$1197,"-",0)="-",0,MATCH(_xlfn.XLOOKUP($A83,Korrelation!$D$4:$D$1197,Korrelation!H$4:H$1197,"",0),DMAV_Dienste!$F$6:$F$140,0))) -> 0 | F83: =IF($A83="","",IF(_xlfn.XLOOKUP($A83,Korrelation!$D$4:$D$1197,Korrelation!I$4:I$1197,"-",0)="-",0,MATCH(_xlfn.XLOOKUP($A83,Korrelation!$D$4:$D$1197,Korrelation!I$4:I$1197,"",0),DMAV_Dienste!$F$6:$F$140,0))) -> 0 | G83: =IF($A83="","",IF(_xlfn.XLOOKUP($A83,Korrelation!$D$4:$D$1197,Korrelation!J$4:J$1197,"-",0)="-",0,MATCH(_xlfn.XLOOKUP($A83,Korrelation!$D$4:$D$1197,Korrelation!J$4:J$1197,"",0),DMAV_Dienste!$F$6:$F$140,0))) -> 0 | H83: =IF($A83="","",IF(_xlfn.XLOOKUP($A83,Korrelation!$D$4:$D$1197,Korrelation!K$4:K$1197,"-",0)="-",0,MATCH(_xlfn.XLOOKUP($A83,Korrelation!$D$4:$D$1197,Korrelation!K$4:K$1197,"",0),'DM01-AV-CH'!$A$6:$A$834,0))) -> 39 | J83: {=IF(B83=0,IF(E83=0,"",HYPERLINK("#"&RIGHT(CELL("adresse",OFFSET(DMAV_Dienste!$M$6,E83-1,0)),LEN(CELL("adresse",OFFSET(DMAV_Dienste!$M$6,E83-1,0)))-FIND("]",CELL("adresse",OFFSET(DMAV_Dienste!$M$6,E83-1,0)))),"Dienst")),HYPERLINK("#"&RIGHT(CELL("adresse",OFFSET(DMAV_Modell!$N$6,B83-1,0)),LEN(CELL("adresse",OFFSET(DMAV_Modell!$N$6,B83-1,0)))-FIND("]",CELL("adresse",OFFSET(DMAV_Modell!$N$6,B83-1,0)))),"Modell"))} | K83: {=IF($B83=0,IF($E83=0,"",IF(INDEX(DMAV_Dienste!P$6:P$140,$E83)="","",INDEX(DMAV_Dienste!P$6:P$140,$E83))),IF(INDEX(DMAV_Modell!Q$6:Q$838,$B83)="","",INDEX(DMAV_Modell!Q$6:Q$838,$B83)))} | L83: {=IF($B83=0,IF($E83=0,"",IF(INDEX(DMAV_Dienste!O$6:O$140,$E83)="","",INDEX(DMAV_Dienste!O$6:O$140,$E83))),IF(INDEX(DMAV_Modell!P$6:P$838,$B83)="","",INDEX(DMAV_Modell!P$6:P$838,$B83)))} | M83: {=IF($B83=0,IF($E83=0,"",IF(INDEX(DMAV_Dienste!Q$6:Q$140,$E83)="","",INDEX(DMAV_Dienste!Q$6:Q$140,$E83))),IF(INDEX(DMAV_Modell!R$6:R$838,$B83)="","",INDEX(DMAV_Modell!R$6:R$838,$B83)))} | N83: {=IF($B83=0,IF($E83=0,"",IF(INDEX(DMAV_Dienste!T$6:T$140,$E83)="","",INDEX(DMAV_Dienste!T$6:T$140,$E83))),IF(INDEX(DMAV_Modell!U$6:U$838,$B83)="","",INDEX(DMAV_Modell!U$6:U$838,$B83)))} | O83: {=IF(C83=0,IF(F83=0,"",HYPERLINK("#"&RIGHT(CELL("adresse",OFFSET(DMAV_Dienste!$M$6,F83-1,0)),LEN(CELL("adresse",OFFSET(DMAV_Dienste!$M$6,F83-1,0)))-FIND("]",CELL("adresse",OFFSET(DMAV_Dienste!$M$6,F83-1,0)))),"Structure")),HYPERLINK("#"&RIGHT(CELL("adresse",OFFSET(DMAV_Modell!$N$6,C83-1,0)),LEN(CELL("adresse",OFFSET(DMAV_Modell!$N$6,C83-1,0)))-FIND("]",CELL("adresse",OFFSET(DMAV_Modell!$N$6,C83-1,0)))),"Structure"))} | P83: {=IF(D83=0,IF(G83=0,"",HYPERLINK("#"&RIGHT(CELL("adresse",OFFSET(DMAV_Dienste!$M$6,G83-1,0)),LEN(CELL("adresse",OFFSET(DMAV_Dienste!$M$6,G83-1,0)))-FIND("]",CELL("adresse",OFFSET(DMAV_Dienste!$M$6,G83-1,0)))),"Substructure")),HYPERLINK("#"&RIGHT(CELL("adresse",OFFSET(DMAV_Modell!$N$6,D83-1,0)),LEN(CELL("adresse",OFFSET(DMAV_Modell!$N$6,D83-1,0)))-FIND("]",CELL("adresse",OFFSET(DMAV_Modell!$N$6,D83-1,0)))),"Substructure"))} | AB83: FixpunkteKategorie1.LFP1Nachfuehrung.NBIdent = [geltender NBIdent], FixpunkteKategorie1.LFP1Nachfuehrung.Identifikator = Zeitstempel{Format:YYYYMMDDHHMMSS}, FixpunkteKategorie1.LFP1Nachfuehrung.Beschreibung = "Bezug_durch_Dienst", FixpunkteKategorie1.LFP1Nachfuehrung.GueltigerEintrag = Datum | AF83: {=IF(H83=0,"",HYPERLINK("#"&RIGHT(CELL("adresse",OFFSET('DM01-AV-CH'!$G$6,H83-1,0)),LEN(CELL("adresse",OFFSET('DM01-AV-CH'!$G$6,H83-1,0)))-FIND("]",CELL("adresse",OFFSET('DM01-AV-CH'!$G$6,H83-1,0)))),"Modell"))} -> Modell | AG83: {=IF($H83=0,"",IF(INDEX('DM01-AV-CH'!G$6:G$834,$H83)="","",INDEX('DM01-AV-CH'!G$6:G$834,$H83)))} -> FixpunkteKategorie1 | AH83: {=IF($H83=0,"",IF(INDEX('DM01-AV-CH'!H$6:H$834,$H83)="","",INDEX('DM01-AV-CH'!H$6:H$834,$H83)))} -> LFP1Nachfuehrung | AI83: {=IF($H83=0,"",IF(INDEX('DM01-AV-CH'!I$6:I$834,$H83)="","",INDEX('DM01-AV-CH'!I$6:I$834,$H83)))} -> Beschreibung
A84: 79 | B84: =IF($A84="","",IF(_xlfn.XLOOKUP($A84,Korrelation!$D$4:$D$1197,Korrelation!E$4:E$1197,"-",0)="-",0,MATCH(_xlfn.XLOOKUP($A84,Korrelation!$D$4:$D$1197,Korrelation!E$4:E$1197,"",0),DMAV_Modell!$G$6:$G$677,0))) -> 0 | C84: =IF($A84="","",IF(_xlfn.XLOOKUP($A84,Korrelation!$D$4:$D$1197,Korrelation!F$4:F$1197,"-",0)="-",0,MATCH(_xlfn.XLOOKUP($A84,Korrelation!$D$4:$D$1197,Korrelation!F$4:F$1197,"",0),DMAV_Modell!$G$6:$G$677,0))) -> 0 | D84: =IF($A84="","",IF(_xlfn.XLOOKUP($A84,Korrelation!$D$4:$D$1197,Korrelation!G$4:G$1197,"-",0)="-",0,MATCH(_xlfn.XLOOKUP($A84,Korrelation!$D$4:$D$1197,Korrelation!G$4:G$1197,"",0),DMAV_Modell!$G$6:$G$677,0))) -> 0 | E84: =IF($A84="","",IF(_xlfn.XLOOKUP($A84,Korrelation!$D$4:$D$1197,Korrelation!H$4:H$1197,"-",0)="-",0,MATCH(_xlfn.XLOOKUP($A84,Korrelation!$D$4:$D$1197,Korrelation!H$4:H$1197,"",0),DMAV_Dienste!$F$6:$F$140,0))) -> 0 | F84: =IF($A84="","",IF(_xlfn.XLOOKUP($A84,Korrelation!$D$4:$D$1197,Korrelation!I$4:I$1197,"-",0)="-",0,MATCH(_xlfn.XLOOKUP($A84,Korrelation!$D$4:$D$1197,Korrelation!I$4:I$1197,"",0),DMAV_Dienste!$F$6:$F$140,0))) -> 0 | G84: =IF($A84="","",IF(_xlfn.XLOOKUP($A84,Korrelation!$D$4:$D$1197,Korrelation!J$4:J$1197,"-",0)="-",0,MATCH(_xlfn.XLOOKUP($A84,Korrelation!$D$4:$D$1197,Korrelation!J$4:J$1197,"",0),DMAV_Dienste!$F$6:$F$140,0))) -> 0 | H84: =IF($A84="","",IF(_xlfn.XLOOKUP($A84,Korrelation!$D$4:$D$1197,Korrelation!K$4:K$1197,"-",0)="-",0,MATCH(_xlfn.XLOOKUP($A84,Korrelation!$D$4:$D$1197,Korrelation!K$4:K$1197,"",0),'DM01-AV-CH'!$A$6:$A$834,0))) -> 40 | J84: {=IF(B84=0,IF(E84=0,"",HYPERLINK("#"&RIGHT(CELL("adresse",OFFSET(DMAV_Dienste!$M$6,E84-1,0)),LEN(CELL("adresse",OFFSET(DMAV_Dienste!$M$6,E84-1,0)))-FIND("]",CELL("adresse",OFFSET(DMAV_Dienste!$M$6,E84-1,0)))),"Dienst")),HYPERLINK("#"&RIGHT(CELL("adresse",OFFSET(DMAV_Modell!$N$6,B84-1,0)),LEN(CELL("adresse",OFFSET(DMAV_Modell!$N$6,B84-1,0)))-FIND("]",CELL("adresse",OFFSET(DMAV_Modell!$N$6,B84-1,0)))),"Modell"))} | K84: {=IF($B84=0,IF($E84=0,"",IF(INDEX(DMAV_Dienste!P$6:P$140,$E84)="","",INDEX(DMAV_Dienste!P$6:P$140,$E84))),IF(INDEX(DMAV_Modell!Q$6:Q$838,$B84)="","",INDEX(DMAV_Modell!Q$6:Q$838,$B84)))} | L84: {=IF($B84=0,IF($E84=0,"",IF(INDEX(DMAV_Dienste!O$6:O$140,$E84)="","",INDEX(DMAV_Dienste!O$6:O$140,$E84))),IF(INDEX(DMAV_Modell!P$6:P$838,$B84)="","",INDEX(DMAV_Modell!P$6:P$838,$B84)))} | M84: {=IF($B84=0,IF($E84=0,"",IF(INDEX(DMAV_Dienste!Q$6:Q$140,$E84)="","",INDEX(DMAV_Dienste!Q$6:Q$140,$E84))),IF(INDEX(DMAV_Modell!R$6:R$838,$B84)="","",INDEX(DMAV_Modell!R$6:R$838,$B84)))} | N84: {=IF($B84=0,IF($E84=0,"",IF(INDEX(DMAV_Dienste!T$6:T$140,$E84)="","",INDEX(DMAV_Dienste!T$6:T$140,$E84))),IF(INDEX(DMAV_Modell!U$6:U$838,$B84)="","",INDEX(DMAV_Modell!U$6:U$838,$B84)))} | O84: {=IF(C84=0,IF(F84=0,"",HYPERLINK("#"&RIGHT(CELL("adresse",OFFSET(DMAV_Dienste!$M$6,F84-1,0)),LEN(CELL("adresse",OFFSET(DMAV_Dienste!$M$6,F84-1,0)))-FIND("]",CELL("adresse",OFFSET(DMAV_Dienste!$M$6,F84-1,0)))),"Structure")),HYPERLINK("#"&RIGHT(CELL("adresse",OFFSET(DMAV_Modell!$N$6,C84-1,0)),LEN(CELL("adresse",OFFSET(DMAV_Modell!$N$6,C84-1,0)))-FIND("]",CELL("adresse",OFFSET(DMAV_Modell!$N$6,C84-1,0)))),"Structure"))} | P84: {=IF(D84=0,IF(G84=0,"",HYPERLINK("#"&RIGHT(CELL("adresse",OFFSET(DMAV_Dienste!$M$6,G84-1,0)),LEN(CELL("adresse",OFFSET(DMAV_Dienste!$M$6,G84-1,0)))-FIND("]",CELL("adresse",OFFSET(DMAV_Dienste!$M$6,G84-1,0)))),"Substructure")),HYPERLINK("#"&RIGHT(CELL("adresse",OFFSET(DMAV_Modell!$N$6,D84-1,0)),LEN(CELL("adresse",OFFSET(DMAV_Modell!$N$6,D84-1,0)))-FIND("]",CELL("adresse",OFFSET(DMAV_Modell!$N$6,D84-1,0)))),"Substructure"))} | AF84: {=IF(H84=0,"",HYPERLINK("#"&RIGHT(CELL("adresse",OFFSET('DM01-AV-CH'!$G$6,H84-1,0)),LEN(CELL("adresse",OFFSET('DM01-AV-CH'!$G$6,H84-1,0)))-FIND("]",CELL("adresse",OFFSET('DM01-AV-CH'!$G$6,H84-1,0)))),"Modell"))} -> Modell | AG84: {=IF($H84=0,"",IF(INDEX('DM01-AV-CH'!G$6:G$834,$H84)="","",INDEX('DM01-AV-CH'!G$6:G$834,$H84)))} -> FixpunkteKategorie1 | AH84: {=IF($H84=0,"",IF(INDEX('DM01-AV-CH'!H$6:H$834,$H84)="","",INDEX('DM01-AV-CH'!H$6:H$834,$H84)))} -> LFP1Nachfuehrung | AI84: {=IF($H84=0,"",IF(INDEX('DM01-AV-CH'!I$6:I$834,$H84)="","",INDEX('DM01-AV-CH'!I$6:I$834,$H84)))} -> Perimeter
A85: 80 | B85: =IF($A85="","",IF(_xlfn.XLOOKUP($A85,Korrelation!$D$4:$D$1197,Korrelation!E$4:E$1197,"-",0)="-",0,MATCH(_xlfn.XLOOKUP($A85,Korrelation!$D$4:$D$1197,Korrelation!E$4:E$1197,"",0),DMAV_Modell!$G$6:$G$677,0))) -> 0 | C85: =IF($A85="","",IF(_xlfn.XLOOKUP($A85,Korrelation!$D$4:$D$1197,Korrelation!F$4:F$1197,"-",0)="-",0,MATCH(_xlfn.XLOOKUP($A85,Korrelation!$D$4:$D$1197,Korrelation!F$4:F$1197,"",0),DMAV_Modell!$G$6:$G$677,0))) -> 0 | D85: =IF($A85="","",IF(_xlfn.XLOOKUP($A85,Korrelation!$D$4:$D$1197,Korrelation!G$4:G$1197,"-",0)="-",0,MATCH(_xlfn.XLOOKUP($A85,Korrelation!$D$4:$D$1197,Korrelation!G$4:G$1197,"",0),DMAV_Modell!$G$6:$G$677,0))) -> 0 | E85: =IF($A85="","",IF(_xlfn.XLOOKUP($A85,Korrelation!$D$4:$D$1197,Korrelation!H$4:H$1197,"-",0)="-",0,MATCH(_xlfn.XLOOKUP($A85,Korrelation!$D$4:$D$1197,Korrelation!H$4:H$1197,"",0),DMAV_Dienste!$F$6:$F$140,0))) -> 0 | F85: =IF($A85="","",IF(_xlfn.XLOOKUP($A85,Korrelation!$D$4:$D$1197,Korrelation!I$4:I$1197,"-",0)="-",0,MATCH(_xlfn.XLOOKUP($A85,Korrelation!$D$4:$D$1197,Korrelation!I$4:I$1197,"",0),DMAV_Dienste!$F$6:$F$140,0))) -> 0 | G85: =IF($A85="","",IF(_xlfn.XLOOKUP($A85,Korrelation!$D$4:$D$1197,Korrelation!J$4:J$1197,"-",0)="-",0,MATCH(_xlfn.XLOOKUP($A85,Korrelation!$D$4:$D$1197,Korrelation!J$4:J$1197,"",0),DMAV_Dienste!$F$6:$F$140,0))) -> 0 | H85: =IF($A85="","",IF(_xlfn.XLOOKUP($A85,Korrelation!$D$4:$D$1197,Korrelation!K$4:K$1197,"-",0)="-",0,MATCH(_xlfn.XLOOKUP($A85,Korrelation!$D$4:$D$1197,Korrelation!K$4:K$1197,"",0),'DM01-AV-CH'!$A$6:$A$834,0))) -> 41 | J85: {=IF(B85=0,IF(E85=0,"",HYPERLINK("#"&RIGHT(CELL("adresse",OFFSET(DMAV_Dienste!$M$6,E85-1,0)),LEN(CELL("adresse",OFFSET(DMAV_Dienste!$M$6,E85-1,0)))-FIND("]",CELL("adresse",OFFSET(DMAV_Dienste!$M$6,E85-1,0)))),"Dienst")),HYPERLINK("#"&RIGHT(CELL("adresse",OFFSET(DMAV_Modell!$N$6,B85-1,0)),LEN(CELL("adresse",OFFSET(DMAV_Modell!$N$6,B85-1,0)))-FIND("]",CELL("adresse",OFFSET(DMAV_Modell!$N$6,B85-1,0)))),"Modell"))} | K85: {=IF($B85=0,IF($E85=0,"",IF(INDEX(DMAV_Dienste!P$6:P$140,$E85)="","",INDEX(DMAV_Dienste!P$6:P$140,$E85))),IF(INDEX(DMAV_Modell!Q$6:Q$838,$B85)="","",INDEX(DMAV_Modell!Q$6:Q$838,$B85)))} | L85: {=IF($B85=0,IF($E85=0,"",IF(INDEX(DMAV_Dienste!O$6:O$140,$E85)="","",INDEX(DMAV_Dienste!O$6:O$140,$E85))),IF(INDEX(DMAV_Modell!P$6:P$838,$B85)="","",INDEX(DMAV_Modell!P$6:P$838,$B85)))} | M85: {=IF($B85=0,IF($E85=0,"",IF(INDEX(DMAV_Dienste!Q$6:Q$140,$E85)="","",INDEX(DMAV_Dienste!Q$6:Q$140,$E85))),IF(INDEX(DMAV_Modell!R$6:R$838,$B85)="","",INDEX(DMAV_Modell!R$6:R$838,$B85)))} | N85: {=IF($B85=0,IF($E85=0,"",IF(INDEX(DMAV_Dienste!T$6:T$140,$E85)="","",INDEX(DMAV_Dienste!T$6:T$140,$E85))),IF(INDEX(DMAV_Modell!U$6:U$838,$B85)="","",INDEX(DMAV_Modell!U$6:U$838,$B85)))} | O85: {=IF(C85=0,IF(F85=0,"",HYPERLINK("#"&RIGHT(CELL("adresse",OFFSET(DMAV_Dienste!$M$6,F85-1,0)),LEN(CELL("adresse",OFFSET(DMAV_Dienste!$M$6,F85-1,0)))-FIND("]",CELL("adresse",OFFSET(DMAV_Dienste!$M$6,F85-1,0)))),"Structure")),HYPERLINK("#"&RIGHT(CELL("adresse",OFFSET(DMAV_Modell!$N$6,C85-1,0)),LEN(CELL("adresse",OFFSET(DMAV_Modell!$N$6,C85-1,0)))-FIND("]",CELL("adresse",OFFSET(DMAV_Modell!$N$6,C85-1,0)))),"Structure"))} | P85: {=IF(D85=0,IF(G85=0,"",HYPERLINK("#"&RIGHT(CELL("adresse",OFFSET(DMAV_Dienste!$M$6,G85-1,0)),LEN(CELL("adresse",OFFSET(DMAV_Dienste!$M$6,G85-1,0)))-FIND("]",CELL("adresse",OFFSET(DMAV_Dienste!$M$6,G85-1,0)))),"Substructure")),HYPERLINK("#"&RIGHT(CELL("adresse",OFFSET(DMAV_Modell!$N$6,D85-1,0)),LEN(CELL("adresse",OFFSET(DMAV_Modell!$N$6,D85-1,0)))-FIND("]",CELL("adresse",OFFSET(DMAV_Modell!$N$6,D85-1,0)))),"Substructure"))} | AB85: FixpunkteKategorie1.LFP1Nachfuehrung.NBIdent = [geltender NBIdent], FixpunkteKategorie1.LFP1Nachfuehrung.Identifikator = Zeitstempel{Format:YYYYMMDDHHMMSS}, FixpunkteKategorie1.LFP1Nachfuehrung.Beschreibung = "Bezug_durch_Dienst", FixpunkteKategorie1.LFP1Nachfuehrung.GueltigerEintrag = Datum | AF85: {=IF(H85=0,"",HYPERLINK("#"&RIGHT(CELL("adresse",OFFSET('DM01-AV-CH'!$G$6,H85-1,0)),LEN(CELL("adresse",OFFSET('DM01-AV-CH'!$G$6,H85-1,0)))-FIND("]",CELL("adresse",OFFSET('DM01-AV-CH'!$G$6,H85-1,0)))),"Modell"))} -> Modell | AG85: {=IF($H85=0,"",IF(INDEX('DM01-AV-CH'!G$6:G$834,$H85)="","",INDEX('DM01-AV-CH'!G$6:G$834,$H85)))} -> FixpunkteKategorie1 | AH85: {=IF($H85=0,"",IF(INDEX('DM01-AV-CH'!H$6:H$834,$H85)="","",INDEX('DM01-AV-CH'!H$6:H$834,$H85)))} -> LFP1Nachfuehrung | AI85: {=IF($H85=0,"",IF(INDEX('DM01-AV-CH'!I$6:I$834,$H85)="","",INDEX('DM01-AV-CH'!I$6:I$834,$H85)))} -> GueltigerEintrag
A86: 81 | B86: =IF($A86="","",IF(_xlfn.XLOOKUP($A86,Korrelation!$D$4:$D$1197,Korrelation!E$4:E$1197,"-",0)="-",0,MATCH(_xlfn.XLOOKUP($A86,Korrelation!$D$4:$D$1197,Korrelation!E$4:E$1197,"",0),DMAV_Modell!$G$6:$G$677,0))) -> 0 | C86: =IF($A86="","",IF(_xlfn.XLOOKUP($A86,Korrelation!$D$4:$D$1197,Korrelation!F$4:F$1197,"-",0)="-",0,MATCH(_xlfn.XLOOKUP($A86,Korrelation!$D$4:$D$1197,Korrelation!F$4:F$1197,"",0),DMAV_Modell!$G$6:$G$677,0))) -> 0 | D86: =IF($A86="","",IF(_xlfn.XLOOKUP($A86,Korrelation!$D$4:$D$1197,Korrelation!G$4:G$1197,"-",0)="-",0,MATCH(_xlfn.XLOOKUP($A86,Korrelation!$D$4:$D$1197,Korrelation!G$4:G$1197,"",0),DMAV_Modell!$G$6:$G$677,0))) -> 0 | E86: =IF($A86="","",IF(_xlfn.XLOOKUP($A86,Korrelation!$D$4:$D$1197,Korrelation!H$4:H$1197,"-",0)="-",0,MATCH(_xlfn.XLOOKUP($A86,Korrelation!$D$4:$D$1197,Korrelation!H$4:H$1197,"",0),DMAV_Dienste!$F$6:$F$140,0))) -> 0 | F86: =IF($A86="","",IF(_xlfn.XLOOKUP($A86,Korrelation!$D$4:$D$1197,Korrelation!I$4:I$1197,"-",0)="-",0,MATCH(_xlfn.XLOOKUP($A86,Korrelation!$D$4:$D$1197,Korrelation!I$4:I$1197,"",0),DMAV_Dienste!$F$6:$F$140,0))) -> 0 | G86: =IF($A86="","",IF(_xlfn.XLOOKUP($A86,Korrelation!$D$4:$D$1197,Korrelation!J$4:J$1197,"-",0)="-",0,MATCH(_xlfn.XLOOKUP($A86,Korrelation!$D$4:$D$1197,Korrelation!J$4:J$1197,"",0),DMAV_Dienste!$F$6:$F$140,0))) -> 0 | H86: =IF($A86="","",IF(_xlfn.XLOOKUP($A86,Korrelation!$D$4:$D$1197,Korrelation!K$4:K$1197,"-",0)="-",0,MATCH(_xlfn.XLOOKUP($A86,Korrelation!$D$4:$D$1197,Korrelation!K$4:K$1197,"",0),'DM01-AV-CH'!$A$6:$A$834,0))) -> 42 | J86: {=IF(B86=0,IF(E86=0,"",HYPERLINK("#"&RIGHT(CELL("adresse",OFFSET(DMAV_Dienste!$M$6,E86-1,0)),LEN(CELL("adresse",OFFSET(DMAV_Dienste!$M$6,E86-1,0)))-FIND("]",CELL("adresse",OFFSET(DMAV_Dienste!$M$6,E86-1,0)))),"Dienst")),HYPERLINK("#"&RIGHT(CELL("adresse",OFFSET(DMAV_Modell!$N$6,B86-1,0)),LEN(CELL("adresse",OFFSET(DMAV_Modell!$N$6,B86-1,0)))-FIND("]",CELL("adresse",OFFSET(DMAV_Modell!$N$6,B86-1,0)))),"Modell"))} | K86: {=IF($B86=0,IF($E86=0,"",IF(INDEX(DMAV_Dienste!P$6:P$140,$E86)="","",INDEX(DMAV_Dienste!P$6:P$140,$E86))),IF(INDEX(DMAV_Modell!Q$6:Q$838,$B86)="","",INDEX(DMAV_Modell!Q$6:Q$838,$B86)))} | L86: {=IF($B86=0,IF($E86=0,"",IF(INDEX(DMAV_Dienste!O$6:O$140,$E86)="","",INDEX(DMAV_Dienste!O$6:O$140,$E86))),IF(INDEX(DMAV_Modell!P$6:P$838,$B86)="","",INDEX(DMAV_Modell!P$6:P$838,$B86)))} | M86: {=IF($B86=0,IF($E86=0,"",IF(INDEX(DMAV_Dienste!Q$6:Q$140,$E86)="","",INDEX(DMAV_Dienste!Q$6:Q$140,$E86))),IF(INDEX(DMAV_Modell!R$6:R$838,$B86)="","",INDEX(DMAV_Modell!R$6:R$838,$B86)))} | N86: {=IF($B86=0,IF($E86=0,"",IF(INDEX(DMAV_Dienste!T$6:T$140,$E86)="","",INDEX(DMAV_Dienste!T$6:T$140,$E86))),IF(INDEX(DMAV_Modell!U$6:U$838,$B86)="","",INDEX(DMAV_Modell!U$6:U$838,$B86)))} | O86: {=IF(C86=0,IF(F86=0,"",HYPERLINK("#"&RIGHT(CELL("adresse",OFFSET(DMAV_Dienste!$M$6,F86-1,0)),LEN(CELL("adresse",OFFSET(DMAV_Dienste!$M$6,F86-1,0)))-FIND("]",CELL("adresse",OFFSET(DMAV_Dienste!$M$6,F86-1,0)))),"Structure")),HYPERLINK("#"&RIGHT(CELL("adresse",OFFSET(DMAV_Modell!$N$6,C86-1,0)),LEN(CELL("adresse",OFFSET(DMAV_Modell!$N$6,C86-1,0)))-FIND("]",CELL("adresse",OFFSET(DMAV_Modell!$N$6,C86-1,0)))),"Structure"))} | P86: {=IF(D86=0,IF(G86=0,"",HYPERLINK("#"&RIGHT(CELL("adresse",OFFSET(DMAV_Dienste!$M$6,G86-1,0)),LEN(CELL("adresse",OFFSET(DMAV_Dienste!$M$6,G86-1,0)))-FIND("]",CELL("adresse",OFFSET(DMAV_Dienste!$M$6,G86-1,0)))),"Substructure")),HYPERLINK("#"&RIGHT(CELL("adresse",OFFSET(DMAV_Modell!$N$6,D86-1,0)),LEN(CELL("adresse",OFFSET(DMAV_Modell!$N$6,D86-1,0)))-FIND("]",CELL("adresse",OFFSET(DMAV_Modell!$N$6,D86-1,0)))),"Substructure"))} | AB86: FixpunkteKategorie1.LFP1Nachfuehrung.NBIdent = [geltender NBIdent], FixpunkteKategorie1.LFP1Nachfuehrung.Identifikator = Zeitstempel{Format:YYYYMMDDHHMMSS}, FixpunkteKategorie1.LFP1Nachfuehrung.Beschreibung = "Bezug_durch_Dienst", FixpunkteKategorie1.LFP1Nachfuehrung.GueltigerEintrag = Datum | AD86: EMPTY | AF86: {=IF(H86=0,"",HYPERLINK("#"&RIGHT(CELL("adresse",OFFSET('DM01-AV-CH'!$G$6,H86-1,0)),LEN(CELL("adresse",OFFSET('DM01-AV-CH'!$G$6,H86-1,0)))-FIND("]",CELL("adresse",OFFSET('DM01-AV-CH'!$G$6,H86-1,0)))),"Modell"))} -> Modell | AG86: {=IF($H86=0,"",IF(INDEX('DM01-AV-CH'!G$6:G$834,$H86)="","",INDEX('DM01-AV-CH'!G$6:G$834,$H86)))} -> FixpunkteKategorie1 | AH86: {=IF($H86=0,"",IF(INDEX('DM01-AV-CH'!H$6:H$834,$H86)="","",INDEX('DM01-AV-CH'!H$6:H$834,$H86)))} -> LFP1Nachfuehrung | AI86: {=IF($H86=0,"",IF(INDEX('DM01-AV-CH'!I$6:I$834,$H86)="","",INDEX('DM01-AV-CH'!I$6:I$834,$H86)))} -> Datum1
A87: 82 | B87: =IF($A87="","",IF(_xlfn.XLOOKUP($A87,Korrelation!$D$4:$D$1197,Korrelation!E$4:E$1197,"-",0)="-",0,MATCH(_xlfn.XLOOKUP($A87,Korrelation!$D$4:$D$1197,Korrelation!E$4:E$1197,"",0),DMAV_Modell!$G$6:$G$677,0))) -> 0 | C87: =IF($A87="","",IF(_xlfn.XLOOKUP($A87,Korrelation!$D$4:$D$1197,Korrelation!F$4:F$1197,"-",0)="-",0,MATCH(_xlfn.XLOOKUP($A87,Korrelation!$D$4:$D$1197,Korrelation!F$4:F$1197,"",0),DMAV_Modell!$G$6:$G$677,0))) -> 0 | D87: =IF($A87="","",IF(_xlfn.XLOOKUP($A87,Korrelation!$D$4:$D$1197,Korrelation!G$4:G$1197,"-",0)="-",0,MATCH(_xlfn.XLOOKUP($A87,Korrelation!$D$4:$D$1197,Korrelation!G$4:G$1197,"",0),DMAV_Modell!$G$6:$G$677,0))) -> 0 | E87: =IF($A87="","",IF(_xlfn.XLOOKUP($A87,Korrelation!$D$4:$D$1197,Korrelation!H$4:H$1197,"-",0)="-",0,MATCH(_xlfn.XLOOKUP($A87,Korrelation!$D$4:$D$1197,Korrelation!H$4:H$1197,"",0),DMAV_Dienste!$F$6:$F$140,0))) -> 0 | F87: =IF($A87="","",IF(_xlfn.XLOOKUP($A87,Korrelation!$D$4:$D$1197,Korrelation!I$4:I$1197,"-",0)="-",0,MATCH(_xlfn.XLOOKUP($A87,Korrelation!$D$4:$D$1197,Korrelation!I$4:I$1197,"",0),DMAV_Dienste!$F$6:$F$140,0))) -> 0 | G87: =IF($A87="","",IF(_xlfn.XLOOKUP($A87,Korrelation!$D$4:$D$1197,Korrelation!J$4:J$1197,"-",0)="-",0,MATCH(_xlfn.XLOOKUP($A87,Korrelation!$D$4:$D$1197,Korrelation!J$4:J$1197,"",0),DMAV_Dienste!$F$6:$F$140,0))) -> 0 | H87: =IF($A87="","",IF(_xlfn.XLOOKUP($A87,Korrelation!$D$4:$D$1197,Korrelation!K$4:K$1197,"-",0)="-",0,MATCH(_xlfn.XLOOKUP($A87,Korrelation!$D$4:$D$1197,Korrelation!K$4:K$1197,"",0),'DM01-AV-CH'!$A$6:$A$834,0))) -> 43 | J87: {=IF(B87=0,IF(E87=0,"",HYPERLINK("#"&RIGHT(CELL("adresse",OFFSET(DMAV_Dienste!$M$6,E87-1,0)),LEN(CELL("adresse",OFFSET(DMAV_Dienste!$M$6,E87-1,0)))-FIND("]",CELL("adresse",OFFSET(DMAV_Dienste!$M$6,E87-1,0)))),"Dienst")),HYPERLINK("#"&RIGHT(CELL("adresse",OFFSET(DMAV_Modell!$N$6,B87-1,0)),LEN(CELL("adresse",OFFSET(DMAV_Modell!$N$6,B87-1,0)))-FIND("]",CELL("adresse",OFFSET(DMAV_Modell!$N$6,B87-1,0)))),"Modell"))} | K87: {=IF($B87=0,IF($E87=0,"",IF(INDEX(DMAV_Dienste!P$6:P$140,$E87)="","",INDEX(DMAV_Dienste!P$6:P$140,$E87))),IF(INDEX(DMAV_Modell!Q$6:Q$838,$B87)="","",INDEX(DMAV_Modell!Q$6:Q$838,$B87)))} | L87: {=IF($B87=0,IF($E87=0,"",IF(INDEX(DMAV_Dienste!O$6:O$140,$E87)="","",INDEX(DMAV_Dienste!O$6:O$140,$E87))),IF(INDEX(DMAV_Modell!P$6:P$838,$B87)="","",INDEX(DMAV_Modell!P$6:P$838,$B87)))} | M87: {=IF($B87=0,IF($E87=0,"",IF(INDEX(DMAV_Dienste!Q$6:Q$140,$E87)="","",INDEX(DMAV_Dienste!Q$6:Q$140,$E87))),IF(INDEX(DMAV_Modell!R$6:R$838,$B87)="","",INDEX(DMAV_Modell!R$6:R$838,$B87)))} | N87: {=IF($B87=0,IF($E87=0,"",IF(INDEX(DMAV_Dienste!T$6:T$140,$E87)="","",INDEX(DMAV_Dienste!T$6:T$140,$E87))),IF(INDEX(DMAV_Modell!U$6:U$838,$B87)="","",INDEX(DMAV_Modell!U$6:U$838,$B87)))} | O87: {=IF(C87=0,IF(F87=0,"",HYPERLINK("#"&RIGHT(CELL("adresse",OFFSET(DMAV_Dienste!$M$6,F87-1,0)),LEN(CELL("adresse",OFFSET(DMAV_Dienste!$M$6,F87-1,0)))-FIND("]",CELL("adresse",OFFSET(DMAV_Dienste!$M$6,F87-1,0)))),"Structure")),HYPERLINK("#"&RIGHT(CELL("adresse",OFFSET(DMAV_Modell!$N$6,C87-1,0)),LEN(CELL("adresse",OFFSET(DMAV_Modell!$N$6,C87-1,0)))-FIND("]",CELL("adresse",OFFSET(DMAV_Modell!$N$6,C87-1,0)))),"Structure"))} | P87: {=IF(D87=0,IF(G87=0,"",HYPERLINK("#"&RIGHT(CELL("adresse",OFFSET(DMAV_Dienste!$M$6,G87-1,0)),LEN(CELL("adresse",OFFSET(DMAV_Dienste!$M$6,G87-1,0)))-FIND("]",CELL("adresse",OFFSET(DMAV_Dienste!$M$6,G87-1,0)))),"Substructure")),HYPERLINK("#"&RIGHT(CELL("adresse",OFFSET(DMAV_Modell!$N$6,D87-1,0)),LEN(CELL("adresse",OFFSET(DMAV_Modell!$N$6,D87-1,0)))-FIND("]",CELL("adresse",OFFSET(DMAV_Modell!$N$6,D87-1,0)))),"Substructure"))} | AF87: {=IF(H87=0,"",HYPERLINK("#"&RIGHT(CELL("adresse",OFFSET('DM01-AV-CH'!$G$6,H87-1,0)),LEN(CELL("adresse",OFFSET('DM01-AV-CH'!$G$6,H87-1,0)))-FIND("]",CELL("adresse",OFFSET('DM01-AV-CH'!$G$6,H87-1,0)))),"Modell"))} -> Modell | AG87: {=IF($H87=0,"",IF(INDEX('DM01-AV-CH'!G$6:G$834,$H87)="","",INDEX('DM01-AV-CH'!G$6:G$834,$H87)))} -> FixpunkteKategorie1 | AH87: {=IF($H87=0,"",IF(INDEX('DM01-AV-CH'!H$6:H$834,$H87)="","",INDEX('DM01-AV-CH'!H$6:H$834,$H87)))} -> LFP1 | AI87: {=IF($H87=0,"",IF(INDEX('DM01-AV-CH'!I$6:I$834,$H87)="","",INDEX('DM01-AV-CH'!I$6:I$834,$H87)))} -> Entstehung
A88: 83 | B88: =IF($A88="","",IF(_xlfn.XLOOKUP($A88,Korrelation!$D$4:$D$1197,Korrelation!E$4:E$1197,"-",0)="-",0,MATCH(_xlfn.XLOOKUP($A88,Korrelation!$D$4:$D$1197,Korrelation!E$4:E$1197,"",0),DMAV_Modell!$G$6:$G$677,0))) -> 0 | C88: =IF($A88="","",IF(_xlfn.XLOOKUP($A88,Korrelation!$D$4:$D$1197,Korrelation!F$4:F$1197,"-",0)="-",0,MATCH(_xlfn.XLOOKUP($A88,Korrelation!$D$4:$D$1197,Korrelation!F$4:F$1197,"",0),DMAV_Modell!$G$6:$G$677,0))) -> 0 | D88: =IF($A88="","",IF(_xlfn.XLOOKUP($A88,Korrelation!$D$4:$D$1197,Korrelation!G$4:G$1197,"-",0)="-",0,MATCH(_xlfn.XLOOKUP($A88,Korrelation!$D$4:$D$1197,Korrelation!G$4:G$1197,"",0),DMAV_Modell!$G$6:$G$677,0))) -> 0 | E88: =IF($A88="","",IF(_xlfn.XLOOKUP($A88,Korrelation!$D$4:$D$1197,Korrelation!H$4:H$1197,"-",0)="-",0,MATCH(_xlfn.XLOOKUP($A88,Korrelation!$D$4:$D$1197,Korrelation!H$4:H$1197,"",0),DMAV_Dienste!$F$6:$F$140,0))) -> 4 | F88: =IF($A88="","",IF(_xlfn.XLOOKUP($A88,Korrelation!$D$4:$D$1197,Korrelation!I$4:I$1197,"-",0)="-",0,MATCH(_xlfn.XLOOKUP($A88,Korrelation!$D$4:$D$1197,Korrelation!I$4:I$1197,"",0),DMAV_Dienste!$F$6:$F$140,0))) -> 0 | G88: =IF($A88="","",IF(_xlfn.XLOOKUP($A88,Korrelation!$D$4:$D$1197,Korrelation!J$4:J$1197,"-",0)="-",0,MATCH(_xlfn.XLOOKUP($A88,Korrelation!$D$4:$D$1197,Korrelation!J$4:J$1197,"",0),DMAV_Dienste!$F$6:$F$140,0))) -> 0 | H88: =IF($A88="","",IF(_xlfn.XLOOKUP($A88,Korrelation!$D$4:$D$1197,Korrelation!K$4:K$1197,"-",0)="-",0,MATCH(_xlfn.XLOOKUP($A88,Korrelation!$D$4:$D$1197,Korrelation!K$4:K$1197,"",0),'DM01-AV-CH'!$A$6:$A$834,0))) -> 44 | J88: {=IF(B88=0,IF(E88=0,"",HYPERLINK("#"&RIGHT(CELL("adresse",OFFSET(DMAV_Dienste!$M$6,E88-1,0)),LEN(CELL("adresse",OFFSET(DMAV_Dienste!$M$6,E88-1,0)))-FIND("]",CELL("adresse",OFFSET(DMAV_Dienste!$M$6,E88-1,0)))),"Dienst")),HYPERLINK("#"&RIGHT(CELL("adresse",OFFSET(DMAV_Modell!$N$6,B88-1,0)),LEN(CELL("adresse",OFFSET(DMAV_Modell!$N$6,B88-1,0)))-FIND("]",CELL("adresse",OFFSET(DMAV_Modell!$N$6,B88-1,0)))),"Modell"))} -> Dienst | K88: {=IF($B88=0,IF($E88=0,"",IF(INDEX(DMAV_Dienste!P$6:P$140,$E88)="","",INDEX(DMAV_Dienste!P$6:P$140,$E88))),IF(INDEX(DMAV_Modell!Q$6:Q$838,$B88)="","",INDEX(DMAV_Modell!Q$6:Q$838,$B88)))} -> CLASS | L88: {=IF($B88=0,IF($E88=0,"",IF(INDEX(DMAV_Dienste!O$6:O$140,$E88)="","",INDEX(DMAV_Dienste!O$6:O$140,$E88))),IF(INDEX(DMAV_Modell!P$6:P$838,$B88)="","",INDEX(DMAV_Modell!P$6:P$838,$B88)))} -> FixpunkteLV | M88: {=IF($B88=0,IF($E88=0,"",IF(INDEX(DMAV_Dienste!Q$6:Q$140,$E88)="","",INDEX(DMAV_Dienste!Q$6:Q$140,$E88))),IF(INDEX(DMAV_Modell!R$6:R$838,$B88)="","",INDEX(DMAV_Modell!R$6:R$838,$B88)))} -> LFP1 | N88: {=IF($B88=0,IF($E88=0,"",IF(INDEX(DMAV_Dienste!T$6:T$140,$E88)="","",INDEX(DMAV_Dienste!T$6:T$140,$E88))),IF(INDEX(DMAV_Modell!U$6:U$838,$B88)="","",INDEX(DMAV_Modell!U$6:U$838,$B88)))} -> NBIDENT | O88: {=IF(C88=0,IF(F88=0,"",HYPERLINK("#"&RIGHT(CELL("adresse",OFFSET(DMAV_Dienste!$M$6,F88-1,0)),LEN(CELL("adresse",OFFSET(DMAV_Dienste!$M$6,F88-1,0)))-FIND("]",CELL("adresse",OFFSET(DMAV_Dienste!$M$6,F88-1,0)))),"Structure")),HYPERLINK("#"&RIGHT(CELL("adresse",OFFSET(DMAV_Modell!$N$6,C88-1,0)),LEN(CELL("adresse",OFFSET(DMAV_Modell!$N$6,C88-1,0)))-FIND("]",CELL("adresse",OFFSET(DMAV_Modell!$N$6,C88-1,0)))),"Structure"))} | P88: {=IF(D88=0,IF(G88=0,"",HYPERLINK("#"&RIGHT(CELL("adresse",OFFSET(DMAV_Dienste!$M$6,G88-1,0)),LEN(CELL("adresse",OFFSET(DMAV_Dienste!$M$6,G88-1,0)))-FIND("]",CELL("adresse",OFFSET(DMAV_Dienste!$M$6,G88-1,0)))),"Substructure")),HYPERLINK("#"&RIGHT(CELL("adresse",OFFSET(DMAV_Modell!$N$6,D88-1,0)),LEN(CELL("adresse",OFFSET(DMAV_Modell!$N$6,D88-1,0)))-FIND("]",CELL("adresse",OFFSET(DMAV_Modell!$N$6,D88-1,0)))),"Substructure"))} | AF88: {=IF(H88=0,"",HYPERLINK("#"&RIGHT(CELL("adresse",OFFSET('DM01-AV-CH'!$G$6,H88-1,0)),LEN(CELL("adresse",OFFSET('DM01-AV-CH'!$G$6,H88-1,0)))-FIND("]",CELL("adresse",OFFSET('DM01-AV-CH'!$G$6,H88-1,0)))),"Modell"))} -> Modell | AG88: {=IF($H88=0,"",IF(INDEX('DM01-AV-CH'!G$6:G$834,$H88)="","",INDEX('DM01-AV-CH'!G$6:G$834,$H88)))} -> FixpunkteKategorie1 | AH88: {=IF($H88=0,"",IF(INDEX('DM01-AV-CH'!H$6:H$834,$H88)="","",INDEX('DM01-AV-CH'!H$6:H$834,$H88)))} -> LFP1 | AI88: {=IF($H88=0,"",IF(INDEX('DM01-AV-CH'!I$6:I$834,$H88)="","",INDEX('DM01-AV-CH'!I$6:I$834,$H88)))} -> NBIdent
A89: 84 | B89: =IF($A89="","",IF(_xlfn.XLOOKUP($A89,Korrelation!$D$4:$D$1197,Korrelation!E$4:E$1197,"-",0)="-",0,MATCH(_xlfn.XLOOKUP($A89,Korrelation!$D$4:$D$1197,Korrelation!E$4:E$1197,"",0),DMAV_Modell!$G$6:$G$677,0))) -> 0 | C89: =IF($A89="","",IF(_xlfn.XLOOKUP($A89,Korrelation!$D$4:$D$1197,Korrelation!F$4:F$1197,"-",0)="-",0,MATCH(_xlfn.XLOOKUP($A89,Korrelation!$D$4:$D$1197,Korrelation!F$4:F$1197,"",0),DMAV_Modell!$G$6:$G$677,0))) -> 0 | D89: =IF($A89="","",IF(_xlfn.XLOOKUP($A89,Korrelation!$D$4:$D$1197,Korrelation!G$4:G$1197,"-",0)="-",0,MATCH(_xlfn.XLOOKUP($A89,Korrelation!$D$4:$D$1197,Korrelation!G$4:G$1197,"",0),DMAV_Modell!$G$6:$G$677,0))) -> 0 | E89: =IF($A89="","",IF(_xlfn.XLOOKUP($A89,Korrelation!$D$4:$D$1197,Korrelation!H$4:H$1197,"-",0)="-",0,MATCH(_xlfn.XLOOKUP($A89,Korrelation!$D$4:$D$1197,Korrelation!H$4:H$1197,"",0),DMAV_Dienste!$F$6:$F$140,0))) -> 5 | F89: =IF($A89="","",IF(_xlfn.XLOOKUP($A89,Korrelation!$D$4:$D$1197,Korrelation!I$4:I$1197,"-",0)="-",0,MATCH(_xlfn.XLOOKUP($A89,Korrelation!$D$4:$D$1197,Korrelation!I$4:I$1197,"",0),DMAV_Dienste!$F$6:$F$140,0))) -> 0 | G89: =IF($A89="","",IF(_xlfn.XLOOKUP($A89,Korrelation!$D$4:$D$1197,Korrelation!J$4:J$1197,"-",0)="-",0,MATCH(_xlfn.XLOOKUP($A89,Korrelation!$D$4:$D$1197,Korrelation!J$4:J$1197,"",0),DMAV_Dienste!$F$6:$F$140,0))) -> 0 | H89: =IF($A89="","",IF(_xlfn.XLOOKUP($A89,Korrelation!$D$4:$D$1197,Korrelation!K$4:K$1197,"-",0)="-",0,MATCH(_xlfn.XLOOKUP($A89,Korrelation!$D$4:$D$1197,Korrelation!K$4:K$1197,"",0),'DM01-AV-CH'!$A$6:$A$834,0))) -> 45 | J89: {=IF(B89=0,IF(E89=0,"",HYPERLINK("#"&RIGHT(CELL("adresse",OFFSET(DMAV_Dienste!$M$6,E89-1,0)),LEN(CELL("adresse",OFFSET(DMAV_Dienste!$M$6,E89-1,0)))-FIND("]",CELL("adresse",OFFSET(DMAV_Dienste!$M$6,E89-1,0)))),"Dienst")),HYPERLINK("#"&RIGHT(CELL("adresse",OFFSET(DMAV_Modell!$N$6,B89-1,0)),LEN(CELL("adresse",OFFSET(DMAV_Modell!$N$6,B89-1,0)))-FIND("]",CELL("adresse",OFFSET(DMAV_Modell!$N$6,B89-1,0)))),"Modell"))} -> Dienst | K89: {=IF($B89=0,IF($E89=0,"",IF(INDEX(DMAV_Dienste!P$6:P$140,$E89)="","",INDEX(DMAV_Dienste!P$6:P$140,$E89))),IF(INDEX(DMAV_Modell!Q$6:Q$838,$B89)="","",INDEX(DMAV_Modell!Q$6:Q$838,$B89)))} -> CLASS | L89: {=IF($B89=0,IF($E89=0,"",IF(INDEX(DMAV_Dienste!O$6:O$140,$E89)="","",INDEX(DMAV_Dienste!O$6:O$140,$E89))),IF(INDEX(DMAV_Modell!P$6:P$838,$B89)="","",INDEX(DMAV_Modell!P$6:P$838,$B89)))} -> FixpunkteLV | M89: {=IF($B89=0,IF($E89=0,"",IF(INDEX(DMAV_Dienste!Q$6:Q$140,$E89)="","",INDEX(DMAV_Dienste!Q$6:Q$140,$E89))),IF(INDEX(DMAV_Modell!R$6:R$838,$B89)="","",INDEX(DMAV_Modell!R$6:R$838,$B89)))} -> LFP1 | N89: {=IF($B89=0,IF($E89=0,"",IF(INDEX(DMAV_Dienste!T$6:T$140,$E89)="","",INDEX(DMAV_Dienste!T$6:T$140,$E89))),IF(INDEX(DMAV_Modell!U$6:U$838,$B89)="","",INDEX(DMAV_Modell!U$6:U$838,$B89)))} -> Nummer | O89: {=IF(C89=0,IF(F89=0,"",HYPERLINK("#"&RIGHT(CELL("adresse",OFFSET(DMAV_Dienste!$M$6,F89-1,0)),LEN(CELL("adresse",OFFSET(DMAV_Dienste!$M$6,F89-1,0)))-FIND("]",CELL("adresse",OFFSET(DMAV_Dienste!$M$6,F89-1,0)))),"Structure")),HYPERLINK("#"&RIGHT(CELL("adresse",OFFSET(DMAV_Modell!$N$6,C89-1,0)),LEN(CELL("adresse",OFFSET(DMAV_Modell!$N$6,C89-1,0)))-FIND("]",CELL("adresse",OFFSET(DMAV_Modell!$N$6,C89-1,0)))),"Structure"))} | P89: {=IF(D89=0,IF(G89=0,"",HYPERLINK("#"&RIGHT(CELL("adresse",OFFSET(DMAV_Dienste!$M$6,G89-1,0)),LEN(CELL("adresse",OFFSET(DMAV_Dienste!$M$6,G89-1,0)))-FIND("]",CELL("adresse",OFFSET(DMAV_Dienste!$M$6,G89-1,0)))),"Substructure")),HYPERLINK("#"&RIGHT(CELL("adresse",OFFSET(DMAV_Modell!$N$6,D89-1,0)),LEN(CELL("adresse",OFFSET(DMAV_Modell!$N$6,D89-1,0)))-FIND("]",CELL("adresse",OFFSET(DMAV_Modell!$N$6,D89-1,0)))),"Substructure"))} | AF89: {=IF(H89=0,"",HYPERLINK("#"&RIGHT(CELL("adresse",OFFSET('DM01-AV-CH'!$G$6,H89-1,0)),LEN(CELL("adresse",OFFSET('DM01-AV-CH'!$G$6,H89-1,0)))-FIND("]",CELL("adresse",OFFSET('DM01-AV-CH'!$G$6,H89-1,0)))),"Modell"))} -> Modell | AG89: {=IF($H89=0,"",IF(INDEX('DM01-AV-CH'!G$6:G$834,$H89)="","",INDEX('DM01-AV-CH'!G$6:G$834,$H89)))} -> FixpunkteKategorie1 | AH89: {=IF($H89=0,"",IF(INDEX('DM01-AV-CH'!H$6:H$834,$H89)="","",INDEX('DM01-AV-CH'!H$6:H$834,$H89)))} -> LFP1 | AI89: {=IF($H89=0,"",IF(INDEX('DM01-AV-CH'!I$6:I$834,$H89)="","",INDEX('DM01-AV-CH'!I$6:I$834,$H89)))} -> Nummer
A90: 85 | B90: =IF($A90="","",IF(_xlfn.XLOOKUP($A90,Korrelation!$D$4:$D$1197,Korrelation!E$4:E$1197,"-",0)="-",0,MATCH(_xlfn.XLOOKUP($A90,Korrelation!$D$4:$D$1197,Korrelation!E$4:E$1197,"",0),DMAV_Modell!$G$6:$G$677,0))) -> 0 | C90: =IF($A90="","",IF(_xlfn.XLOOKUP($A90,Korrelation!$D$4:$D$1197,Korrelation!F$4:F$1197,"-",0)="-",0,MATCH(_xlfn.XLOOKUP($A90,Korrelation!$D$4:$D$1197,Korrelation!F$4:F$1197,"",0),DMAV_Modell!$G$6:$G$677,0))) -> 0 | D90: =IF($A90="","",IF(_xlfn.XLOOKUP($A90,Korrelation!$D$4:$D$1197,Korrelation!G$4:G$1197,"-",0)="-",0,MATCH(_xlfn.XLOOKUP($A90,Korrelation!$D$4:$D$1197,Korrelation!G$4:G$1197,"",0),DMAV_Modell!$G$6:$G$677,0))) -> 0 | E90: =IF($A90="","",IF(_xlfn.XLOOKUP($A90,Korrelation!$D$4:$D$1197,Korrelation!H$4:H$1197,"-",0)="-",0,MATCH(_xlfn.XLOOKUP($A90,Korrelation!$D$4:$D$1197,Korrelation!H$4:H$1197,"",0),DMAV_Dienste!$F$6:$F$140,0))) -> 6 | F90: =IF($A90="","",IF(_xlfn.XLOOKUP($A90,Korrelation!$D$4:$D$1197,Korrelation!I$4:I$1197,"-",0)="-",0,MATCH(_xlfn.XLOOKUP($A90,Korrelation!$D$4:$D$1197,Korrelation!I$4:I$1197,"",0),DMAV_Dienste!$F$6:$F$140,0))) -> 0 | G90: =IF($A90="","",IF(_xlfn.XLOOKUP($A90,Korrelation!$D$4:$D$1197,Korrelation!J$4:J$1197,"-",0)="-",0,MATCH(_xlfn.XLOOKUP($A90,Korrelation!$D$4:$D$1197,Korrelation!J$4:J$1197,"",0),DMAV_Dienste!$F$6:$F$140,0))) -> 0 | H90: =IF($A90="","",IF(_xlfn.XLOOKUP($A90,Korrelation!$D$4:$D$1197,Korrelation!K$4:K$1197,"-",0)="-",0,MATCH(_xlfn.XLOOKUP($A90,Korrelation!$D$4:$D$1197,Korrelation!K$4:K$1197,"",0),'DM01-AV-CH'!$A$6:$A$834,0))) -> 46 | J90: {=IF(B90=0,IF(E90=0,"",HYPERLINK("#"&RIGHT(CELL("adresse",OFFSET(DMAV_Dienste!$M$6,E90-1,0)),LEN(CELL("adresse",OFFSET(DMAV_Dienste!$M$6,E90-1,0)))-FIND("]",CELL("adresse",OFFSET(DMAV_Dienste!$M$6,E90-1,0)))),"Dienst")),HYPERLINK("#"&RIGHT(CELL("adresse",OFFSET(DMAV_Modell!$N$6,B90-1,0)),LEN(CELL("adresse",OFFSET(DMAV_Modell!$N$6,B90-1,0)))-FIND("]",CELL("adresse",OFFSET(DMAV_Modell!$N$6,B90-1,0)))),"Modell"))} -> Dienst | K90: {=IF($B90=0,IF($E90=0,"",IF(INDEX(DMAV_Dienste!P$6:P$140,$E90)="","",INDEX(DMAV_Dienste!P$6:P$140,$E90))),IF(INDEX(DMAV_Modell!Q$6:Q$838,$B90)="","",INDEX(DMAV_Modell!Q$6:Q$838,$B90)))} -> CLASS | L90: {=IF($B90=0,IF($E90=0,"",IF(INDEX(DMAV_Dienste!O$6:O$140,$E90)="","",INDEX(DMAV_Dienste!O$6:O$140,$E90))),IF(INDEX(DMAV_Modell!P$6:P$838,$B90)="","",INDEX(DMAV_Modell!P$6:P$838,$B90)))} -> FixpunkteLV | M90: {=IF($B90=0,IF($E90=0,"",IF(INDEX(DMAV_Dienste!Q$6:Q$140,$E90)="","",INDEX(DMAV_Dienste!Q$6:Q$140,$E90))),IF(INDEX(DMAV_Modell!R$6:R$838,$B90)="","",INDEX(DMAV_Modell!R$6:R$838,$B90)))} -> LFP1 | N90: {=IF($B90=0,IF($E90=0,"",IF(INDEX(DMAV_Dienste!T$6:T$140,$E90)="","",INDEX(DMAV_Dienste!T$6:T$140,$E90))),IF(INDEX(DMAV_Modell!U$6:U$838,$B90)="","",INDEX(DMAV_Modell!U$6:U$838,$B90)))} -> Geometrie | O90: {=IF(C90=0,IF(F90=0,"",HYPERLINK("#"&RIGHT(CELL("adresse",OFFSET(DMAV_Dienste!$M$6,F90-1,0)),LEN(CELL("adresse",OFFSET(DMAV_Dienste!$M$6,F90-1,0)))-FIND("]",CELL("adresse",OFFSET(DMAV_Dienste!$M$6,F90-1,0)))),"Structure")),HYPERLINK("#"&RIGHT(CELL("adresse",OFFSET(DMAV_Modell!$N$6,C90-1,0)),LEN(CELL("adresse",OFFSET(DMAV_Modell!$N$6,C90-1,0)))-FIND("]",CELL("adresse",OFFSET(DMAV_Modell!$N$6,C90-1,0)))),"Structure"))} | P90: {=IF(D90=0,IF(G90=0,"",HYPERLINK("#"&RIGHT(CELL("adresse",OFFSET(DMAV_Dienste!$M$6,G90-1,0)),LEN(CELL("adresse",OFFSET(DMAV_Dienste!$M$6,G90-1,0)))-FIND("]",CELL("adresse",OFFSET(DMAV_Dienste!$M$6,G90-1,0)))),"Substructure")),HYPERLINK("#"&RIGHT(CELL("adresse",OFFSET(DMAV_Modell!$N$6,D90-1,0)),LEN(CELL("adresse",OFFSET(DMAV_Modell!$N$6,D90-1,0)))-FIND("]",CELL("adresse",OFFSET(DMAV_Modell!$N$6,D90-1,0)))),"Substructure"))} | AF90: {=IF(H90=0,"",HYPERLINK("#"&RIGHT(CELL("adresse",OFFSET('DM01-AV-CH'!$G$6,H90-1,0)),LEN(CELL("adresse",OFFSET('DM01-AV-CH'!$G$6,H90-1,0)))-FIND("]",CELL("adresse",OFFSET('DM01-AV-CH'!$G$6,H90-1,0)))),"Modell"))} -> Modell | AG90: {=IF($H90=0,"",IF(INDEX('DM01-AV-CH'!G$6:G$834,$H90)="","",INDEX('DM01-AV-CH'!G$6:G$834,$H90)))} -> FixpunkteKategorie1 | AH90: {=IF($H90=0,"",IF(INDEX('DM01-AV-CH'!H$6:H$834,$H90)="","",INDEX('DM01-AV-CH'!H$6:H$834,$H90)))} -> LFP1 | AI90: {=IF($H90=0,"",IF(INDEX('DM01-AV-CH'!I$6:I$834,$H90)="","",INDEX('DM01-AV-CH'!I$6:I$834,$H90)))} -> Geometrie
A91: 86 | B91: =IF($A91="","",IF(_xlfn.XLOOKUP($A91,Korrelation!$D$4:$D$1197,Korrelation!E$4:E$1197,"-",0)="-",0,MATCH(_xlfn.XLOOKUP($A91,Korrelation!$D$4:$D$1197,Korrelation!E$4:E$1197,"",0),DMAV_Modell!$G$6:$G$677,0))) -> 0 | C91: =IF($A91="","",IF(_xlfn.XLOOKUP($A91,Korrelation!$D$4:$D$1197,Korrelation!F$4:F$1197,"-",0)="-",0,MATCH(_xlfn.XLOOKUP($A91,Korrelation!$D$4:$D$1197,Korrelation!F$4:F$1197,"",0),DMAV_Modell!$G$6:$G$677,0))) -> 0 | D91: =IF($A91="","",IF(_xlfn.XLOOKUP($A91,Korrelation!$D$4:$D$1197,Korrelation!G$4:G$1197,"-",0)="-",0,MATCH(_xlfn.XLOOKUP($A91,Korrelation!$D$4:$D$1197,Korrelation!G$4:G$1197,"",0),DMAV_Modell!$G$6:$G$677,0))) -> 0 | E91: =IF($A91="","",IF(_xlfn.XLOOKUP($A91,Korrelation!$D$4:$D$1197,Korrelation!H$4:H$1197,"-",0)="-",0,MATCH(_xlfn.XLOOKUP($A91,Korrelation!$D$4:$D$1197,Korrelation!H$4:H$1197,"",0),DMAV_Dienste!$F$6:$F$140,0))) -> 7 | F91: =IF($A91="","",IF(_xlfn.XLOOKUP($A91,Korrelation!$D$4:$D$1197,Korrelation!I$4:I$1197,"-",0)="-",0,MATCH(_xlfn.XLOOKUP($A91,Korrelation!$D$4:$D$1197,Korrelation!I$4:I$1197,"",0),DMAV_Dienste!$F$6:$F$140,0))) -> 0 | G91: =IF($A91="","",IF(_xlfn.XLOOKUP($A91,Korrelation!$D$4:$D$1197,Korrelation!J$4:J$1197,"-",0)="-",0,MATCH(_xlfn.XLOOKUP($A91,Korrelation!$D$4:$D$1197,Korrelation!J$4:J$1197,"",0),DMAV_Dienste!$F$6:$F$140,0))) -> 0 | H91: =IF($A91="","",IF(_xlfn.XLOOKUP($A91,Korrelation!$D$4:$D$1197,Korrelation!K$4:K$1197,"-",0)="-",0,MATCH(_xlfn.XLOOKUP($A91,Korrelation!$D$4:$D$1197,Korrelation!K$4:K$1197,"",0),'DM01-AV-CH'!$A$6:$A$834,0))) -> 47 | J91: {=IF(B91=0,IF(E91=0,"",HYPERLINK("#"&RIGHT(CELL("adresse",OFFSET(DMAV_Dienste!$M$6,E91-1,0)),LEN(CELL("adresse",OFFSET(DMAV_Dienste!$M$6,E91-1,0)))-FIND("]",CELL("adresse",OFFSET(DMAV_Dienste!$M$6,E91-1,0)))),"Dienst")),HYPERLINK("#"&RIGHT(CELL("adresse",OFFSET(DMAV_Modell!$N$6,B91-1,0)),LEN(CELL("adresse",OFFSET(DMAV_Modell!$N$6,B91-1,0)))-FIND("]",CELL("adresse",OFFSET(DMAV_Modell!$N$6,B91-1,0)))),"Modell"))} -> Dienst | K91: {=IF($B91=0,IF($E91=0,"",IF(INDEX(DMAV_Dienste!P$6:P$140,$E91)="","",INDEX(DMAV_Dienste!P$6:P$140,$E91))),IF(INDEX(DMAV_Modell!Q$6:Q$838,$B91)="","",INDEX(DMAV_Modell!Q$6:Q$838,$B91)))} -> CLASS | L91: {=IF($B91=0,IF($E91=0,"",IF(INDEX(DMAV_Dienste!O$6:O$140,$E91)="","",INDEX(DMAV_Dienste!O$6:O$140,$E91))),IF(INDEX(DMAV_Modell!P$6:P$838,$B91)="","",INDEX(DMAV_Modell!P$6:P$838,$B91)))} -> FixpunkteLV | M91: {=IF($B91=0,IF($E91=0,"",IF(INDEX(DMAV_Dienste!Q$6:Q$140,$E91)="","",INDEX(DMAV_Dienste!Q$6:Q$140,$E91))),IF(INDEX(DMAV_Modell!R$6:R$838,$B91)="","",INDEX(DMAV_Modell!R$6:R$838,$B91)))} -> LFP1 | N91: {=IF($B91=0,IF($E91=0,"",IF(INDEX(DMAV_Dienste!T$6:T$140,$E91)="","",INDEX(DMAV_Dienste!T$6:T$140,$E91))),IF(INDEX(DMAV_Modell!U$6:U$838,$B91)="","",INDEX(DMAV_Modell!U$6:U$838,$B91)))} -> Hoehengeometrie | O91: {=IF(C91=0,IF(F91=0,"",HYPERLINK("#"&RIGHT(CELL("adresse",OFFSET(DMAV_Dienste!$M$6,F91-1,0)),LEN(CELL("adresse",OFFSET(DMAV_Dienste!$M$6,F91-1,0)))-FIND("]",CELL("adresse",OFFSET(DMAV_Dienste!$M$6,F91-1,0)))),"Structure")),HYPERLINK("#"&RIGHT(CELL("adresse",OFFSET(DMAV_Modell!$N$6,C91-1,0)),LEN(CELL("adresse",OFFSET(DMAV_Modell!$N$6,C91-1,0)))-FIND("]",CELL("adresse",OFFSET(DMAV_Modell!$N$6,C91-1,0)))),"Structure"))} | P91: {=IF(D91=0,IF(G91=0,"",HYPERLINK("#"&RIGHT(CELL("adresse",OFFSET(DMAV_Dienste!$M$6,G91-1,0)),LEN(CELL("adresse",OFFSET(DMAV_Dienste!$M$6,G91-1,0)))-FIND("]",CELL("adresse",OFFSET(DMAV_Dienste!$M$6,G91-1,0)))),"Substructure")),HYPERLINK("#"&RIGHT(CELL("adresse",OFFSET(DMAV_Modell!$N$6,D91-1,0)),LEN(CELL("adresse",OFFSET(DMAV_Modell!$N$6,D91-1,0)))-FIND("]",CELL("adresse",OFFSET(DMAV_Modell!$N$6,D91-1,0)))),"Substructure"))} | AF91: {=IF(H91=0,"",HYPERLINK("#"&RIGHT(CELL("adresse",OFFSET('DM01-AV-CH'!$G$6,H91-1,0)),LEN(CELL("adresse",OFFSET('DM01-AV-CH'!$G$6,H91-1,0)))-FIND("]",CELL("adresse",OFFSET('DM01-AV-CH'!$G$6,H91-1,0)))),"Modell"))} -> Modell | AG91: {=IF($H91=0,"",IF(INDEX('DM01-AV-CH'!G$6:G$834,$H91)="","",INDEX('DM01-AV-CH'!G$6:G$834,$H91)))} -> FixpunkteKategorie1 | AH91: {=IF($H91=0,"",IF(INDEX('DM01-AV-CH'!H$6:H$834,$H91)="","",INDEX('DM01-AV-CH'!H$6:H$834,$H91)))} -> LFP1 | AI91: {=IF($H91=0,"",IF(INDEX('DM01-AV-CH'!I$6:I$834,$H91)="","",INDEX('DM01-AV-CH'!I$6:I$834,$H91)))} -> HoeheGeom
A92: 87 | B92: =IF($A92="","",IF(_xlfn.XLOOKUP($A92,Korrelation!$D$4:$D$1197,Korrelation!E$4:E$1197,"-",0)="-",0,MATCH(_xlfn.XLOOKUP($A92,Korrelation!$D$4:$D$1197,Korrelation!E$4:E$1197,"",0),DMAV_Modell!$G$6:$G$677,0))) -> 0 | C92: =IF($A92="","",IF(_xlfn.XLOOKUP($A92,Korrelation!$D$4:$D$1197,Korrelation!F$4:F$1197,"-",0)="-",0,MATCH(_xlfn.XLOOKUP($A92,Korrelation!$D$4:$D$1197,Korrelation!F$4:F$1197,"",0),DMAV_Modell!$G$6:$G$677,0))) -> 0 | D92: =IF($A92="","",IF(_xlfn.XLOOKUP($A92,Korrelation!$D$4:$D$1197,Korrelation!G$4:G$1197,"-",0)="-",0,MATCH(_xlfn.XLOOKUP($A92,Korrelation!$D$4:$D$1197,Korrelation!G$4:G$1197,"",0),DMAV_Modell!$G$6:$G$677,0))) -> 0 | E92: =IF($A92="","",IF(_xlfn.XLOOKUP($A92,Korrelation!$D$4:$D$1197,Korrelation!H$4:H$1197,"-",0)="-",0,MATCH(_xlfn.XLOOKUP($A92,Korrelation!$D$4:$D$1197,Korrelation!H$4:H$1197,"",0),DMAV_Dienste!$F$6:$F$140,0))) -> 8 | F92: =IF($A92="","",IF(_xlfn.XLOOKUP($A92,Korrelation!$D$4:$D$1197,Korrelation!I$4:I$1197,"-",0)="-",0,MATCH(_xlfn.XLOOKUP($A92,Korrelation!$D$4:$D$1197,Korrelation!I$4:I$1197,"",0),DMAV_Dienste!$F$6:$F$140,0))) -> 0 | G92: =IF($A92="","",IF(_xlfn.XLOOKUP($A92,Korrelation!$D$4:$D$1197,Korrelation!J$4:J$1197,"-",0)="-",0,MATCH(_xlfn.XLOOKUP($A92,Korrelation!$D$4:$D$1197,Korrelation!J$4:J$1197,"",0),DMAV_Dienste!$F$6:$F$140,0))) -> 0 | H92: =IF($A92="","",IF(_xlfn.XLOOKUP($A92,Korrelation!$D$4:$D$1197,Korrelation!K$4:K$1197,"-",0)="-",0,MATCH(_xlfn.XLOOKUP($A92,Korrelation!$D$4:$D$1197,Korrelation!K$4:K$1197,"",0),'DM01-AV-CH'!$A$6:$A$834,0))) -> 48 | J92: {=IF(B92=0,IF(E92=0,"",HYPERLINK("#"&RIGHT(CELL("adresse",OFFSET(DMAV_Dienste!$M$6,E92-1,0)),LEN(CELL("adresse",OFFSET(DMAV_Dienste!$M$6,E92-1,0)))-FIND("]",CELL("adresse",OFFSET(DMAV_Dienste!$M$6,E92-1,0)))),"Dienst")),HYPERLINK("#"&RIGHT(CELL("adresse",OFFSET(DMAV_Modell!$N$6,B92-1,0)),LEN(CELL("adresse",OFFSET(DMAV_Modell!$N$6,B92-1,0)))-FIND("]",CELL("adresse",OFFSET(DMAV_Modell!$N$6,B92-1,0)))),"Modell"))} -> Dienst | K92: {=IF($B92=0,IF($E92=0,"",IF(INDEX(DMAV_Dienste!P$6:P$140,$E92)="","",INDEX(DMAV_Dienste!P$6:P$140,$E92))),IF(INDEX(DMAV_Modell!Q$6:Q$838,$B92)="","",INDEX(DMAV_Modell!Q$6:Q$838,$B92)))} -> CLASS | L92: {=IF($B92=0,IF($E92=0,"",IF(INDEX(DMAV_Dienste!O$6:O$140,$E92)="","",INDEX(DMAV_Dienste!O$6:O$140,$E92))),IF(INDEX(DMAV_Modell!P$6:P$838,$B92)="","",INDEX(DMAV_Modell!P$6:P$838,$B92)))} -> FixpunkteLV | M92: {=IF($B92=0,IF($E92=0,"",IF(INDEX(DMAV_Dienste!Q$6:Q$140,$E92)="","",INDEX(DMAV_Dienste!Q$6:Q$140,$E92))),IF(INDEX(DMAV_Modell!R$6:R$838,$B92)="","",INDEX(DMAV_Modell!R$6:R$838,$B92)))} -> LFP1 | N92: {=IF($B92=0,IF($E92=0,"",IF(INDEX(DMAV_Dienste!T$6:T$140,$E92)="","",INDEX(DMAV_Dienste!T$6:T$140,$E92))),IF(INDEX(DMAV_Modell!U$6:U$838,$B92)="","",INDEX(DMAV_Modell!U$6:U$838,$B92)))} -> Lagegenauigkeit | O92: {=IF(C92=0,IF(F92=0,"",HYPERLINK("#"&RIGHT(CELL("adresse",OFFSET(DMAV_Dienste!$M$6,F92-1,0)),LEN(CELL("adresse",OFFSET(DMAV_Dienste!$M$6,F92-1,0)))-FIND("]",CELL("adresse",OFFSET(DMAV_Dienste!$M$6,F92-1,0)))),"Structure")),HYPERLINK("#"&RIGHT(CELL("adresse",OFFSET(DMAV_Modell!$N$6,C92-1,0)),LEN(CELL("adresse",OFFSET(DMAV_Modell!$N$6,C92-1,0)))-FIND("]",CELL("adresse",OFFSET(DMAV_Modell!$N$6,C92-1,0)))),"Structure"))} | P92: {=IF(D92=0,IF(G92=0,"",HYPERLINK("#"&RIGHT(CELL("adresse",OFFSET(DMAV_Dienste!$M$6,G92-1,0)),LEN(CELL("adresse",OFFSET(DMAV_Dienste!$M$6,G92-1,0)))-FIND("]",CELL("adresse",OFFSET(DMAV_Dienste!$M$6,G92-1,0)))),"Substructure")),HYPERLINK("#"&RIGHT(CELL("adresse",OFFSET(DMAV_Modell!$N$6,D92-1,0)),LEN(CELL("adresse",OFFSET(DMAV_Modell!$N$6,D92-1,0)))-FIND("]",CELL("adresse",OFFSET(DMAV_Modell!$N$6,D92-1,0)))),"Substructure"))} | AF92: {=IF(H92=0,"",HYPERLINK("#"&RIGHT(CELL("adresse",OFFSET('DM01-AV-CH'!$G$6,H92-1,0)),LEN(CELL("adresse",OFFSET('DM01-AV-CH'!$G$6,H92-1,0)))-FIND("]",CELL("adresse",OFFSET('DM01-AV-CH'!$G$6,H92-1,0)))),"Modell"))} -> Modell | AG92: {=IF($H92=0,"",IF(INDEX('DM01-AV-CH'!G$6:G$834,$H92)="","",INDEX('DM01-AV-CH'!G$6:G$834,$H92)))} -> FixpunkteKategorie1 | AH92: {=IF($H92=0,"",IF(INDEX('DM01-AV-CH'!H$6:H$834,$H92)="","",INDEX('DM01-AV-CH'!H$6:H$834,$H92)))} -> LFP1 | AI92: {=IF($H92=0,"",IF(INDEX('DM01-AV-CH'!I$6:I$834,$H92)="","",INDEX('DM01-AV-CH'!I$6:I$834,$H92)))} -> LageGen
A93: 88 | B93: =IF($A93="","",IF(_xlfn.XLOOKUP($A93,Korrelation!$D$4:$D$1197,Korrelation!E$4:E$1197,"-",0)="-",0,MATCH(_xlfn.XLOOKUP($A93,Korrelation!$D$4:$D$1197,Korrelation!E$4:E$1197,"",0),DMAV_Modell!$G$6:$G$677,0))) -> 0 | C93: =IF($A93="","",IF(_xlfn.XLOOKUP($A93,Korrelation!$D$4:$D$1197,Korrelation!F$4:F$1197,"-",0)="-",0,MATCH(_xlfn.XLOOKUP($A93,Korrelation!$D$4:$D$1197,Korrelation!F$4:F$1197,"",0),DMAV_Modell!$G$6:$G$677,0))) -> 0 | D93: =IF($A93="","",IF(_xlfn.XLOOKUP($A93,Korrelation!$D$4:$D$1197,Korrelation!G$4:G$1197,"-",0)="-",0,MATCH(_xlfn.XLOOKUP($A93,Korrelation!$D$4:$D$1197,Korrelation!G$4:G$1197,"",0),DMAV_Modell!$G$6:$G$677,0))) -> 0 | E93: =IF($A93="","",IF(_xlfn.XLOOKUP($A93,Korrelation!$D$4:$D$1197,Korrelation!H$4:H$1197,"-",0)="-",0,MATCH(_xlfn.XLOOKUP($A93,Korrelation!$D$4:$D$1197,Korrelation!H$4:H$1197,"",0),DMAV_Dienste!$F$6:$F$140,0))) -> 9 | F93: =IF($A93="","",IF(_xlfn.XLOOKUP($A93,Korrelation!$D$4:$D$1197,Korrelation!I$4:I$1197,"-",0)="-",0,MATCH(_xlfn.XLOOKUP($A93,Korrelation!$D$4:$D$1197,Korrelation!I$4:I$1197,"",0),DMAV_Dienste!$F$6:$F$140,0))) -> 0 | G93: =IF($A93="","",IF(_xlfn.XLOOKUP($A93,Korrelation!$D$4:$D$1197,Korrelation!J$4:J$1197,"-",0)="-",0,MATCH(_xlfn.XLOOKUP($A93,Korrelation!$D$4:$D$1197,Korrelation!J$4:J$1197,"",0),DMAV_Dienste!$F$6:$F$140,0))) -> 0 | H93: =IF($A93="","",IF(_xlfn.XLOOKUP($A93,Korrelation!$D$4:$D$1197,Korrelation!K$4:K$1197,"-",0)="-",0,MATCH(_xlfn.XLOOKUP($A93,Korrelation!$D$4:$D$1197,Korrelation!K$4:K$1197,"",0),'DM01-AV-CH'!$A$6:$A$834,0))) -> 49 | J93: {=IF(B93=0,IF(E93=0,"",HYPERLINK("#"&RIGHT(CELL("adresse",OFFSET(DMAV_Dienste!$M$6,E93-1,0)),LEN(CELL("adresse",OFFSET(DMAV_Dienste!$M$6,E93-1,0)))-FIND("]",CELL("adresse",OFFSET(DMAV_Dienste!$M$6,E93-1,0)))),"Dienst")),HYPERLINK("#"&RIGHT(CELL("adresse",OFFSET(DMAV_Modell!$N$6,B93-1,0)),LEN(CELL("adresse",OFFSET(DMAV_Modell!$N$6,B93-1,0)))-FIND("]",CELL("adresse",OFFSET(DMAV_Modell!$N$6,B93-1,0)))),"Modell"))} -> Dienst | K93: {=IF($B93=0,IF($E93=0,"",IF(INDEX(DMAV_Dienste!P$6:P$140,$E93)="","",INDEX(DMAV_Dienste!P$6:P$140,$E93))),IF(INDEX(DMAV_Modell!Q$6:Q$838,$B93)="","",INDEX(DMAV_Modell!Q$6:Q$838,$B93)))} -> CLASS | L93: {=IF($B93=0,IF($E93=0,"",IF(INDEX(DMAV_Dienste!O$6:O$140,$E93)="","",INDEX(DMAV_Dienste!O$6:O$140,$E93))),IF(INDEX(DMAV_Modell!P$6:P$838,$B93)="","",INDEX(DMAV_Modell!P$6:P$838,$B93)))} -> FixpunkteLV | M93: {=IF($B93=0,IF($E93=0,"",IF(INDEX(DMAV_Dienste!Q$6:Q$140,$E93)="","",INDEX(DMAV_Dienste!Q$6:Q$140,$E93))),IF(INDEX(DMAV_Modell!R$6:R$838,$B93)="","",INDEX(DMAV_Modell!R$6:R$838,$B93)))} -> LFP1 | N93: {=IF($B93=0,IF($E93=0,"",IF(INDEX(DMAV_Dienste!T$6:T$140,$E93)="","",INDEX(DMAV_Dienste!T$6:T$140,$E93))),IF(INDEX(DMAV_Modell!U$6:U$838,$B93)="","",INDEX(DMAV_Modell!U$6:U$838,$B93)))} -> IstLagezuverlaessig | O93: {=IF(C93=0,IF(F93=0,"",HYPERLINK("#"&RIGHT(CELL("adresse",OFFSET(DMAV_Dienste!$M$6,F93-1,0)),LEN(CELL("adresse",OFFSET(DMAV_Dienste!$M$6,F93-1,0)))-FIND("]",CELL("adresse",OFFSET(DMAV_Dienste!$M$6,F93-1,0)))),"Structure")),HYPERLINK("#"&RIGHT(CELL("adresse",OFFSET(DMAV_Modell!$N$6,C93-1,0)),LEN(CELL("adresse",OFFSET(DMAV_Modell!$N$6,C93-1,0)))-FIND("]",CELL("adresse",OFFSET(DMAV_Modell!$N$6,C93-1,0)))),"Structure"))} | P93: {=IF(D93=0,IF(G93=0,"",HYPERLINK("#"&RIGHT(CELL("adresse",OFFSET(DMAV_Dienste!$M$6,G93-1,0)),LEN(CELL("adresse",OFFSET(DMAV_Dienste!$M$6,G93-1,0)))-FIND("]",CELL("adresse",OFFSET(DMAV_Dienste!$M$6,G93-1,0)))),"Substructure")),HYPERLINK("#"&RIGHT(CELL("adresse",OFFSET(DMAV_Modell!$N$6,D93-1,0)),LEN(CELL("adresse",OFFSET(DMAV_Modell!$N$6,D93-1,0)))-FIND("]",CELL("adresse",OFFSET(DMAV_Modell!$N$6,D93-1,0)))),"Substructure"))} | AF93: {=IF(H93=0,"",HYPERLINK("#"&RIGHT(CELL("adresse",OFFSET('DM01-AV-CH'!$G$6,H93-1,0)),LEN(CELL("adresse",OFFSET('DM01-AV-CH'!$G$6,H93-1,0)))-FIND("]",CELL("adresse",OFFSET('DM01-AV-CH'!$G$6,H93-1,0)))),"Modell"))} -> Modell | AG93: {=IF($H93=0,"",IF(INDEX('DM01-AV-CH'!G$6:G$834,$H93)="","",INDEX('DM01-AV-CH'!G$6:G$834,$H93)))} -> FixpunkteKategorie1 | AH93: {=IF($H93=0,"",IF(INDEX('DM01-AV-CH'!H$6:H$834,$H93)="","",INDEX('DM01-AV-CH'!H$6:H$834,$H93)))} -> LFP1 | AI93: {=IF($H93=0,"",IF(INDEX('DM01-AV-CH'!I$6:I$834,$H93)="","",INDEX('DM01-AV-CH'!I$6:I$834,$H93)))} -> LageZuv
A94: 89 | B94: =IF($A94="","",IF(_xlfn.XLOOKUP($A94,Korrelation!$D$4:$D$1197,Korrelation!E$4:E$1197,"-",0)="-",0,MATCH(_xlfn.XLOOKUP($A94,Korrelation!$D$4:$D$1197,Korrelation!E$4:E$1197,"",0),DMAV_Modell!$G$6:$G$677,0))) -> 0 | C94: =IF($A94="","",IF(_xlfn.XLOOKUP($A94,Korrelation!$D$4:$D$1197,Korrelation!F$4:F$1197,"-",0)="-",0,MATCH(_xlfn.XLOOKUP($A94,Korrelation!$D$4:$D$1197,Korrelation!F$4:F$1197,"",0),DMAV_Modell!$G$6:$G$677,0))) -> 0 | D94: =IF($A94="","",IF(_xlfn.XLOOKUP($A94,Korrelation!$D$4:$D$1197,Korrelation!G$4:G$1197,"-",0)="-",0,MATCH(_xlfn.XLOOKUP($A94,Korrelation!$D$4:$D$1197,Korrelation!G$4:G$1197,"",0),DMAV_Modell!$G$6:$G$677,0))) -> 0 | E94: =IF($A94="","",IF(_xlfn.XLOOKUP($A94,Korrelation!$D$4:$D$1197,Korrelation!H$4:H$1197,"-",0)="-",0,MATCH(_xlfn.XLOOKUP($A94,Korrelation!$D$4:$D$1197,Korrelation!H$4:H$1197,"",0),DMAV_Dienste!$F$6:$F$140,0))) -> 10 | F94: =IF($A94="","",IF(_xlfn.XLOOKUP($A94,Korrelation!$D$4:$D$1197,Korrelation!I$4:I$1197,"-",0)="-",0,MATCH(_xlfn.XLOOKUP($A94,Korrelation!$D$4:$D$1197,Korrelation!I$4:I$1197,"",0),DMAV_Dienste!$F$6:$F$140,0))) -> 0 | G94: =IF($A94="","",IF(_xlfn.XLOOKUP($A94,Korrelation!$D$4:$D$1197,Korrelation!J$4:J$1197,"-",0)="-",0,MATCH(_xlfn.XLOOKUP($A94,Korrelation!$D$4:$D$1197,Korrelation!J$4:J$1197,"",0),DMAV_Dienste!$F$6:$F$140,0))) -> 0 | H94: =IF($A94="","",IF(_xlfn.XLOOKUP($A94,Korrelation!$D$4:$D$1197,Korrelation!K$4:K$1197,"-",0)="-",0,MATCH(_xlfn.XLOOKUP($A94,Korrelation!$D$4:$D$1197,Korrelation!K$4:K$1197,"",0),'DM01-AV-CH'!$A$6:$A$834,0))) -> 50 | J94: {=IF(B94=0,IF(E94=0,"",HYPERLINK("#"&RIGHT(CELL("adresse",OFFSET(DMAV_Dienste!$M$6,E94-1,0)),LEN(CELL("adresse",OFFSET(DMAV_Dienste!$M$6,E94-1,0)))-FIND("]",CELL("adresse",OFFSET(DMAV_Dienste!$M$6,E94-1,0)))),"Dienst")),HYPERLINK("#"&RIGHT(CELL("adresse",OFFSET(DMAV_Modell!$N$6,B94-1,0)),LEN(CELL("adresse",OFFSET(DMAV_Modell!$N$6,B94-1,0)))-FIND("]",CELL("adresse",OFFSET(DMAV_Modell!$N$6,B94-1,0)))),"Modell"))} -> Dienst | K94: {=IF($B94=0,IF($E94=0,"",IF(INDEX(DMAV_Dienste!P$6:P$140,$E94)="","",INDEX(DMAV_Dienste!P$6:P$140,$E94))),IF(INDEX(DMAV_Modell!Q$6:Q$838,$B94)="","",INDEX(DMAV_Modell!Q$6:Q$838,$B94)))} -> CLASS | L94: {=IF($B94=0,IF($E94=0,"",IF(INDEX(DMAV_Dienste!O$6:O$140,$E94)="","",INDEX(DMAV_Dienste!O$6:O$140,$E94))),IF(INDEX(DMAV_Modell!P$6:P$838,$B94)="","",INDEX(DMAV_Modell!P$6:P$838,$B94)))} -> FixpunkteLV | M94: {=IF($B94=0,IF($E94=0,"",IF(INDEX(DMAV_Dienste!Q$6:Q$140,$E94)="","",INDEX(DMAV_Dienste!Q$6:Q$140,$E94))),IF(INDEX(DMAV_Modell!R$6:R$838,$B94)="","",INDEX(DMAV_Modell!R$6:R$838,$B94)))} -> LFP1 | N94: {=IF($B94=0,IF($E94=0,"",IF(INDEX(DMAV_Dienste!T$6:T$140,$E94)="","",INDEX(DMAV_Dienste!T$6:T$140,$E94))),IF(INDEX(DMAV_Modell!U$6:U$838,$B94)="","",INDEX(DMAV_Modell!U$6:U$838,$B94)))} -> Hoehengenauigkeit | O94: {=IF(C94=0,IF(F94=0,"",HYPERLINK("#"&RIGHT(CELL("adresse",OFFSET(DMAV_Dienste!$M$6,F94-1,0)),LEN(CELL("adresse",OFFSET(DMAV_Dienste!$M$6,F94-1,0)))-FIND("]",CELL("adresse",OFFSET(DMAV_Dienste!$M$6,F94-1,0)))),"Structure")),HYPERLINK("#"&RIGHT(CELL("adresse",OFFSET(DMAV_Modell!$N$6,C94-1,0)),LEN(CELL("adresse",OFFSET(DMAV_Modell!$N$6,C94-1,0)))-FIND("]",CELL("adresse",OFFSET(DMAV_Modell!$N$6,C94-1,0)))),"Structure"))} | P94: {=IF(D94=0,IF(G94=0,"",HYPERLINK("#"&RIGHT(CELL("adresse",OFFSET(DMAV_Dienste!$M$6,G94-1,0)),LEN(CELL("adresse",OFFSET(DMAV_Dienste!$M$6,G94-1,0)))-FIND("]",CELL("adresse",OFFSET(DMAV_Dienste!$M$6,G94-1,0)))),"Substructure")),HYPERLINK("#"&RIGHT(CELL("adresse",OFFSET(DMAV_Modell!$N$6,D94-1,0)),LEN(CELL("adresse",OFFSET(DMAV_Modell!$N$6,D94-1,0)))-FIND("]",CELL("adresse",OFFSET(DMAV_Modell!$N$6,D94-1,0)))),"Substructure"))} | AF94: {=IF(H94=0,"",HYPERLINK("#"&RIGHT(CELL("adresse",OFFSET('DM01-AV-CH'!$G$6,H94-1,0)),LEN(CELL("adresse",OFFSET('DM01-AV-CH'!$G$6,H94-1,0)))-FIND("]",CELL("adresse",OFFSET('DM01-AV-CH'!$G$6,H94-1,0)))),"Modell"))} -> Modell | AG94: {=IF($H94=0,"",IF(INDEX('DM01-AV-CH'!G$6:G$834,$H94)="","",INDEX('DM01-AV-CH'!G$6:G$834,$H94)))} -> FixpunkteKategorie1 | AH94: {=IF($H94=0,"",IF(INDEX('DM01-AV-CH'!H$6:H$834,$H94)="","",INDEX('DM01-AV-CH'!H$6:H$834,$H94)))} -> LFP1 | AI94: {=IF($H94=0,"",IF(INDEX('DM01-AV-CH'!I$6:I$834,$H94)="","",INDEX('DM01-AV-CH'!I$6:I$834,$H94)))} -> HoeheGen
